Workbook

Sheet Respuestas de formulario 1
A1: Marca temporal | B1: Dirección de correo electrónico | C1: Nombre OFICIAL y COMPLETO de la institución educativa | D1: codigo unico de escuela (cue) | E1: tipo de institucion educativa y orientacion | F1: Especifique su orientación | G1: tipo de gestion de la institucion educativa | H1: apellido y nombre del/la docente responsable de la visita | I1: Nombre y apellido del/la docente acompañante 1 | J1: Nombre y apellido del/la docente acompañante 2 | K1: Dirección de correo electrónico para recibir resultado de la asignación | L1: ubicacion de la escuela | M1: Barrio/Localidad de la escuela | N1: cantidad de alumnos que asistiran | O1: curso que asistira | P1: Conectividad en la institución | Q1: Acceso a las ciencias exactas y naturales | R1: porcentaje aproximado de estudiantes de familias de bajos recursos | S1: Exprese observaciones o comentarios que considere pertinentes | T1: Turno/s solicitado/s [Turno mañana (9:00 a 12.30 hs.)] | U1: Turno/s solicitado/s [Turno tarde (12.30 a 16:00 hs.)] | V1: turno solicitado | W1: fecha solicitada | X1: CHARLAS [9:30 Redes sociales: la matemática detrás de los "influencers". Rocío Balderrama] | Y1: CHARLAS [11:30 La Biblio junto a... la calculadora. Historias que no hacen historia. Juan Carlos Pedraza] | Z1: CHARLAS [14:00 ¿Cómo hacer ciencia con Twitter? Sofía del Pozo] | AA1: ESTACIONES INTERACTIVAS [9:30] | AB1: ESTACIONES INTERACTIVAS [10:30] | AC1: ESTACIONES INTERACTIVAS [11:30] | AD1: ESTACIONES INTERACTIVAS [13:00] | AE1: ESTACIONES INTERACTIVAS [14:00] | AF1: ESTACIONES INTERACTIVAS [15:00] | AG1: TALLERES [9:30] | AH1: TALLERES [10:30] | AI1: TALLERES [11:30] | AJ1: TALLERES [14:00] | AK1: TALLERES [15:00] | AL1: ARTE MATEMÁTICO [9:30] | AM1: ARTE MATEMÁTICO [10:30] | AN1: ARTE MATEMÁTICO [11:30] | AO1: ARTE MATEMÁTICO [14:00] | AP1: ARTE MATEMÁTICO [15:00] | AQ1: VISITAS GUIADAS TEMÁTICAS [10:30] | AR1: VISITAS GUIADAS TEMÁTICAS [11:30] | AS1: VISITAS GUIADAS TEMÁTICAS [14:00] | AT1: VISITAS GUIADAS TEMÁTICAS [15:00] | AU1: Exprese cualquier aclaración sobre la solicitud de inscripción que facilite la administración de vacantes. | AV1: CHARLAS [9:30 Desorden ordenado, ¡qué caos es esto! Paula Kuna] | AW1: CHARLAS [11:30 ¿Tenés una idea para cambiar el mundo? Primero simulalo. Rodrigo Castro] | AX1: CHARLAS [14:00 Embaldosados Fractales. Ursula Molter] | AY1: ESTACIONES INTERACTIVAS [9:30] | AZ1: ESTACIONES INTERACTIVAS [10:30] | BA1: ESTACIONES INTERACTIVAS [11:30] | BB1: ESTACIONES INTERACTIVAS [13:00] | BC1: ESTACIONES INTERACTIVAS [14:00] | BD1: ESTACIONES INTERACTIVAS [15:00] | BE1: TALLERES [9.30] | BF1: TALLERES [10:30] | BG1: TALLERES [11:30] | BH1: TALLERES [14:00] | BI1: TALLERES [15:00] | BJ1: ARTE MATEMÁTICO [9:30] | BK1: ARTE MATEMÁTICO [10:30] | BL1: ARTE MATEMÁTICO [11:30] | BM1: ARTE MATEMÁTICO [14:00] | BN1: ARTE MATEMÁTICO [15:00] | BO1: VISITA GUIADA [10:30] | BP1: VISITA GUIADA [11:30] | BQ1: VISITA GUIADA [14:00] | BR1: VISITA GUIADA [15:00] | BS1: Exprese cualquier aclaración sobre la solicitud de inscripción que facilite la administración de vacantes. | BT1: CHARLAS [9:30 Geometría proyectiva, fotografía y la final del mundo. Charly Di Fiore] | BU1: CHARLAS [11:30 Detective de datos. Guillermo Solovey] | BV1: CHARLAS [14:00 Datos y deportes. Iván Monardo] | BW1: ESTACIONES INTERACTIVAS [9:30] | BX1: ESTACIONES INTERACTIVAS [10:30] | BY1: ESTACIONES INTERACTIVAS [11:30] | BZ1: ESTACIONES INTERACTIVAS [13:00] | CA1: ESTACIONES INTERACTIVAS [14:00] | CB1: ESTACIONES INTERACTIVAS [15:00] | CC1: TALLERES [9:30] | CD1: TALLERES [10:30 ] | CE1: TALLERES [11:30] | CF1: TALLERES [14:00] | CG1: TALLERES [15:00] | CH1: ARTE MATEMÁTICO [9:30] | CI1: ARTE MATEMÁTICO [10:30] | CJ1: ARTE MATEMÁTICO [11:30] | CK1: ARTE MATEMÁTICO [14:00] | CL1: ARTE MATEMÁTICO [15:00] | CM1: VISITA GUIADA [10:30] | CN1: VISITA GUIADA [11:30] | CO1: VISITA GUIADA [14:00] | CP1: VISITA GUIADA [15:00] | CQ1: Exprese cualquier aclaración sobre la solicitud de inscripción que facilite la administración de vacantes.
A2: 45006.451 | B2: sromio@colegioesquiu.edu.ar | C2: Instituto Esquiu Asociaciòn Civil | D2: 000200976 | E2: 10. Liceos / Normales / Colegios / Institutos de otras orientaciones | F2: Ciencias naturales | G2: Privada | H2: Luis Rovella | I2: Romio Sol | K2: sromio@colegioesquiu.edu.ar | L2: CABA | M2: Belgrano | N2: 19 | O2: 6º Secundaria (Prov.) / 5º Media (CABA) | P2: 5 | Q2: 5 | R2: 0 | T2: Si | U2: No | V2: Jornada simple: sólo turno mañana (9:00 a 12.30 hs.) | W2: Jueves 27/4 | BT2: Si | BU2: No | BV2: No | BW2: No | BX2: Si | BY2: Si | BZ2: No | CA2: No | CB2: No | CC2: No | CD2: Si | CE2: Si | CF2: No | CG2: No | CH2: No | CI2: No | CJ2: No | CK2: No | CL2: No | CM2: No | CN2: No | CO2: No | CP2: No
A3: 45006.454 | B3: sromio@colegioesquiu.edu.ar | C3: Instituto Esquiu Asociaxion civil | D3: 000200976 | E3: 10. Liceos / Normales / Colegios / Institutos de otras orientaciones | F3: Economia y administracion | G3: Privada | H3: Romio Sol | I3: Rovella Luis | K3: sromio@colegioesquiu.edu.ar | L3: CABA | M3: Belgrano | N3: 23 | O3: 6º Secundaria (Prov.) / 5º Media (CABA) | P3: 5 | Q3: 5 | R3: 0 | T3: Si | U3: No | V3: Jornada simple: sólo turno mañana (9:00 a 12.30 hs.) | W3: Jueves 27/4 | BT3: Si | BU3: No | BV3: No | BW3: No | BX3: Si | BY3: Si | BZ3: No | CA3: No | CB3: No | CC3: No | CD3: Si | CE3: Si | CF3: No | CG3: No | CH3: No | CI3: No | CJ3: No | CK3: No | CL3: No | CM3: No | CN3: No | CO3: No | CP3: No
A4: 45003.415 | B4: yesicagambino@cesfj.edu.ar | C4: CENTRO EDUCATIVO SAN FRANCISCO JAVIER (A-136) | D4: 020010000 | E4: 10. Liceos / Normales / Colegios / Institutos de otras orientaciones | F4: Bachiller con orientación en Economía y Administración | G4: Privada | H4: Yesica Paola Gambino | I4: Daniela Menzulio | J4: Marcos Cayol | K4: yesicagambino@cesfj.edu.ar | L4: CABA | M4: Palermo | N4: 15 | O4: 6º Secundaria (Prov.) / 5º Media (CABA) | P4: 3 | Q4: 2 | R4: 40 | S4: Se trata de un colegio parroquial con 100% de subvención estatal. | T4: No | U4: Si | V4: Jornada simple: sólo turno tarde (12.30 a 16:00 hs.) | W4: Jueves 27/4 | BT4: No | BU4: No | BV4: Si | BW4: No | BX4: No | BY4: No | BZ4: No | CA4: Si | CB4: Si | CC4: No | CD4: No | CE4: No | CF4: Si | CG4: Si | CH4: No | CI4: No | CJ4: No | CK4: Si | CL4: Si | CM4: No | CN4: No | CO4: Si | CP4: Si
A5: 45005.552 | B5: roberto.holub@philips.edu.ar | C5: ESCUELA TECNICA PHILIPS ARGENTINA | D5: 020012900 | E5: 5. Técnicas área producción (electromecánica, mecánica, metalurgia, electricidad, automotores, refrigeración, construcciones, maestro mayor de obras, aeronáutica, naval, aviónico, óptico, en geografía matemática) | F5: ELECTROMECANICA | G5: Privada | H5: ROBERTO HOLUB | I5: NATALIA GRIMALDI | J5: FACUNDO ALBERINO | K5: roberto.holub@philips.edu.ar | L5: CABA | M5: COLEGIALES | N5: 29 | O5: 5º Secundaria (Prov.) / 4º Media (CABA) | P5: 5 | Q5: 4 | R5: 0 | T5: Si | U5: No | V5: Jornada simple: sólo turno mañana (9:00 a 12.30 hs.) | W5: Jueves 27/4 | BT5: No | BU5: Si | BV5: No | BW5: No | BX5: Si | BY5: No | BZ5: No | CA5: No | CB5: No | CC5: Si | CD5: No | CE5: No | CF5: No | CG5: No | CH5: No | CI5: No | CJ5: No | CK5: No | CL5: No | CM5: No | CN5: No | CO5: No | CP5: No
A6: 45005.547 | B6: roberto.holub@philips.edu.ar | C6: ESCUELA TECNICA PHILIPS ARGENTINA | D6: 020012900 | E6: 5. Técnicas área producción (electromecánica, mecánica, metalurgia, electricidad, automotores, refrigeración, construcciones, maestro mayor de obras, aeronáutica, naval, aviónico, óptico, en geografía matemática) | F6: ELECTROMECANICA | G6: Privada | H6: ROBERTO HOLUB | I6: NATALIA GRIMALDI | J6: FACUNDO ALBERINO | K6: roberto.holub@philips.edu.ar | L6: CABA | M6: COLEGIALES | N6: 31 | O6: 6º Secundaria (Prov.) / 5º Media (CABA) | P6: 5 | Q6: 4 | R6: 0 | T6: Si | U6: No | V6: Jornada simple: sólo turno mañana (9:00 a 12.30 hs.) | W6: Miércoles 26/4 | AV6: No | AW6: Si | AX6: No | AY6: No | AZ6: Si | BA6: No | BB6: No | BC6: No | BD6: No | BE6: Si | BF6: No | BG6: No | BH6: No | BI6: No | BJ6: No | BK6: No | BL6: No | BM6: No | BN6: No | BO6: No | BP6: No | BQ6: No | BR6: No
A7: 45000.677 | B7: mavisonora@yahoo.com.ar | C7: Colegio 19 Luis Pasteur | D7: 020014300 | E7: 1. Liceos / Normales / Colegios / Institutos orientados en ciencias naturales y/o exactas | F7: Cs Naturales | G7: Estatal | H7: María Virginia Sóñora | I7: PAOLA ARENA | K7: mavisonora@yahoo.com.ar | L7: CABA | M7: Devoto | N7: 25 | O7: 5º Secundaria (Prov.) / 4º Media (CABA) | P7: 3 | Q7: 3 | R7: 80 | T7: Si | U7: No | V7: Jornada simple: sólo turno mañana (9:00 a 12.30 hs.) | W7: Miércoles 26/4 | AV7: No | AW7: Si | AX7: No | AY7: No | AZ7: No | BA7: No | BB7: Si | BC7: No | BD7: No
A8: 45000.68 | B8: mavisonora@yahoo.com.ar | C8: Colegio 19 Luis Pasteur | D8: 020014300 | E8: 1. Liceos / Normales / Colegios / Institutos orientados en ciencias naturales y/o exactas | F8: Cs naturales | G8: Estatal | H8: Mtía Virginia Soñora | I8: Paola Arena | J8: Daniela Bragnolo | K8: mavisonora@yahoo.com.ar | L8: CABA | M8: Devoto | N8: 25 | O8: 5º Secundaria (Prov.) / 4º Media (CABA) | P8: 3 | Q8: 3 | R8: 80 | T8: No | U8: Si | V8: Jornada simple: sólo turno tarde (12.30 a 16:00 hs.) | W8: Miércoles 26/4 | AV8: No | AW8: No | AX8: Si | AY8: No | AZ8: No | BA8: No | BB8: No | BC8: No | BD8: Si
A9: 45001.521 | B9: mariade.castro@bue.edu.ar | C9: Colegio N° 19 DE 17 "Luis Pasteur" | D9: 020014300 | E9: 1. Liceos / Normales / Colegios / Institutos orientados en ciencias naturales y/o exactas | F9: Naturales | G9: Estatal | H9: Ángeles Castro | I9: Verónica Marrano | K9: mariade.castro@bue.edu.ar | L9: CABA | M9: Villa Devoto | N9: 35 | O9: 6º Secundaria (Prov.) / 5º Media (CABA) | P9: 4 | Q9: 1 | R9: 50 | T9: No | U9: Si | V9: Jornada simple: sólo turno tarde (12.30 a 16:00 hs.) | W9: Jueves 27/4 | BT9: No | BU9: Si | BV9: Si | BW9: No | BX9: No | BY9: No | BZ9: Si | CA9: No | CB9: No | CC9: No | CD9: No | CE9: No | CF9: No | CG9: Si | CH9: No | CI9: No | CJ9: No | CK9: No | CL9: Si | CM9: No | CN9: No | CO9: No | CP9: Si
A10: 45005.865 | B10: barrioluis92@gmail.com | C10: ESC. DE COM. Nº 20 DR. JUAN AGUSTIN GARCIA DE 14 | D10: 020015900 | E10: 10. Liceos / Normales / Colegios / Institutos de otras orientaciones | F10: Comercial | G10: Estatal | H10: Luis Octavio Barrio | I10: Mirta Filgueira | K10: barrioluis92@gmail.com | L10: CABA | M10: Paternal | N10: 20 | O10: 6º Secundaria (Prov.) / 5º Media (CABA) | P10: 4 | Q10: 2 | R10: 40 | T10: Si | U10: No | V10: Jornada simple: sólo turno mañana (9:00 a 12.30 hs.) | W10: Miércoles 26/4 | AV10: Si | AW10: Si | AX10: No | AY10: Si | AZ10: Si | BA10: Si | BB10: No | BC10: No | BD10: No | BE10: Si | BF10: Si | BG10: Si | BH10: No | BI10: No | BJ10: No | BK10: No | BL10: No | BM10: No | BN10: No | BO10: Si | BP10: Si | BS10: Actividades prioritarias: 9:30: Desorden ordenado, ¡qué caos es esto! 10:30: ESTACIONES INTERACTIVAS 11:30: VISITA GUIADA
A11: 45006.503 | B11: dekergustavo@gmail.com | C11: Instituto La Candelaria | D11: 020017800 | E11: 10. Liceos / Normales / Colegios / Institutos de otras orientaciones | F11: Economía | G11: Privada | H11: Gustavo Deker | I11: Marcelo Collavino | J11: Soledad Deker | K11: dekergustavo@gmail.com | L11: CABA | M11: Floresta | N11: 35 | O11: 5º Secundaria (Prov.) / 4º Media (CABA) | P11: 3 | Q11: 3 | R11: 5 | T11: Si | U11: No | V11: Jornada simple: sólo turno mañana (9:00 a 12.30 hs.) | W11: Miércoles 26/4 | AV11: Si | AW11: Si | AX11: Si | AY11: Si | AZ11: Si | BA11: Si | BB11: Si | BC11: Si | BD11: Si | BE11: Si | BF11: Si | BG11: Si | BH11: Si | BI11: Si | BJ11: No | BK11: No | BL11: Si | BM11: No | BN11: No | BO11: No | BP11: No | BQ11: No | BR11: No
A12: 45003.486 | B12: romina.angulo@bue.edu.ar | C12: ESCUELA TECNICA Nº12 "LIBERTADOR GRAL. SAN MARTIN" | D12: 020050900 | E12: 2. Técnicas en computación, electrónica, informática | F12: ELECTRONICA | G12: Estatal | H12: ROMINA ANGULO | I12: MICAELA RODRIGUEZ | K12: romina.angulo@bue.edu.ar | L12: CABA | M12: RETIRO | N12: 17 | O12: 5º Secundaria (Prov.) / 4º Media (CABA) | P12: 3 | Q12: 3 | R12: 90 | T12: No | U12: Si | V12: Jornada simple: sólo turno tarde (12.30 a 16:00 hs.) | W12: Martes 25/4 | X12: No | Y12: No | Z12: Si | AA12: No | AB12: No | AC12: No | AD12: Si | AE12: No | AF12: No | AG12: No | AH12: No | AI12: No | AJ12: No | AK12: Si | AL12: No | AM12: No | AN12: No | AO12: Si | AP12: No | AQ12: No | AR12: No | AS12: No | AT12: No
A13: 45002.995 | B13: ceciliadiaz@docentes.sanmaron.edu.ar | C13: INSTITUTO SAN MARON | D13: 020056200 | E13: 9. Liceos / Normales / Colegios / Institutos orientados en ciencias sociales y/o humanidades | F13: Sociales y Humanidades | G13: Privada | H13: Cecilia Díaz | I13: Marcela Urbano | K13: ceciliadiaz@docentes.sanmaron.edu.ar | L13: CABA | M13: Retiro | N13: 25 | O13: 6º Secundaria (Prov.) / 5º Media (CABA) | P13: 4 | Q13: 3 | R13: 8 | T13: Si | U13: No | V13: Jornada simple: sólo turno mañana (9:00 a 12.30 hs.) | W13: Martes 25/4 | X13: Si | Y13: No | Z13: No | AA13: No | AB13: No | AC13: No | AD13: Si | AE13: No | AF13: No | AG13: No | AH13: Si | AI13: No | AJ13: No | AK13: No | AL13: No | AM13: No | AN13: Si | AO13: No | AP13: No | AQ13: No | AR13: No | AS13: No | AT13: No
A14: 45000.83 | B14: rodrical85@hotmail.com | C14: INSTITUTO COLEGIO DE NUESTRA SEÑORA | D14: 020056500 | E14: 10. Liceos / Normales / Colegios / Institutos de otras orientaciones | F14: Informática | G14: Privada | H14: Ana María Rodríguez | I14: Laura López | J14: Maria Esther Fabbro | K14: rodrical85@hotmail.com | L14: CABA | M14: San Nicolás | N14: 20 | O14: 6º Secundaria (Prov.) / 5º Media (CABA) | P14: 5 | Q14: 4 | R14: 10 | T14: Si | U14: No | V14: Jornada simple: sólo turno mañana (9:00 a 12.30 hs.) | W14: Jueves 27/4 | BT14: Si | BU14: No | BV14: No | BW14: No | BX14: No | BY14: Si | BZ14: No | CA14: No | CB14: No | CC14: No | CD14: Si | CE14: No | CF14: No | CG14: No | CH14: No | CI14: No | CJ14: No | CK14: No | CL14: No | CM14: No | CN14: No | CO14: No | CP14: No
A15: 45001.487 | B15: mbusso@huergo.edu.ar | C15: Instituto industrial Luis A. Huergo | D15: 020056800 | E15: 10. Liceos / Normales / Colegios / Institutos de otras orientaciones | F15: Artes | G15: Privada | H15: María Laura Busso | I15: Gabriela Tarcetti | J15: Carolina Ruggeri | K15: mbusso@huergo.edu.ar | L15: CABA | M15: San Telmo | N15: 32 | O15: 5º Secundaria (Prov.) / 4º Media (CABA) | P15: 4 | Q15: 4 | R15: 0 | T15: Si | U15: No | V15: Jornada simple: sólo turno mañana (9:00 a 12.30 hs.) | W15: Jueves 27/4 | BT15: Si | BU15: No | BV15: No | BW15: No | BX15: No | BY15: No | BZ15: No | CA15: No | CB15: No | CC15: No | CD15: Si | CE15: No | CF15: No | CG15: No | CH15: No | CI15: No | CJ15: Si | CK15: No | CL15: No | CM15: No | CN15: No | CO15: No | CP15: No
A16: 45001.489 | B16: mbusso@huergo.edu.ar | C16: Instituto Huergo | D16: 020056800 | E16: 10. Liceos / Normales / Colegios / Institutos de otras orientaciones | F16: Artes | G16: Privada | H16: María Laura Busso | I16: Gabriela Tarcetti | J16: Carolina Ruggeri | K16: mbusso@huergo.edu.ar | L16: CABA | M16: San Telmo | N16: 32 | O16: 5º Secundaria (Prov.) / 4º Media (CABA) | P16: 4 | Q16: 4 | R16: 0 | T16: Si | U16: No | V16: Jornada simple: sólo turno mañana (9:00 a 12.30 hs.) | W16: Jueves 27/4 | BT16: Si | BU16: No | BV16: No | BW16: No | BX16: No | BY16: No | BZ16: No | CA16: No | CB16: No | CC16: No | CD16: Si | CE16: No | CF16: No | CG16: No | CH16: No | CI16: No | CJ16: Si | CK16: No | CL16: No | CM16: No | CN16: No | CO16: No | CP16: No
A17: 45001.648 | B17: mbusso@huergo.edu.ar | C17: Instituto Huergo | D17: 020056800 | E17: 10. Liceos / Normales / Colegios / Institutos de otras orientaciones | F17: Artes | G17: Privada | H17: María Laura Busso | I17: Gabriela Tarcetti | J17: Carolina Ruggeri | K17: mbusso@huergo.edu.ar | L17: CABA | M17: San Telmo | N17: 30 | O17: 5º Secundaria (Prov.) / 4º Media (CABA) | P17: 4 | Q17: 4 | R17: 0 | S17: Consideramos interesantes las propuestas para lograr, con nuestros estudiantes destacar el vínculo entre la matemática y las artes | T17: Si | U17: No | V17: Jornada simple: sólo turno mañana (9:00 a 12.30 hs.) | W17: Jueves 27/4 | BT17: Si | BU17: No | BV17: No | BW17: No | BX17: No | BY17: No | BZ17: No | CA17: No | CB17: No | CC17: No | CD17: Si | CE17: No | CF17: No | CG17: No | CH17: No | CI17: No | CJ17: Si | CK17: No | CL17: No | CM17: No | CN17: No | CO17: No | CP17: No | CQ17: Consideramos interesantes las propuestas para lograr, con nuestros estudiantes, destacar el vínculo entre la matemática y las artes.
A18: 45004.571 | B18: fbeitia@hotmail.com | C18: INST.EDUC.ARG.NTRA.SRA.DE LUJAN | D18: 020059400 | E18: 10. Liceos / Normales / Colegios / Institutos de otras orientaciones | F18: Bachillerato con orientación en Comunicación Social | G18: Privada | H18: Fernando Beitia | I18: Fernanda Goldaracena | J18: Jéssica Maidana | K18: fbeitia@hotmail.com | L18: CABA | M18: Villa Pueyrredón | N18: 34 | O18: 6º Secundaria (Prov.) / 5º Media (CABA) | P18: 4 | Q18: 4 | R18: 15 | T18: Si | U18: No | V18: Jornada simple: sólo turno mañana (9:00 a 12.30 hs.) | W18: Martes 25/4 | X18: Si | Y18: Si | Z18: No | AA18: No | AB18: Si | AC18: No | AD18: No | AE18: No | AF18: No | AG18: No | AH18: No | AI18: No | AJ18: No | AK18: No | AL18: No | AM18: No | AN18: No | AO18: No | AP18: No | AQ18: No | AR18: No | AS18: No | AT18: No
A19: 45004.573 | B19: fbeitia@hotmail.com | C19: INST.EDUC.ARG.NTRA.SRA.DE LUJAN | D19: 020059400 | E19: 10. Liceos / Normales / Colegios / Institutos de otras orientaciones | F19: Bachillerato con orientación en Economía y Administración | G19: Privada | H19: Jéssica Maidana | I19: Fernanda Goldaracena | J19: Fernando Beitia | K19: fbeitia@hotmail.com | L19: CABA | M19: Villa Pueyrredón | N19: 35 | O19: 6º Secundaria (Prov.) / 5º Media (CABA) | P19: 4 | Q19: 4 | R19: 15 | T19: Si | U19: No | V19: Jornada simple: sólo turno mañana (9:00 a 12.30 hs.) | W19: Martes 25/4 | X19: Si | Y19: Si | Z19: No | AA19: No | AB19: Si | AC19: No | AD19: No | AE19: No | AF19: No | AG19: No | AH19: Si | AI19: No | AJ19: No | AK19: No | AL19: No | AM19: No | AN19: No | AO19: No | AP19: No | AQ19: No | AR19: No | AS19: No | AT19: No
A20: 45004.575 | B20: fbeitia@hotmail.com | C20: INST.EDUC.ARG.NTRA.SRA.DE LUJAN | D20: 020059400 | E20: 10. Liceos / Normales / Colegios / Institutos de otras orientaciones | F20: Bachillerato con orientación en Informática | G20: Privada | H20: Jéssica Maidana | I20: Fernanda Goldaracena | J20: Fernando Beitia | K20: fbeitia@hotmail.com | L20: CABA | M20: Villa Pueyrredón | N20: 33 | O20: 6º Secundaria (Prov.) / 5º Media (CABA) | P20: 4 | Q20: 4 | R20: 15 | T20: Si | U20: No | V20: Jornada simple: sólo turno mañana (9:00 a 12.30 hs.) | W20: Martes 25/4 | X20: Si | Y20: Si | Z20: No | AA20: No | AB20: Si | AC20: No | AD20: No | AE20: No | AF20: No | AG20: No | AH20: Si | AI20: No | AJ20: No | AK20: No | AL20: No | AM20: Si | AN20: No | AO20: No | AP20: No | AQ20: No | AR20: Si | AS20: No | AT20: No
A21: 45001.806 | B21: magalimorelli@misericordia.edu.ar | C21: INST. NUESTRA SEÑORA DE LA MISERICORDIA | D21: 020067300 | E21: 9. Liceos / Normales / Colegios / Institutos orientados en ciencias sociales y/o humanidades | F21: Economía y Administración de Empresas / Comunicación | G21: Privada | H21: Magalí Morelli | I21: Andrea Mortati | J21: Luciana Perea | K21: magalimorelli@misericordia.edu.ar | L21: CABA | M21: Recoleta | N21: 29 | O21: 4º Secundaria (Prov:) / 3º Media (CABA) | P21: 3 | Q21: 3 | R21: 50 | S21: En lo posible que sea el jueves 27/04 que es el día que está la docente de Matemática a cargo del curso. | T21: Si | U21: No | V21: Jornada simple: sólo turno mañana (9:00 a 12.30 hs.) | W21: Jueves 27/4 | BT21: No | BU21: Si | BV21: Si | BW21: Si | BX21: Si | BY21: Si | BZ21: No | CA21: No | CB21: No | CC21: Si | CD21: Si | CE21: Si | CF21: No | CG21: No | CH21: Si | CI21: Si | CJ21: Si | CK21: No | CL21: No | CM21: No | CN21: No | CO21: No | CP21: No
A22: 45001.407 | B22: lucilazobra@beataimelda.org | C22: Instituto Beata Imelda | D22: 020067400 | E22: 9. Liceos / Normales / Colegios / Institutos orientados en ciencias sociales y/o humanidades | F22: Ciencias Sociales | G22: Privada | H22: Lucila Zobra | I22: Ariel Malatesta | J22: Andrea Chiola | K22: lucilazobra@beataimelda.org | L22: CABA | M22: Villa Urquiza | N22: 30 | O22: 5º Secundaria (Prov.) / 4º Media (CABA) | P22: 4 | Q22: 4 | R22: 20 | T22: Si | U22: No | V22: Jornada simple: sólo turno mañana (9:00 a 12.30 hs.) | W22: Jueves 27/4 | BT22: Si | BU22: No | BV22: No | BW22: No | BX22: Si | BY22: Si | BZ22: No | CA22: No | CB22: No | CC22: No | CD22: Si | CE22: Si | CF22: No | CG22: No | CH22: No | CI22: Si | CJ22: Si | CK22: No | CL22: No | CM22: No | CN22: No | CO22: No | CP22: No
A23: 45001.411 | B23: nivelsecundario@beataimelda.org | C23: Instituto Beata Imelda | D23: 020067400 | E23: 10. Liceos / Normales / Colegios / Institutos de otras orientaciones | F23: Economía y Administración | G23: Privada | H23: Andrea Chiola | I23: Lucila Zobra | J23: Ariel Malatesta | K23: nivelsecundario@beataimelda.org | L23: CABA | M23: Villa Urquiza | N23: 34 | O23: 5º Secundaria (Prov.) / 4º Media (CABA) | P23: 4 | Q23: 4 | R23: 10 | T23: Si | U23: No | V23: Jornada simple: sólo turno mañana (9:00 a 12.30 hs.) | W23: Jueves 27/4 | BT23: Si | BU23: No | BV23: No | BW23: No | BX23: Si | BY23: Si | BZ23: No | CA23: No | CB23: No | CC23: No | CD23: Si | CE23: Si | CF23: No | CG23: No | CH23: No | CI23: Si | CJ23: Si | CK23: No | CL23: No | CM23: No | CN23: No | CO23: No | CP23: No
A24: 45005.589 | B24: rosana.dionisio@bue.edu.ar | C24: ESC. DE COM. N° 33 MAIPU DE 18 -Prof Rosana Dionisio | D24: 020068000 | E24: 10. Liceos / Normales / Colegios / Institutos de otras orientaciones | F24: Administración y economía | G24: Estatal | H24: Dionisio Rosana | I24: Zarlenga Silvina | J24: Zambonini Verónica | K24: rosana.dionisio@bue.edu.ar | L24: CABA | M24: Monte Castro | N24: 35 | O24: 6º Secundaria (Prov.) / 5º Media (CABA) | P24: 4 | Q24: 4 | R24: 40 | T24: Si | U24: No | V24: Jornada simple: sólo turno mañana (9:00 a 12.30 hs.) | W24: Jueves 27/4 | BT24: Si | BU24: No | BV24: No | BW24: No | BX24: Si | BY24: No | BZ24: No | CA24: No | CB24: No | CC24: No | CD24: No | CE24: Si | CF24: No | CG24: No | CH24: No | CI24: No | CJ24: No | CK24: No | CL24: No | CM24: Si | CN24: Si | CO24: No | CP24: No
A25: 45001.751 | B25: valeria.shuman@bue.edu.ar | C25: Ens 6 Vicente Lopez y PlaneS | D25: 020071700 | E25: 1. Liceos / Normales / Colegios / Institutos orientados en ciencias naturales y/o exactas | F25: Matemática y Fisica | G25: Estatal | H25: Valeria Shuman | I25: Monica Robledo | J25: Kelly Dabek | K25: valeria.shuman@bue.edu.ar | L25: CABA | M25: Palermo | N25: 27 | O25: 6º Secundaria (Prov.) / 5º Media (CABA) | P25: 4 | Q25: 3 | R25: 60 | T25: Si | U25: No | V25: Jornada simple: sólo turno mañana (9:00 a 12.30 hs.) | W25: Miércoles 26/4 | AV25: Si | AW25: No | AX25: No | AY25: No | AZ25: Si | BA25: No | BB25: No | BC25: No | BD25: No | BE25: No | BF25: No | BG25: Si | BH25: No | BI25: No | BJ25: No | BK25: No | BL25: Si | BM25: No | BN25: No | BO25: No | BP25: No | BQ25: No | BR25: No
A26: 45005.822 | B26: r.estrella@instcristomaestro.edu.ar | C26: Instituto Cristo Maestro | D26: 020072300 | E26: 2. Técnicas en computación, electrónica, informática | F26: Bachiller en informática | G26: Privada | H26: Silvana Rocío Estrella | I26: Santiago Mollano | J26: Ana Bardauil | K26: r.estrella@instcristomaestro.edu.ar | L26: CABA | M26: CABA Floresta | N26: 25 | O26: 6º Secundaria (Prov.) / 5º Media (CABA) | P26: 4 | Q26: 3 | R26: 40 | T26: Si | U26: Si | V26: Jornada completa: turno completo (9:00 a 16.00 hs.) | W26: Jueves 27/4 | BT26: Si | BU26: Si | BV26: Si | BW26: No | BX26: Si | BY26: Si | BZ26: Si | CA26: Si | CB26: Si | CC26: No | CD26: Si | CE26: Si | CF26: Si | CG26: Si | CH26: No | CI26: Si | CJ26: Si | CK26: Si | CL26: Si | CM26: Si | CN26: Si | CO26: Si | CP26: Si | CQ26: Todo parece muy interesante , las propuestas con cupo serán enriquecedoras cual sea.
A27: 45002.545 | B27: secretaria.secundaria@sangregorio.edu.ar | C27: Instituto educativo san gregorio el iluminador | D27: 020074000 | E27: 10. Liceos / Normales / Colegios / Institutos de otras orientaciones | F27: Economía y administración | G27: Privada | H27: Adriana Margossian | I27: Adriana Maegossian | J27: Mariana Crespo | K27: secretaria.secundaria@sangregorio.edu.ar | L27: CABA | M27: Palermo | N27: 24 | O27: 6º Secundaria (Prov.) / 5º Media (CABA) | P27: 4 | Q27: 4 | R27: 30 | S27: A pesar de tener la orientación de economía y administración, tenes alumnos interesados en carreras de ciencias exactas y naturales, y desde las materias matematica y química y física fomentamos estas ciencias | T27: Si | U27: No | V27: Jornada simple: sólo turno mañana (9:00 a 12.30 hs.) | W27: Martes 25/4 | X27: Si | Y27: No | Z27: Si | AA27: No | AB27: Si | AC27: Si | AD27: No | AE27: No | AF27: No | AG27: No | AH27: Si | AI27: Si | AJ27: No | AK27: No | AL27: No | AM27: Si | AN27: Si | AO27: No | AP27: No | AQ27: Si | AR27: Si | AS27: No | AT27: No
A28: 45003.74 | B28: secretaria.secundaria@sangregorio.edu.ar | C28: instituto educativo san gregorio el iluminador | D28: 020074000 | E28: 10. Liceos / Normales / Colegios / Institutos de otras orientaciones | F28: Economía y administración | G28: Privada | H28: Adriana Margossian | I28: Adriana Margossian | J28: Mariana crespo | K28: secretaria.secundaria@sangregorio.edu.ar | L28: CABA | M28: Palermo | N28: 25 | O28: 6º Secundaria (Prov.) / 5º Media (CABA) | P28: 4 | Q28: 4 | R28: 30 | S28: A pesar de tener la orientación de economía y administración, tenes alumnos interesados en carreras de ciencias exactas y naturales, y desde las materias matematica y química y física fomentamos estas ciencias | T28: Si | U28: No | V28: Jornada simple: sólo turno mañana (9:00 a 12.30 hs.) | W28: Martes 25/4 | X28: Si | Y28: No | Z28: No | AA28: No | AB28: Si | AC28: Si | AD28: No | AE28: No | AF28: No | AG28: No | AH28: Si | AI28: Si | AJ28: No | AK28: No | AL28: No | AM28: Si | AN28: Si | AO28: No | AP28: No | AQ28: Si | AR28: Si | AS28: No | AT28: No
A29: 45001.377 | B29: mariaa.sosa@bue.edu.ar | C29: Liceo N° 01 Jose Figueroa Alcorta DE 02 | D29: 020074400 | E29: 1. Liceos / Normales / Colegios / Institutos orientados en ciencias naturales y/o exactas | F29: Ciencias Naturales y Exactas | G29: Estatal | H29: Jonathan España | I29: Maria Andrea Sosa | J29: Nicolas Lovece | K29: mariaa.sosa@bue.edu.ar | L29: CABA | M29: Barrio Norte | N29: 40 | O29: 6º Secundaria (Prov.) / 5º Media (CABA) | P29: 4 | Q29: 3 | R29: 80 | T29: Si | U29: Si | V29: Jornada completa: turno completo (9:00 a 16.00 hs.) | W29: Jueves 27/4 | BT29: Si | BU29: Si | BV29: Si | BW29: Si | BX29: Si | BY29: Si | BZ29: Si | CA29: Si | CB29: Si | CC29: Si | CD29: Si | CE29: Si | CF29: Si | CG29: Si | CH29: No | CI29: No | CJ29: No | CK29: No | CL29: No | CM29: Si | CN29: Si | CO29: Si | CP29: Si
A30: 45001.497 | B30: biblioteca@casasantacatalina.com.ar | C30: Instituto Privado Santa Catalina | D30: 020076800 | E30: 3. Técnicas en administración de empresas, administración de las organizaciones, servicios turísticos, multimedios | F30: Administracion | G30: Privada | H30: Paz Rozen | I30: Alicia Mendella | K30: biblioteca@casasantacatalina.com.ar | L30: CABA | M30: Constitucion | N30: 35 | O30: 6º Secundaria (Prov.) / 5º Media (CABA) | P30: 3 | Q30: 2 | R30: 20 | T30: Si | U30: No | V30: Jornada simple: sólo turno mañana (9:00 a 12.30 hs.) | W30: Martes 25/4 | X30: Si | Y30: Si | Z30: No | AA30: Si | AB30: Si | AC30: Si | AD30: No | AE30: No | AF30: No | AG30: Si | AH30: Si | AI30: Si | AJ30: No | AK30: No | AL30: Si | AM30: Si | AN30: Si | AO30: No | AP30: No | AQ30: Si | AR30: Si | AS30: No | AT30: No
A31: 45001.499 | B31: biblioteca@casasantacatalina.com.ar | C31: Instituto privado santa catalina | D31: 020076800 | E31: 10. Liceos / Normales / Colegios / Institutos de otras orientaciones | F31: comunicacion | G31: Privada | H31: paz rozen | I31: alicia mendella | K31: biblioteca@casasantacatalina.com.ar | L31: CABA | M31: constitcion | N31: 35 | O31: 6º Secundaria (Prov.) / 5º Media (CABA) | P31: 3 | Q31: 2 | R31: 20 | T31: Si | U31: No | V31: Jornada simple: sólo turno mañana (9:00 a 12.30 hs.) | W31: Jueves 27/4 | BT31: Si | BU31: Si | BV31: No | BW31: Si | BX31: Si | BY31: Si | BZ31: No | CA31: No | CB31: No | CC31: Si | CD31: Si | CE31: Si | CF31: No | CG31: No | CH31: Si | CI31: Si | CJ31: Si | CK31: No | CL31: No | CM31: Si | CN31: Si | CO31: No | CP31: No
A32: 45002.34 | B32: biblioteca@casasantacatalina.com.ar | C32: Instituto privado santa catalina | D32: 020076800 | E32: 10. Liceos / Normales / Colegios / Institutos de otras orientaciones | F32: Economía y Administración | G32: Privada | H32: Paz Rozen | I32: Alicia Mendella | K32: biblioteca@casasantacatalina.com.ar | L32: CABA | M32: Constitucion | N32: 35 | O32: 6º Secundaria (Prov.) / 5º Media (CABA) | P32: 3 | Q32: 2 | R32: 20 | S32: Este formulario lo complete ayer pero confundi la orientacion del curso. Puse Técnicas en administración de empresas, administración de las organizaciones, servicios turísticos, multimedios en lugar de 10. Liceos / Normales / Colegios / Institutos de otras orientaciones, mil disculpas. | T32: Si | U32: No | V32: Jornada simple: sólo turno mañana (9:00 a 12.30 hs.) | W32: Martes 25/4 | X32: Si | Y32: Si | Z32: No | AA32: Si | AB32: Si | AC32: Si | AD32: No | AE32: No | AF32: No | AG32: Si | AH32: Si | AI32: Si | AJ32: No | AK32: No | AL32: Si | AM32: Si | AN32: Si | AO32: No | AP32: No | AQ32: Si | AR32: Si | AS32: No | AT32: No
A33: 45002.736 | B33: lulizobra@gmail.com | C33: Colegio San Francisco Coll | D33: 020078500 | E33: 10. Liceos / Normales / Colegios / Institutos de otras orientaciones | F33: Economía y Administración | G33: Privada | H33: Lucila Zobra | I33: Silvina Salvia | J33: Macarena Sanguiao | K33: lulizobra@gmail.com | L33: CABA | M33: Villa Urquiza | N33: 31 | O33: 6º Secundaria (Prov.) / 5º Media (CABA) | P33: 4 | Q33: 4 | R33: 25 | T33: Si | U33: No | V33: Jornada simple: sólo turno mañana (9:00 a 12.30 hs.) | W33: Martes 25/4 | X33: Si | Y33: No | Z33: No | AA33: No | AB33: Si | AC33: Si | AD33: No | AE33: No | AF33: No | AG33: No | AH33: Si | AI33: Si | AJ33: No | AK33: No | AL33: No | AM33: Si | AN33: Si | AO33: No | AP33: No | AQ33: No | AR33: No | AS33: No | AT33: No
A34: 45002.738 | B34: sfc.lucilazobra@gmail.com | C34: Colegio San Francisco Coll | D34: 020078500 | E34: 10. Liceos / Normales / Colegios / Institutos de otras orientaciones | F34: Economía y Administración | G34: Privada | H34: Lucila Zobra | I34: Silvina Salvia | J34: Macarena Sanguiao | K34: sfc.lucilazobra@gmail.com | L34: CABA | M34: Villa Urquiza | N34: 34 | O34: 6º Secundaria (Prov.) / 5º Media (CABA) | P34: 4 | Q34: 4 | R34: 25 | T34: Si | U34: No | V34: Jornada simple: sólo turno mañana (9:00 a 12.30 hs.) | W34: Martes 25/4 | X34: Si | Y34: No | Z34: No | AA34: No | AB34: Si | AC34: Si | AD34: No | AE34: No | AF34: No | AG34: No | AH34: Si | AI34: Si | AJ34: No | AK34: No | AL34: No | AM34: Si | AN34: Si | AO34: No | AP34: No | AQ34: No | AR34: No | AS34: No | AT34: No
A35: 45001.757 | B35: carla.spazzali@gmail.com | C35: Instituto Santa María de Nazareth | D35: 020082200 | E35: 10. Liceos / Normales / Colegios / Institutos de otras orientaciones | F35: economía y comunicación | G35: Privada | H35: Carla | I35: Spazzali | J35: Belen Gonzalez | K35: carla.spazzali@gmail.com | L35: CABA | M35: saavedra | N35: 40 | O35: 6º Secundaria (Prov.) / 5º Media (CABA) | P35: 3 | Q35: 3 | R35: 5 | T35: Si | U35: No | V35: Jornada simple: sólo turno mañana (9:00 a 12.30 hs.) | W35: Martes 25/4 | X35: Si | Y35: Si | Z35: No | AA35: Si | AB35: Si | AC35: Si | AD35: No | AE35: No | AF35: No | AG35: Si | AH35: Si | AI35: Si | AJ35: No | AK35: No | AL35: Si | AM35: Si | AN35: Si | AO35: No | AP35: No | AQ35: Si | AR35: Si | AS35: No | AT35: No
A36: 45000.67 | B36: morelli.nicolas.a@gmail.com | C36: Colegio Norbridge | D36: 020082300 | E36: 10. Liceos / Normales / Colegios / Institutos de otras orientaciones | F36: Economía y Administración | G36: Privada | H36: Nicolás Morelli | I36: Liliana Villena | J36: Alejandra Sánchez | K36: morelli.nicolas.a@gmail.com | L36: CABA | M36: Saavedra | N36: 36 | O36: 6º Secundaria (Prov.) / 5º Media (CABA) | P36: 4 | Q36: 4 | R36: 0 | S36: Llevamos todos los años a nuestro 5to año a la Semana De la Matemática y los estudiantes la disfrutan mucho! | T36: Si | U36: No | V36: Jornada simple: sólo turno mañana (9:00 a 12.30 hs.) | W36: Martes 25/4 | X36: Si | Y36: No | Z36: No | AA36: No | AB36: No | AC36: Si | AD36: No | AE36: No | AF36: No | AG36: No | AH36: No | AI36: No | AJ36: No | AK36: No | AL36: No | AM36: No | AN36: Si | AO36: No | AP36: No | AQ36: Si | AR36: No | AS36: No | AT36: No | AU36: Nos gustaría poder hacer la visita guiada ya que el año pasado no pudimos.
A37: 45001.528 | B37: nicolas.morelli@colegionorbridge.edu.ar | C37: Colegio Norbridge | D37: 020082300 | E37: 10. Liceos / Normales / Colegios / Institutos de otras orientaciones | F37: Economía y Administración | G37: Privada | H37: Nicolás Morelli | I37: Liliana Villena | J37: Analía Mezzelani | K37: nicolas.morelli@colegionorbridge.edu.ar | L37: CABA | M37: Saavedra | N37: 35 | O37: 6º Secundaria (Prov.) / 5º Media (CABA) | P37: 5 | Q37: 5 | R37: 0 | S37: Realicé una inscripción para el día martes, y por un problema de agenda de la Rectora me pidió cambiarlo a jueves. Pido por favor desestimar esa inscripción y tomar como válida esta. Vamos todos los años y los chicos disfrutan mucho la experiencia. Gracias por todo el trabajo! | T37: Si | U37: No | V37: Jornada simple: sólo turno mañana (9:00 a 12.30 hs.) | W37: Jueves 27/4 | BT37: Si | BU37: No | BV37: No | BW37: No | BX37: Si | BY37: No | BZ37: No | CA37: No | CB37: No | CC37: No | CD37: No | CE37: No | CF37: No | CG37: No | CH37: No | CI37: Si | CJ37: No | CK37: No | CL37: No | CM37: No | CN37: Si | CO37: No | CP37: No | CQ37: Pido si por favor podemos tener la visita guiada. El año pasado no pudimos tenerla y los chicos se quedaron con muchas ganas de hacerla. Muchas gracias.
A38: 45000.911 | B38: ariadna.rio@bue.edu.ar | C38: ESC. DE COM. Nº 11 DR JOSE PERALTA DE 17 | D38: 020085900 | E38: 10. Liceos / Normales / Colegios / Institutos de otras orientaciones | F38: economía | G38: Estatal | H38: Ariadna Rio | I38: Magdalena aguiar | K38: ariadna.rio@bue.edu.ar | L38: CABA | M38: Villa Devoto CABA | N38: 30 | O38: 5º Secundaria (Prov.) / 4º Media (CABA) | P38: 5 | Q38: 3 | R38: 40 | S38: El porcentaje es estimativo. No tengo los datos. Pero los estudiantes vienen mayormente del barrio ejército de los andes y ese porcentaje es el beneficiario de las becas. | T38: Si | U38: No | V38: Jornada simple: sólo turno mañana (9:00 a 12.30 hs.) | W38: Jueves 27/4 | BT38: Si | BU38: Si | BV38: No | BW38: No | BX38: Si | BY38: No | BZ38: No | CA38: No | CB38: No | CC38: No | CD38: No | CE38: Si | CF38: No | CG38: No | CH38: No | CI38: No | CJ38: Si | CK38: No | CL38: No | CM38: No | CN38: No | CO38: No | CP38: No | CQ38: Marcamos varias opciones porque nos gustan todas y para poder hacer alguna en el horario de 10:30 y otra en el de 11:30 dejamos a criterio de la disponibilidad que tengan
A39: 45003.55 | B39: nariv@misericordiadevoto.edu.ar | C39: Colegio Nuestra Señora de la Misericordia de devoto A-110 | D39: 020086000 | E39: 9. Liceos / Normales / Colegios / Institutos orientados en ciencias sociales y/o humanidades | F39: Humanidades y Cs. Sociales | G39: Privada | H39: Victoria Anahí Nari | I39: Maria Adriana Lopez | J39: Ignacio Gonzalez | K39: nariv@misericordiadevoto.edu.ar | L39: CABA | M39: Devoto | N39: 30 | O39: 6º Secundaria (Prov.) / 5º Media (CABA) | P39: 3 | Q39: 2 | R39: 5 | T39: No | U39: Si | V39: Jornada simple: sólo turno tarde (12.30 a 16:00 hs.) | W39: Miércoles 26/4 | AV39: No | AW39: No | AX39: Si | AY39: No | AZ39: No | BA39: No | BB39: Si | BC39: No | BD39: Si | BE39: No | BF39: No | BG39: No | BH39: No | BI39: Si | BJ39: No | BK39: No | BL39: No | BM39: No | BN39: No | BO39: No | BP39: No | BR39: No
A40: 45003.553 | B40: nariv@misericordiadevoto.edu.ar | C40: Colegio Nuestra Señora de la Misericordia de devoto A-110 | D40: 020086000 | E40: 9. Liceos / Normales / Colegios / Institutos orientados en ciencias sociales y/o humanidades | F40: Humanidades y Cs. Sociales | G40: Privada | H40: Maria Adriana Lopez | I40: Victoria Anahí Nari | J40: Ignacio Gonzalez | K40: nariv@misericordiadevoto.edu.ar | L40: CABA | M40: Devoto | N40: 28 | O40: 6º Secundaria (Prov.) / 5º Media (CABA) | P40: 3 | Q40: 2 | R40: 5 | T40: No | U40: Si | V40: Jornada simple: sólo turno tarde (12.30 a 16:00 hs.) | W40: Miércoles 26/4 | AV40: No | AW40: No | AX40: Si | AY40: No | AZ40: No | BA40: No | BB40: Si | BC40: No | BD40: Si | BE40: No | BF40: No | BG40: No | BH40: No | BI40: Si | BJ40: No | BK40: No | BL40: No | BM40: No | BN40: No | BO40: No | BP40: No | BQ40: No | BR40: No
A41: 45000.77 | B41: natalia.grandal@bue.edu.ar | C41: ENS EN LENGUAS VIVAS Nº 02 MARIANO ACOSTA DE 06 | D41: 020086600 | E41: 9. Liceos / Normales / Colegios / Institutos orientados en ciencias sociales y/o humanidades | F41: Físico-Matemático | G41: Estatal | H41: Natalia Grandal | I41: Clarisa Redin | K41: natalia.grandal@bue.edu.ar | L41: CABA | M41: Balvanera | N41: 10 | O41: 6º Secundaria (Prov.) / 5º Media (CABA) | P41: 4 | Q41: 3 | R41: 30 | T41: Si | U41: Si | V41: Jornada completa: turno completo (9:00 a 16.00 hs.) | W41: Jueves 27/4 | BT41: Si | BU41: No | BV41: Si | BW41: No | BX41: No | BY41: No | BZ41: Si | CA41: No | CB41: No | CC41: No | CD41: No | CE41: Si | CF41: No | CG41: No | CH41: No | CI41: No | CJ41: No | CK41: Si | CL41: Si
A42: 45003.473 | B42: yaninasdiaz86@gmail.com | C42: ENS N°2 "Mariano Acosta" | D42: 020086600 | E42: 1. Liceos / Normales / Colegios / Institutos orientados en ciencias naturales y/o exactas | F42: Normal | G42: Estatal | H42: Diaz Yanina | I42: Falabella Alberto | J42: Tupone Gustavo | K42: yaninasdiaz86@gmail.com | L42: CABA | M42: Balvanera | N42: 35 | O42: 5º Secundaria (Prov.) / 4º Media (CABA) | P42: 4 | Q42: 4 | R42: 10 | T42: Si | U42: No | V42: Jornada simple: sólo turno mañana (9:00 a 12.30 hs.) | W42: Jueves 27/4 | BT42: Si | BU42: No | BV42: No | BW42: No | BX42: Si | BY42: No | BZ42: Si | CA42: No | CB42: No | CC42: No | CD42: Si | CE42: Si | CF42: No | CG42: No | CH42: No | CI42: Si | CJ42: Si | CK42: No | CL42: No | CM42: Si | CN42: Si | CO42: No | CP42: No
A43: 45002.413 | B43: yaninasdiaz86@gmail.com | C43: ENS N°2 "Mariano Acosta" | D43: 020086600 | E43: 1. Liceos / Normales / Colegios / Institutos orientados en ciencias naturales y/o exactas | F43: Normal | G43: Estatal | H43: Diaz Yanina | I43: Redin Clarisa | J43: Grandal Natalia | K43: yaninas.diaz@bue.edu.ar | L43: CABA | M43: Balvanera | N43: 35 | O43: 6º Secundaria (Prov.) / 5º Media (CABA) | P43: 4 | Q43: 4 | R43: 10 | T43: Si | U43: Si | V43: Jornada completa: turno completo (9:00 a 16.00 hs.) | W43: Martes 25/4 | X43: Si | Y43: No | Z43: No | AA43: No | AB43: No | AC43: Si | AD43: Si | AE43: No | AF43: No | AG43: No | AH43: Si | AI43: Si | AJ43: No | AK43: No | AL43: No | AM43: Si | AN43: Si | AO43: No | AP43: No | AQ43: Si | AR43: Si | AS43: No | AT43: No
A44: 45006.425 | B44: marisa_mariani@yahoo.com.ar | C44: INSTITUTO RAUL SCALABRINI ORTIZ | D44: 020086700 | E44: 10. Liceos / Normales / Colegios / Institutos de otras orientaciones | F44: EN ECONOMIA Y AMINISTRACION | G44: Privada | H44: MARISA MARIANI | I44: PATRICIA MIIZRAJI | J44: LAURA VITULLO | K44: marisa_mariani@yahoo.com.ar | L44: CABA | M44: MONSERRAT | N44: 30 | O44: 5º Secundaria (Prov.) / 4º Media (CABA) | P44: 5 | Q44: 4 | R44: 50 | T44: Si | U44: No | V44: Jornada simple: sólo turno mañana (9:00 a 12.30 hs.) | W44: Jueves 27/4 | BT44: Si | BU44: No | BV44: No | BW44: No | BX44: Si | BY44: No | BZ44: No | CA44: No | CB44: No | CC44: No | CD44: No | CE44: No | CF44: No | CG44: No | CH44: No | CI44: No | CJ44: No | CK44: No | CL44: No | CM44: No | CN44: Si | CO44: No | CP44: No
A45: 45006.433 | B45: marisa_mariani@yahoo.com.ar | C45: INSTITUTO RAUL SCALABRINI ORTIZ | D45: 020086700 | E45: 10. Liceos / Normales / Colegios / Institutos de otras orientaciones | F45: EN ECONOMIA Y ADMINISTRACION | G45: Privada | H45: MARISA MARIANI | I45: PATRICIA MIZRAJI | J45: LAURA VITULLO | K45: marisa_mariani@yahoo.com.ar | L45: CABA | M45: MONSERRAT | N45: 30 | O45: 6º Secundaria (Prov.) / 5º Media (CABA) | P45: 5 | Q45: 4 | R45: 50 | T45: Si | U45: No | V45: Jornada simple: sólo turno mañana (9:00 a 12.30 hs.) | W45: Jueves 27/4 | BT45: Si | BU45: No | BV45: No | BW45: No | BX45: Si | BY45: No | BZ45: No | CA45: No | CB45: No | CC45: No | CD45: No | CE45: No | CF45: No | CG45: No | CH45: No | CI45: No | CJ45: No | CK45: No | CL45: No | CM45: No | CN45: Si | CO45: No | CP45: No
A46: 45002.772 | B46: maria.chiodini@bue.edu.ar | C46: ESC. TEC. Nº 24 DEFENSA DE BUENOS AIRES DE 17 | D46: 020090300 | E46: 2. Técnicas en computación, electrónica, informática | F46: Computación | G46: Estatal | H46: Chiodini María Teresa | I46: Sinisi Carina | J46: Ciriza Lilian | K46: maria.chiodini@bue.edu.ar | L46: CABA | M46: Villa del parque/CABA | N46: 30 | O46: 5º Secundaria (Prov.) / 4º Media (CABA) | P46: 4 | Q46: 4 | R46: 20 | T46: Si | U46: No | V46: Jornada simple: sólo turno mañana (9:00 a 12.30 hs.) | W46: Jueves 27/4 | BT46: No | BU46: No | BV46: Si | BW46: No | BX46: Si | BY46: Si | BZ46: No | CA46: No | CB46: No | CE46: Si | CH46: Si
A47: 45005.497 | B47: maria.chiodini@bue.edu.ar | C47: ESC. TEC. Nº 24 DEFENSA DE BUENOS AIRES DE 17 | D47: 020090300 | E47: 2. Técnicas en computación, electrónica, informática | F47: Computación | G47: Estatal | H47: María Teresa Chiodini | I47: Sinisi Carina | J47: Ciriza Lilian | K47: maria.chiodini@bue.edu.ar | L47: CABA | M47: Villa del Parque | N47: 35 | O47: 4º Secundaria (Prov:) / 3º Media (CABA) | P47: 4 | Q47: 4 | R47: 30 | S47: De la pregunta anterior tengo poco conocimiento aproximado | T47: Si | U47: No | V47: Jornada simple: sólo turno mañana (9:00 a 12.30 hs.) | W47: Jueves 27/4 | BT47: No | BU47: No | BV47: No | BW47: No | BX47: Si | BY47: No | BZ47: No | CA47: No | CB47: No | CE47: Si | CH47: Si | CM47: No | CN47: No | CO47: No | CP47: No | CQ47: Si es posible ir con los dos cursos solicitados. Gracias
A48: 45005.502 | B48: maria.chiodini@bue.edu.ar | C48: ESC. TEC. Nº 24 DEFENSA DE BUENOS AIRES DE 17 | D48: 020090300 | E48: 2. Técnicas en computación, electrónica, informática | F48: Computación | G48: Estatal | H48: Chiodini María Teresa | I48: Sinisi Carina | J48: Ciriza Lilian | K48: maria.chiodini@bue.edu.ar | L48: CABA | M48: Villa del Parque | N48: 35 | O48: 5º Secundaria (Prov.) / 4º Media (CABA) | P48: 4 | Q48: 4 | R48: 30 | T48: Si | U48: No | V48: Jornada simple: sólo turno mañana (9:00 a 12.30 hs.) | W48: Jueves 27/4 | BT48: No | BU48: No | BV48: No | BW48: No | BX48: Si | BY48: No | BZ48: No | CA48: No | CB48: No | CE48: Si | CH48: Si | CM48: No | CN48: No | CO48: No | CP48: No | CQ48: Esta inscripción ya la realice el día Viernes 17, pero tuve que modificar cantidad de alumnos. Disculpas
A49: 45005.567 | B49: profececiliamoran@gmail.com | C49: escuela de comercio 32 | D49: 020093000 | E49: 1. Liceos / Normales / Colegios / Institutos orientados en ciencias naturales y/o exactas | F49: Comercial | G49: Estatal | H49: Maria Cecilia Moran Salgueiro | I49: Jimena Montes | J49: Natalia Dangelo | K49: profececiliamoran@gmail.com | L49: CABA | M49: Liniers | N49: 35 | O49: 5º Secundaria (Prov.) / 4º Media (CABA) | P49: 4 | Q49: 3 | R49: 40 | T49: Si | U49: No | V49: Jornada simple: sólo turno mañana (9:00 a 12.30 hs.) | W49: Miércoles 26/4 | AV49: Si | AW49: No | AX49: No | AY49: Si | AZ49: Si | BA49: Si | BB49: No | BC49: No | BD49: No | BE49: Si | BF49: Si | BG49: Si | BH49: No | BI49: No | BJ49: Si | BK49: Si | BL49: Si | BM49: No | BN49: No | BO49: Si | BP49: Si | BQ49: No | BR49: No
A50: 45005.569 | B50: jimemontes@gmail.com | C50: comercial 32 | D50: 020093000 | E50: 1. Liceos / Normales / Colegios / Institutos orientados en ciencias naturales y/o exactas | F50: comercial | G50: Estatal | H50: Jimena Montes | I50: Natalia Dangelo | J50: Maria Salgueiro | K50: jimemontes@gmail.com | L50: CABA | M50: liniers | N50: 35 | O50: 5º Secundaria (Prov.) / 4º Media (CABA) | P50: 3 | Q50: 3 | R50: 40 | T50: Si | U50: No | V50: Jornada simple: sólo turno mañana (9:00 a 12.30 hs.) | W50: Miércoles 26/4 | AV50: Si | AW50: No | AX50: No | AY50: Si | AZ50: Si | BA50: Si | BB50: No | BC50: No | BD50: No | BE50: Si | BF50: Si | BG50: Si | BH50: No | BI50: No | BJ50: Si | BK50: Si | BL50: Si | BM50: No | BN50: No | BO50: Si | BP50: Si | BQ50: No | BR50: No
A51: 45000.682 | B51: reboiras.juan@colegioesclavas.edu.ar | C51: Instituto Esclavas del Sagrado Corazón de Jesús (A-14) | D51: 020094900 | E51: 1. Liceos / Normales / Colegios / Institutos orientados en ciencias naturales y/o exactas | F51: Ciencias Naturales | G51: Privada | H51: Juan Martín Reboiras | I51: Patricia Julia Castro | K51: reboiras.juan@colegioesclavas.edu.ar | L51: CABA | M51: Belgrano | N51: 30 | O51: 6º Secundaria (Prov.) / 5º Media (CABA) | P51: 2 | Q51: 3 | R51: 0 | T51: Si | U51: Si | V51: Jornada completa: turno completo (9:00 a 16.00 hs.) | W51: Jueves 27/4 | BT51: Si | BU51: Si | BV51: Si | BW51: Si | BX51: Si | BY51: Si | BZ51: Si | CA51: Si | CB51: Si | CC51: Si | CD51: Si | CE51: Si | CF51: Si | CG51: Si | CH51: Si | CI51: Si | CJ51: Si | CK51: Si | CL51: Si | CM51: Si | CN51: Si | CO51: Si | CP51: Si
A52: 45000.728 | B52: profelaueltaller@gmail.com | C52: Instituto secundario El Taller | D52: 020095800 | E52: 10. Liceos / Normales / Colegios / Institutos de otras orientaciones | F52: Comunicación | G52: Privada | H52: María Laura Busso | I52: Rosana Prieto | J52: Carolina Puente | K52: profelaueltaller@gmail.com | L52: CABA | M52: Boedo | N52: 32 | O52: 6º Secundaria (Prov.) / 5º Media (CABA) | P52: 4 | Q52: 1 | R52: 0 | S52: Nos resultan interesantes las actividades para luego llevarlas al aula y trabajarlas para la muestra anual del colegio. | T52: Si | U52: No | V52: Jornada simple: sólo turno mañana (9:00 a 12.30 hs.) | W52: Miércoles 26/4 | AV52: No | AW52: Si | AX52: No | AY52: Si | AZ52: No | BA52: No | BB52: No | BC52: No | BD52: No | BE52: Si | BF52: Si | BG52: Si | BH52: No | BI52: No | BJ52: Si | BK52: Si | BL52: Si | BM52: Si | BN52: Si | BO52: No | BP52: No | BQ52: No | BR52: No
A53: 45001.588 | B53: mmcannilla@gmail.com | C53: COLEGIO LINCOLN | D53: 020097800 | E53: 10. Liceos / Normales / Colegios / Institutos de otras orientaciones | F53: Bachiller Bilingue con Orientación en letras y ciencias sociales | G53: Privada | H53: María Marta Cannilla | I53: Guadalupe Rosso | J53: Mercedes Álvarez | K53: mmcannilla@gmail.com | L53: CABA | M53: Belgrano | N53: 33 | O53: 6º Secundaria (Prov.) / 5º Media (CABA) | P53: 5 | Q53: 5 | R53: 0 | T53: Si | U53: No | V53: Jornada simple: sólo turno mañana (9:00 a 12.30 hs.) | W53: Martes 25/4 | X53: Si | Y53: No | Z53: No | AA53: No | AB53: Si | AC53: Si | AD53: No | AE53: No | AF53: No | AG53: No | AH53: No | AI53: No | AJ53: No | AK53: No | AL53: No | AM53: Si | AN53: Si | AO53: No | AP53: No | AQ53: No | AR53: No | AS53: No | AT53: No
A54: 45002.352 | B54: ciademaria_nivelmedio@yahoo.com.ar | C54: Instituto Compañía de María | D54: 020099900 | E54: 3. Técnicas en administración de empresas, administración de las organizaciones, servicios turísticos, multimedios | F54: Bachiller en Economía y Administración | G54: Privada | H54: Mara Barbagallo | I54: Claudia Vezzaro | J54: Guadalupe Carrillo | K54: ciademaria_nivelmedio@yahoo.com.ar | L54: CABA | M54: Colegiales | N54: 26 | O54: 6º Secundaria (Prov.) / 5º Media (CABA) | P54: 4 | Q54: 5 | R54: 1 | T54: Si | U54: No | V54: Jornada simple: sólo turno mañana (9:00 a 12.30 hs.) | W54: Martes 25/4 | X54: Si | Y54: No | Z54: No | AA54: No | AB54: Si | AC54: No | AD54: No | AE54: No | AF54: No | AG54: No | AH54: No | AI54: Si | AJ54: No | AK54: No | AL54: No | AM54: No | AN54: Si | AO54: No | AP54: No
A55: 45002.494 | B55: ciademaria_nivelmedio@yahoo.com.ar | C55: Instituto Compañía de María | D55: 020099900 | E55: 9. Liceos / Normales / Colegios / Institutos orientados en ciencias sociales y/o humanidades | F55: Bachiller en Humanidades y Ciencias Sociales | G55: Privada | H55: Mara Barbagallo | I55: Caludia Vezzaro | J55: Guadalupe Carillo | K55: ciademaria_nivelmedio@yahoo.com.ar | L55: CABA | M55: Colegiales | N55: 18 | O55: 6º Secundaria (Prov.) / 5º Media (CABA) | P55: 4 | Q55: 5 | R55: 1 | T55: Si | U55: No | V55: Jornada simple: sólo turno mañana (9:00 a 12.30 hs.) | W55: Miércoles 26/4 | AV55: No | AW55: Si | AX55: No | AY55: No | AZ55: Si | BA55: No | BB55: No | BC55: No | BD55: No | BE55: Si | BF55: No | BG55: No | BH55: No | BI55: No
A56: 45000.705 | B56: mariadelcarmencandeloro1@gmail.com | C56: INSTITUTO SAGRADA FAMILIA A 70 | D56: 020100400 | E56: 10. Liceos / Normales / Colegios / Institutos de otras orientaciones | F56: Economía y Administración | G56: Privada | H56: María del Carmen Candeloro | I56: Guadalupe Dominguez | J56: Victor Sacco | K56: mariadelcarmencandeloro1@gmail.com | L56: CABA | M56: Villa General Mitre | N56: 30 | O56: 6º Secundaria (Prov.) / 5º Media (CABA) | P56: 2 | Q56: 1 | R56: 40 | T56: Si | U56: No | V56: Jornada simple: sólo turno mañana (9:00 a 12.30 hs.) | W56: Miércoles 26/4 | AV56: Si | AW56: No | AX56: No | AY56: No | AZ56: Si | BA56: No | BB56: No | BC56: No | BD56: No | BE56: No | BF56: No | BG56: No | BH56: No | BI56: No | BJ56: No | BK56: No | BL56: Si | BM56: No | BN56: No | BO56: No | BP56: No | BQ56: No | BR56: No
A57: 45000.708 | B57: mariadelcarmencandeloro1@gmail.com | C57: INSTITUTO SAGRADA FAMILIA A 70 | D57: 020100400 | E57: 9. Liceos / Normales / Colegios / Institutos orientados en ciencias sociales y/o humanidades | F57: Sociales y Humanidades | G57: Privada | H57: María del Carmen Candeloro | I57: Guadalupe Dominguez | J57: Victor Sacco | K57: mariadelcarmencandeloro1@gmail.com | L57: CABA | M57: Villa General Mitre | N57: 30 | O57: 6º Secundaria (Prov.) / 5º Media (CABA) | P57: 2 | Q57: 1 | R57: 40 | T57: Si | U57: No | V57: Jornada simple: sólo turno mañana (9:00 a 12.30 hs.) | W57: Miércoles 26/4 | AV57: Si | AW57: No | AX57: No | AY57: No | AZ57: Si | BA57: No | BB57: No | BC57: No | BD57: No | BE57: No | BF57: No | BG57: No | BH57: No | BI57: No | BJ57: No | BK57: No | BL57: Si | BM57: No | BN57: No | BO57: No | BP57: No | BQ57: No | BR57: No
A58: 45002.002 | B58: liliana.molina@bue.edu.ar | C58: E.E.M.N°1 DE 20 Biblioteca del Congreso de la Nación | D58: 020106200 | E58: 4. Artísticas de todas las orientaciones | F58: Artes Visuales | G58: Estatal | H58: Liliana Ines Molina | I58: Carolina Rivarola | J58: Candela García | K58: liliana.molina@bue.edu.ar | L58: CABA | M58: Villa Lugano | N58: 35 | O58: 3º Secundaria (Prov.) / 2º Media (CABA) | P58: 4 | Q58: 2 | R58: 95 | T58: Si | U58: No | V58: Jornada simple: sólo turno mañana (9:00 a 12.30 hs.) | W58: Martes 25/4 | X58: Si | Y58: No | Z58: No | AA58: No | AB58: Si | AC58: No | AD58: No | AE58: No | AF58: No | AG58: No | AH58: No | AI58: No | AJ58: No | AK58: No | AL58: No | AM58: No | AN58: Si | AO58: No | AP58: No | AQ58: No | AR58: No | AS58: No | AT58: No
A59: 45000.716 | B59: laurabusso@bue.edu.ar | C59: Escuela Normal N°9 Domingo F Sarmiento | D59: 020113300 | E59: 1. Liceos / Normales / Colegios / Institutos orientados en ciencias naturales y/o exactas | F59: Educación | G59: Estatal | H59: María Laura Busso | I59: María Fernanda Faggionatto | J59: Gonzalo Godoy | K59: laurabusso@bue.edu.ar | L59: CABA | M59: Balvanera | N59: 28 | O59: 5º Secundaria (Prov.) / 4º Media (CABA) | P59: 3 | Q59: 2 | R59: 30 | S59: Nos resulta una propuesta complementaria para un proyecto que estamos armando con los estudiantes. | T59: Si | U59: No | V59: Jornada simple: sólo turno mañana (9:00 a 12.30 hs.) | W59: Martes 25/4 | X59: Si | Y59: No | Z59: No | AA59: No | AB59: No | AC59: Si | AD59: No | AE59: No | AF59: No | AG59: No | AH59: Si | AI59: No | AJ59: No | AK59: No | AL59: No | AM59: No | AN59: Si | AO59: No | AP59: No | AQ59: No | AR59: No | AS59: No | AT59: No | AU59: Nuestra salida esta autorizada hasta las 12.15hs
A60: 45000.968 | B60: j.ferrero.1964@gmail.com | C60: Escuela Normal Superior N°9 Sarmiento | D60: 020117700 | E60: 1. Liceos / Normales / Colegios / Institutos orientados en ciencias naturales y/o exactas | F60: Ciencias Naturales | G60: Estatal | H60: Javier Ferrero | I60: Sabrina Bobinac | J60: - | K60: j.ferrero.1964@gmail.com | L60: CABA | M60: Balvanera | N60: 28 | O60: 5º Secundaria (Prov.) / 4º Media (CABA) | P60: 5 | Q60: 5 | R60: 7 | S60: - | T60: Si | U60: No | V60: Jornada simple: sólo turno mañana (9:00 a 12.30 hs.) | W60: Miércoles 26/4 | AV60: Si | AW60: No | AX60: No | AY60: No | AZ60: No | BA60: Si | BB60: No | BC60: No | BD60: No | BE60: No | BF60: Si | BG60: No | BH60: No | BI60: No | BJ60: No | BK60: No | BL60: Si | BM60: No | BN60: No | BO60: No | BP60: No | BQ60: No | BR60: No
A61: 45005.613 | B61: gabriela.lucca@bue.edu.ar | C61: ENS Nº 10 JUAN BAUTISTA ALBERDI DE 10 | D61: 020121400 | E61: 1. Liceos / Normales / Colegios / Institutos orientados en ciencias naturales y/o exactas | F61: Naturales | G61: Estatal | H61: Gabriela Lucca | I61: Cecilia Accorinti | J61: Alejandra Falconi | K61: gabriela.lucca@bue.edu.ar | L61: CABA | M61: Belgrano | N61: 40 | O61: 5º Secundaria (Prov.) / 4º Media (CABA) | P61: 4 | Q61: 4 | R61: 20 | S61: son 41 alumnos en total, si van todos. | T61: Si | U61: No | V61: Jornada simple: sólo turno mañana (9:00 a 12.30 hs.) | W61: Martes 25/4 | X61: Si | Y61: Si | Z61: No | AA61: No | AB61: Si | AC61: Si | AD61: No | AE61: No | AF61: No | AG61: No | AH61: Si | AI61: Si | AJ61: No | AK61: No | AL61: No | AM61: Si | AN61: Si | AO61: No | AP61: No | AQ61: Si | AR61: Si | AS61: No | AT61: No | AU61: Priorizamos primero la charla de 9.30; y la de 11.30 en este último caso de no ser posible, nos anotamos en arte matemático, taller o visita guiada. Podemos quedarnos hasta las 12.45 aprox.
A62: 45003.653 | B62: rodrigog.diaz@bue.edu.ar | C62: INSTITUTO INMACULADA CONCEPCIÓN A-86 | D62: 020122500 | E62: 2. Técnicas en computación, electrónica, informática | F62: Informática | G62: Privada | H62: RODRIGO GASTÓN DÍAZ | I62: MARIANA CHIESA | J62: NAZARENO AGUIRRE | K62: rodrigog.diaz@bue.edu.ar | L62: CABA | M62: Almagro | N62: 35 | O62: 5º Secundaria (Prov.) / 4º Media (CABA) | P62: 3 | Q62: 3 | R62: 30 | T62: Si | U62: Si | V62: Jornada completa: turno completo (9:00 a 16.00 hs.) | W62: Martes 25/4 | X62: Si | Y62: Si | Z62: Si | AA62: Si | AB62: Si | AC62: Si | AD62: Si | AE62: Si | AF62: Si | AG62: Si | AH62: Si | AI62: Si | AJ62: Si | AK62: Si | AL62: Si | AM62: Si | AN62: Si | AO62: Si | AP62: Si | AQ62: Si | AR62: Si | AS62: Si | AT62: Si | AU62: Importante porcentaje de alumnos cursando UBA XXI en carreras afines a la temática.
A63: 45003.656 | B63: rodrigog.diaz@bue.edu.ar | C63: INSTITUTO INMACULADA CONCEPCIÓN A-86 | D63: 020122500 | E63: 1. Liceos / Normales / Colegios / Institutos orientados en ciencias naturales y/o exactas | F63: Informática | G63: Privada | H63: RODRIGO DIAZ | I63: NAZARENO AGUIRRE | J63: MARIANA CHIESA | K63: rodrigog.diaz@bue.edu.ar | L63: CABA | M63: Almagro | N63: 35 | O63: 5º Secundaria (Prov.) / 4º Media (CABA) | P63: 3 | Q63: 3 | R63: 30 | S63: Corresponde a otra división de la orientación | T63: Si | U63: Si | V63: Jornada completa: turno completo (9:00 a 16.00 hs.) | W63: Martes 25/4 | X63: Si | Y63: Si | Z63: Si | AA63: Si | AB63: Si | AC63: Si | AD63: Si | AE63: Si | AF63: Si | AG63: Si | AH63: Si | AI63: Si | AJ63: Si | AK63: Si | AL63: Si | AM63: Si | AN63: Si | AO63: Si | AP63: Si | AQ63: Si | AR63: Si | AS63: Si | AT63: Si | AU63: Importante porcentaje de alumnos cursando UBA XXI en carreras afines.
A64: 45000.738 | B64: silveiga@yahoo.com.ar | C64: ENS Nº 4 ESTANISLAO ZEBALLOS | D64: 020129700 | E64: 1. Liceos / Normales / Colegios / Institutos orientados en ciencias naturales y/o exactas | F64: Matemática y física | G64: Estatal | H64: Silvia Ana Veiga | I64: Gisela Serrano | J64: Mónica Sivila | K64: silveiga@yahoo.com.ar | L64: CABA | M64: Caballito | N64: 23 | O64: 6º Secundaria (Prov.) / 5º Media (CABA) | P64: 4 | Q64: 4 | R64: 50 | S64: Vamos a la semana de la Matemática todos los años con nuestros 5º bach matemática y Física | T64: Si | U64: No | V64: Jornada simple: sólo turno mañana (9:00 a 12.30 hs.) | W64: Martes 25/4 | X64: Si | Y64: No | Z64: No | AA64: No | AB64: Si | AC64: No | AD64: No | AE64: No | AF64: No | AG64: No | AH64: No | AI64: Si | AJ64: No | AK64: No | AL64: No | AM64: No | AN64: No | AO64: No | AP64: No | AQ64: No | AR64: No | AS64: No | AT64: No | AU64: Vamos con los chicos de 5º orientación Matemática y Física todos los años desde que comenzó la semana de la Matemática.
A65: 45000.835 | B65: Anabella.caceres@bue.edu.ar | C65: Escuela Normal Superior n5 "Martin Miguel de Güemes" | D65: 020132800 | E65: 1. Liceos / Normales / Colegios / Institutos orientados en ciencias naturales y/o exactas | F65: Matematica y Fisica | G65: Estatal | H65: A. Carolina Cáceres | I65: Lorena Paniagua | J65: Gustavo Catuara | K65: Anabella.caceres@bue.edu.ar | L65: CABA | M65: Barracas | N65: 15 | O65: 6º Secundaria (Prov.) / 5º Media (CABA) | P65: 3 | Q65: 3 | R65: 30 | T65: Si | U65: No | V65: Jornada simple: sólo turno mañana (9:00 a 12.30 hs.) | W65: Martes 25/4 | X65: Si | Y65: No | Z65: No | AA65: No | AB65: No | AC65: Si | AD65: Si | AE65: No | AF65: No | AI65: Si | AM65: Si | AS65: Si
A66: 45000.84 | B66: Anabella.caceres@bue.edu.ar | C66: Escuela Normal Superior n5 " Martin Miguel de Güemes" | D66: 020132800 | E66: 1. Liceos / Normales / Colegios / Institutos orientados en ciencias naturales y/o exactas | F66: Matematica y Fisica | G66: Estatal | H66: A. Carolina Cáceres | I66: Lorena Paniagua | J66: Gustavo Catuara | K66: Anabella.caceres@bue.edu.ar | L66: CABA | M66: Barracas | N66: 16 | O66: 5º Secundaria (Prov.) / 4º Media (CABA) | P66: 3 | Q66: 3 | R66: 30 | T66: Si | U66: No | V66: Jornada simple: sólo turno mañana (9:00 a 12.30 hs.) | W66: Martes 25/4 | X66: Si | Y66: No | Z66: No | AA66: No | AB66: Si | AC66: No | AD66: No | AE66: No | AF66: No | AG66: No | AH66: No | AI66: Si | AJ66: No | AK66: No | AL66: No | AM66: No | AN66: No | AO66: Si | AP66: No | AQ66: No | AR66: No | AS66: Si | AT66: No
A67: 45000.824 | B67: d.ana.gomez@sanrafael.esc.edu.ar | C67: Instituto San Rafael (A-120) | D67: 020133700 | E67: 1. Liceos / Normales / Colegios / Institutos orientados en ciencias naturales y/o exactas | F67: Administración de empresas | G67: Privada | H67: Ana Paula Gómez Tascón | I67: Franco Luciano Mazzoli | K67: d.ana.gomez@sanrafael.esc.edu.ar | L67: CABA | M67: Villa Devoto | N67: 34 | O67: 4º Secundaria (Prov:) / 3º Media (CABA) | P67: 3 | Q67: 1 | R67: 15 | T67: Si | U67: No | V67: Jornada simple: sólo turno mañana (9:00 a 12.30 hs.) | W67: Martes 25/4 | X67: Si | Y67: Si | Z67: No | AA67: No | AB67: No | AC67: No | AD67: No | AE67: No | AF67: No | AG67: No | AH67: Si | AI67: No | AJ67: No | AK67: No | AL67: No | AM67: No | AN67: No | AO67: No | AP67: No | AQ67: No | AR67: No | AS67: No | AT67: No | AU67: Consideré q cada actividad dura una hora. Por ello, me anoté con este fixture: 9:30 charla de redes/ 10:30 taller del hacer matemático / 11:30 charla de calculadora
A68: 45000.828 | B68: d.ana.gomez@sanrafael.esc.edu.ar | C68: Instituto San Rafael (A-120) | D68: 020133700 | E68: 1. Liceos / Normales / Colegios / Institutos orientados en ciencias naturales y/o exactas | F68: Administración | G68: Privada | H68: Ana Paula Gómez Tascón | I68: Gabriel Giberti | K68: d.ana.gomez@sanrafael.esc.edu.ar | L68: CABA | M68: Villa Devoto | N68: 30 | O68: 6º Secundaria (Prov.) / 5º Media (CABA) | P68: 3 | Q68: 1 | R68: 10 | T68: Si | U68: No | V68: Jornada simple: sólo turno mañana (9:00 a 12.30 hs.) | W68: Miércoles 26/4 | AV68: No | AW68: Si | AX68: No | AY68: No | AZ68: No | BA68: No | BB68: No | BC68: No | BD68: No | BE68: Si | BJ68: No | BK68: No | BL68: No | BM68: No | BN68: No | BO68: Si | BP68: No | BQ68: No | BR68: No | BS68: Me encantaría q los estudiantes de 5to año vean algo de fractales pero si cada posta es de una hora, no nos darán los tiempos. Muchas gracias
A69: 45000.831 | B69: d.ana.gomez@sanrafael.esc.edu.ar | C69: Instituto San Rafael (A-120) | D69: 020133700 | E69: 1. Liceos / Normales / Colegios / Institutos orientados en ciencias naturales y/o exactas | F69: Ciencias Naturales | G69: Privada | H69: Ana Paula Gómez Tascón | I69: Franco Luciano Mazzoli | K69: d.ana.gomez@sanrafael.esc.edu.ar | L69: CABA | M69: Villa Devoto | N69: 34 | O69: 4º Secundaria (Prov:) / 3º Media (CABA) | P69: 3 | Q69: 1 | R69: 15 | T69: Si | U69: No | V69: Jornada simple: sólo turno mañana (9:00 a 12.30 hs.) | W69: Martes 25/4 | X69: Si | Y69: Si | Z69: No | AA69: No | AB69: No | AC69: No | AD69: No | AE69: No | AF69: No | AG69: No | AH69: Si | AI69: No | AJ69: No | AK69: No | AL69: No | AM69: No | AN69: No | AO69: No | AP69: No | AQ69: No | AR69: No | AS69: No | AT69: No
A70: 45001.784 | B70: andreoniraquel@institutourquiza.edu.ar | C70: Instituto General Justo José de Urquiza A 40 | D70: 020134800 | E70: 3. Técnicas en administración de empresas, administración de las organizaciones, servicios turísticos, multimedios | F70: Economía y administración / Comunicación | G70: Privada | H70: Raquel Andreoni | I70: Micaela Barbalace | J70: Mercedes González | K70: andreoniraquel@institutourquiza.edu.ar | L70: CABA | M70: Caballito | N70: 40 | O70: 5º Secundaria (Prov.) / 4º Media (CABA) | P70: 5 | Q70: 4 | R70: 5 | T70: Si | U70: No | V70: Jornada simple: sólo turno mañana (9:00 a 12.30 hs.) | W70: Martes 25/4 | X70: No | Y70: No | Z70: No | AA70: Si | AB70: No | AC70: No | AD70: No | AE70: No | AF70: No | AG70: No | AH70: No | AI70: No | AJ70: No | AK70: No | AL70: No | AM70: Si | AN70: No | AO70: No | AP70: No | AQ70: No | AR70: No | AS70: No | AT70: No
A71: 45000.818 | B71: veronica.garces@bue.edu.ar | C71: COLEGIO N 17 DE 7 | D71: 020135200 | E71: 9. Liceos / Normales / Colegios / Institutos orientados en ciencias sociales y/o humanidades | F71: Bachiller con orientación Ciencias Sociales | G71: Estatal | H71: Verónica Garcés | I71: Laura Mancuso | J71: Claudia Uzal | K71: veronica.garces@bue.edu.ar | L71: CABA | M71: Caballito | N71: 35 | O71: 4º Secundaria (Prov:) / 3º Media (CABA) | P71: 3 | Q71: 3 | R71: 30 | T71: Si | U71: No | V71: Jornada simple: sólo turno mañana (9:00 a 12.30 hs.) | W71: Miércoles 26/4 | AV71: Si | AW71: Si | AX71: No | AY71: Si | AZ71: Si | BA71: Si | BB71: No | BC71: No | BD71: No | BE71: Si | BF71: Si | BG71: Si | BH71: No | BI71: No | BJ71: Si | BK71: Si | BL71: Si | BM71: No | BN71: No | BO71: Si | BP71: Si | BQ71: No | BR71: No
A72: 45000.7 | B72: laya.marconi@cristoforocolombo.org.ar | C72: ESCUELA ITALIANA CRISTOFORO COLOMBO | D72: 020148000 | E72: 1. Liceos / Normales / Colegios / Institutos orientados en ciencias naturales y/o exactas | F72: cientìfico | G72: Privada | H72: Laya Marconi | I72: Giosafat Nasta | K72: laya.marconi@cristoforocolombo.org.ar | L72: CABA | M72: Belgrano | N72: 24 | O72: 4º Secundaria (Prov:) / 3º Media (CABA) | P72: 4 | Q72: 5 | R72: 0 | T72: Si | U72: No | V72: Jornada simple: sólo turno mañana (9:00 a 12.30 hs.) | W72: Martes 25/4 | X72: Si | Y72: Si | Z72: Si | AA72: Si | AB72: Si | AC72: Si | AD72: No | AE72: No | AF72: No | AG72: Si | AH72: Si | AI72: Si | AJ72: No | AK72: No | AL72: Si | AM72: Si | AN72: Si | AO72: No | AP72: No | AQ72: Si | AR72: Si | AS72: No | AT72: No
A73: 45005.711 | B73: laya.marconi@cristoforocolombo.org.ar | C73: ESCUELA ITALIANA CRISTOFORO COLOMBO | D73: 020148000 | E73: 1. Liceos / Normales / Colegios / Institutos orientados en ciencias naturales y/o exactas | F73: CIENCIAS | G73: Privada | H73: LAYA MARCONI | I73: GIOSAFAT NASTA | K73: laya.marconi@cristoforocolombo.org.ar | L73: CABA | M73: Belgrano | N73: 24 | O73: 4º Secundaria (Prov:) / 3º Media (CABA) | P73: 5 | Q73: 5 | R73: 0 | T73: Si | U73: No | V73: Jornada simple: sólo turno mañana (9:00 a 12.30 hs.) | W73: Miércoles 26/4 | AV73: Si | AW73: Si | AX73: No | AY73: Si | AZ73: Si | BA73: Si | BB73: No | BC73: No | BD73: No | BE73: Si | BF73: Si | BG73: Si | BH73: No | BI73: No | BJ73: Si | BK73: Si | BL73: Si | BM73: No | BN73: No | BO73: Si | BP73: Si | BQ73: No | BR73: No
A74: 45001.394 | B74: gabrielaterenzani@institutovelez.edu.ar | C74: Instituto Dr. Dalmacio Vélez Sarsfield | D74: 020148300 | E74: 1. Liceos / Normales / Colegios / Institutos orientados en ciencias naturales y/o exactas | F74: Bachiller en Educación Física (3°A EF TM) | G74: Privada | H74: Gabriela Terenzani | I74: Andrea Lares | K74: gabrielaterenzani@institutovelez.edu.ar | L74: CABA | M74: Liniers CABA | N74: 38 | O74: 4º Secundaria (Prov:) / 3º Media (CABA) | P74: 4 | Q74: 3 | R74: 10 | S74: PORCENTAJE SOLICITADO ES APROXIMADO | T74: Si | U74: No | V74: Jornada simple: sólo turno mañana (9:00 a 12.30 hs.) | W74: Martes 25/4 | X74: Si | Y74: Si | Z74: No | AA74: Si | AB74: Si | AC74: Si | AD74: No | AE74: No | AF74: No | AG74: Si | AH74: Si | AI74: Si | AJ74: No | AK74: No | AL74: Si | AM74: Si | AN74: Si | AO74: No | AP74: No | AQ74: Si | AR74: Si | AS74: No | AT74: No | AU74: 3° A EF TM 38 alumnos
A75: 45001.399 | B75: gabrielaterenzani@institutoveolez.edu.ar | C75: Instituto Dr. Dalmacio Velez Sarsfield | D75: 020148300 | E75: 1. Liceos / Normales / Colegios / Institutos orientados en ciencias naturales y/o exactas | F75: Bachiller en Educación Física | G75: Privada | H75: Gabriela Terenzani | I75: Andrea Lares | K75: gabrielaterenzani@institutovelez.edu.ar | L75: CABA | M75: Liniers CABA | N75: 37 | O75: 4º Secundaria (Prov:) / 3º Media (CABA) | P75: 4 | Q75: 3 | R75: 10 | S75: Porcentaje solicitado aproximado | T75: Si | U75: No | V75: Jornada simple: sólo turno mañana (9:00 a 12.30 hs.) | W75: Miércoles 26/4 | AV75: Si | AW75: Si | AX75: No | AY75: Si | AZ75: Si | BA75: Si | BB75: No | BC75: No | BD75: No | BE75: Si | BF75: Si | BG75: Si | BH75: No | BI75: No | BJ75: Si | BK75: Si | BL75: Si | BM75: No | BN75: No | BO75: Si | BP75: Si | BQ75: No | BR75: No | BS75: 3° B EF TM 37 alumnos
A76: 45001.412 | B76: gabrielaterenzani@institutovelez.edu.ar | C76: Instituto Dr. Dalmacio Vélez Sarsfield | D76: 020148300 | E76: 1. Liceos / Normales / Colegios / Institutos orientados en ciencias naturales y/o exactas | F76: Bachiller en Educación Física | G76: Privada | H76: Gabriela Terenzani | I76: Andrea Lares | K76: gabrielaterenzani@institutovelez.edu.ar | L76: CABA | M76: Liniers CABA | N76: 37 | O76: 4º Secundaria (Prov:) / 3º Media (CABA) | P76: 4 | Q76: 3 | R76: 10 | S76: Porcentaje solicitado aproximado | T76: Si | U76: Si | V76: Jornada completa: turno completo (9:00 a 16.00 hs.) | W76: Miércoles 26/4 | AV76: Si | AW76: Si | AX76: No | AY76: Si | AZ76: Si | BA76: Si | BB76: No | BC76: No | BD76: No | BE76: Si | BF76: Si | BG76: Si | BH76: No | BI76: No | BJ76: Si | BK76: Si | BL76: Si | BM76: No | BN76: No | BO76: Si | BP76: Si | BQ76: No | BR76: No | BS76: 3° B EF TM 37 alumnos (AL NO RECIBIR MAIL DE CONFIRMACIÓN AL RELLENAR EL FORMULARIO PARA ESTE CURSO, LO COMPLETÉ NUEVAMENTE, aviso por las dudas por si reciben otro formulario para este curso).
A77: 45001.423 | B77: gabrielaterenzani@institutovelez.edu.ar | C77: Instituto Dr. Dalmacio Vélez Sarsfield | D77: 020148300 | E77: 1. Liceos / Normales / Colegios / Institutos orientados en ciencias naturales y/o exactas | F77: Bachiller en Educación Física | G77: Privada | H77: Gabriela Terenzani | I77: Andrea Lares | K77: gabrielaterenzani@institutovelez.edu.ar | L77: CABA | M77: Liniers CABA | N77: 30 | O77: 4º Secundaria (Prov:) / 3º Media (CABA) | P77: 4 | Q77: 3 | R77: 10 | S77: Porcentaje solicitado estimativo | T77: No | U77: Si | V77: Jornada simple: sólo turno tarde (12.30 a 16:00 hs.) | W77: Miércoles 26/4 | AV77: No | AW77: No | AX77: Si | AY77: No | AZ77: No | BA77: No | BB77: No | BC77: Si | BD77: Si | BE77: No | BF77: No | BG77: No | BH77: Si | BI77: Si | BJ77: No | BK77: No | BL77: No | BM77: Si | BN77: Si | BO77: No | BP77: No | BQ77: Si | BR77: Si | BS77: 3° A EF TT 30 alumnos
A78: 45001.406 | B78: gabrielaterenzani@institutovelez.edu.ar | C78: Instituto Dr. Dalmacio Vélez Sarsfield | D78: 020148300 | E78: 1. Liceos / Normales / Colegios / Institutos orientados en ciencias naturales y/o exactas | F78: Bachiller en Comunicación | G78: Privada | H78: Gabriela Terenzani | I78: Andrea Lares | K78: gabrielaterenzani@institutovelez.edu.ar | L78: CABA | M78: Liniers CABA | N78: 36 | O78: 4º Secundaria (Prov:) / 3º Media (CABA) | P78: 4 | Q78: 3 | R78: 10 | S78: Porcentaje solicitado aproximado | T78: Si | U78: No | V78: Jornada simple: sólo turno mañana (9:00 a 12.30 hs.) | W78: Jueves 27/4 | BT78: Si | BU78: Si | BV78: No | BW78: Si | BX78: Si | BY78: Si | BZ78: No | CA78: No | CB78: No | CC78: Si | CD78: Si | CE78: Si | CF78: No | CG78: No | CH78: Si | CI78: Si | CJ78: Si | CK78: No | CL78: No | CM78: Si | CN78: Si | CO78: No | CP78: No | CQ78: 3° A COM TM 36 alumnos
A79: 45001.435 | B79: gabrielaterenzani@institutovelez.edu.ar | C79: Instituto Dr. Dalmacio Vélez Sarsfield | D79: 020148300 | E79: 1. Liceos / Normales / Colegios / Institutos orientados en ciencias naturales y/o exactas | F79: Bachiller en Comunicación | G79: Privada | H79: Gabriela Terenzani | I79: Andrea Lares | K79: gabrielaterenzani@institutovelez.edu.ar | L79: CABA | M79: Liniers CABA | N79: 34 | O79: 5º Secundaria (Prov.) / 4º Media (CABA) | P79: 4 | Q79: 3 | R79: 10 | S79: El porcentaje solicitado es estimativo. La cantidad es de alumnos, no incluye a los acompañantes. | T79: No | U79: Si | V79: Jornada simple: sólo turno tarde (12.30 a 16:00 hs.) | W79: Jueves 27/4 | BT79: No | BU79: No | BV79: Si | BW79: No | BX79: No | BY79: No | BZ79: No | CA79: Si | CB79: Si | CC79: No | CD79: No | CE79: No | CF79: Si | CG79: Si | CH79: No | CI79: No | CJ79: No | CK79: Si | CL79: Si | CM79: No | CN79: No | CO79: Si | CP79: Si | CQ79: 3° A COM TM 34 alumnos
A80: 45002.568 | B80: agustina.cafiero@ort.edu.ar | C80: Escuela ORT N°2 | D80: 020149400 | E80: 2. Técnicas en computación, electrónica, informática | F80: TIC/HUMANIDADES | G80: Privada | H80: Agustina Cafiero | I80: Dalmiro Dellechiaie | K80: agustina.cafiero@ort.edu.ar | L80: CABA | M80: Nuñez | N80: 35 | O80: 5º Secundaria (Prov.) / 4º Media (CABA) | P80: 5 | Q80: 5 | R80: 30 | S80: Los grupos estarán conformados por alumnos de 3ro, 4to y 5to (ciclo superior) | T80: Si | U80: No | V80: Jornada simple: sólo turno mañana (9:00 a 12.30 hs.) | W80: Miércoles 26/4 | AV80: No | AW80: Si | AX80: No | AY80: Si | AZ80: Si | BA80: Si | BB80: No | BC80: No | BD80: No | BE80: Si | BF80: Si | BG80: Si | BH80: No | BI80: No | BJ80: Si | BK80: Si | BL80: Si | BM80: No | BN80: No | BO80: No | BP80: No | BQ80: No | BR80: No
A81: 45002.571 | B81: agustina.cafiero@ort.edu.ar | C81: Escuela ORT N°2 | D81: 020149400 | E81: 9. Liceos / Normales / Colegios / Institutos orientados en ciencias sociales y/o humanidades | F81: TIC/HUMANIDADES | G81: Privada | H81: Luis Perez | I81: Mariana Gartner | K81: agustina.cafiero@ort.edu.ar | L81: CABA | M81: Nuñez | N81: 35 | O81: 6º Secundaria (Prov.) / 5º Media (CABA) | P81: 5 | Q81: 5 | R81: 30 | S81: Los grupos estarán conformados por alumnos de 3ro, 4to y 5to (ciclo superior) | T81: Si | U81: No | V81: Jornada simple: sólo turno mañana (9:00 a 12.30 hs.) | W81: Miércoles 26/4 | AV81: No | AW81: Si | AX81: No | AY81: Si | AZ81: Si | BA81: Si | BB81: No | BC81: No | BD81: No | BE81: Si | BF81: Si | BG81: Si | BH81: No | BI81: No | BJ81: Si | BK81: Si | BL81: Si | BM81: No | BN81: No | BO81: No | BP81: No | BQ81: No | BR81: No
A82: 45000.664 | B82: mariamarta82@gmail.com | C82: Instituto San Francisco de Asís | D82: 020150400 | E82: 9. Liceos / Normales / Colegios / Institutos orientados en ciencias sociales y/o humanidades | F82: Economía y Admistración | G82: Privada | H82: María Marta Sosa | I82: Patricia Cabrera | J82: Gonzalo Gallo | K82: mariamarta82@gmail.com | L82: CABA | M82: Nuñez | N82: 39 | O82: 5º Secundaria (Prov.) / 4º Media (CABA) | P82: 4 | Q82: 3 | R82: 30 | T82: Si | U82: No | V82: Jornada simple: sólo turno mañana (9:00 a 12.30 hs.) | W82: Martes 25/4 | X82: Si | Y82: Si | Z82: Si | AA82: Si | AB82: Si | AC82: Si | AD82: Si | AE82: No | AF82: No | AG82: Si | AH82: Si | AI82: Si | AJ82: No | AL82: Si | AM82: Si | AN82: Si | AO82: No | AP82: No | AQ82: Si | AR82: Si | AS82: No | AT82: No
A83: 45000.666 | B83: mariamarta82@gmail.com | C83: Instituto San Francisco de Asís | D83: 020150400 | E83: 4. Artísticas de todas las orientaciones | F83: Artes visuales | G83: Privada | H83: María Marta Sosa | I83: Patricia Cabrera | J83: Gonzalo Gallo | K83: mariamarta82@gmail.com | L83: CABA | M83: Nuñez | N83: 35 | O83: 5º Secundaria (Prov.) / 4º Media (CABA) | P83: 3 | Q83: 2 | R83: 30 | T83: Si | U83: No | V83: Jornada simple: sólo turno mañana (9:00 a 12.30 hs.) | W83: Martes 25/4 | X83: Si | Y83: Si | Z83: No | AA83: Si | AB83: Si | AC83: Si | AD83: No | AE83: No | AF83: No | AG83: Si | AH83: Si | AI83: Si | AJ83: No | AK83: No | AL83: Si | AM83: Si | AN83: Si | AO83: No | AP83: No | AQ83: Si | AR83: Si | AS83: No | AT83: No
A84: 45001.938 | B84: gonzalez.mercedes.sango@gmail.com | C84: Instituto San José | D84: 020169900 | E84: 1. Liceos / Normales / Colegios / Institutos orientados en ciencias naturales y/o exactas | F84: Gestión | G84: Privada | H84: Mercedes GONZALEZ | I84: Carolina Malter | J84: Diego Pozzi | K84: gonzalez.mercedes.sanjo@gmail.com | L84: CABA | M84: Balvanera | N84: 25 | O84: 6º Secundaria (Prov.) / 5º Media (CABA) | P84: 5 | Q84: 5 | R84: 10 | T84: Si | U84: Si | V84: Jornada completa: turno completo (9:00 a 16.00 hs.) | W84: Jueves 27/4 | BT84: No | BU84: No | BV84: No | BW84: No | BX84: No | BY84: Si | BZ84: Si | CA84: Si | CB84: Si | CC84: No | CD84: No | CE84: No | CF84: No | CG84: No | CH84: Si | CI84: Si | CJ84: Si | CK84: Si | CL84: Si | CM84: Si | CN84: Si | CO84: Si | CP84: Si | CQ84: Según el horario que ustedes nos otorguen deseamos realizar una visita guiada, participar de las estaciones interactivas y del Arte Matemático.
A85: 45001.941 | B85: gonzalez.mercedes.sanjo@gmail.com | C85: Instituto San José | D85: 020169900 | E85: 9. Liceos / Normales / Colegios / Institutos orientados en ciencias sociales y/o humanidades | F85: Comunicación | G85: Privada | H85: Mercedes Gonzalez | I85: Carolina Malter | J85: Diego Pozzi | K85: gonzalez.mercedes.sanjo@gmail.com | L85: CABA | M85: Balvanera | N85: 30 | O85: 6º Secundaria (Prov.) / 5º Media (CABA) | P85: 5 | Q85: 5 | R85: 10 | T85: Si | U85: Si | V85: Jornada completa: turno completo (9:00 a 16.00 hs.) | W85: Jueves 27/4 | BT85: No | BU85: No | BV85: No | BW85: No | BX85: No | BY85: Si | BZ85: Si | CA85: Si | CB85: Si | CC85: No | CD85: No | CE85: No | CF85: No | CG85: No | CH85: Si | CI85: Si | CJ85: Si | CK85: Si | CL85: Si | CM85: Si | CN85: Si | CO85: Si | CP85: Si | CQ85: Según los horarios que ustedes dispongan deseamos participar de VISITA GUIADA, ESTACIONES INTERACTIVAS y ARTE MATEMÁTICO.
A86: 45001.944 | B86: gonzalez.mercedes.sanjo@gmail.com | C86: Instituto San José | D86: 020169900 | E86: 1. Liceos / Normales / Colegios / Institutos orientados en ciencias naturales y/o exactas | F86: Gestión y economía | G86: Privada | H86: Mercedes Gonzalez | I86: Carolina Malter | J86: Diego Pozzi | K86: gonzalez.mercedes.sanjo@gmail.com | L86: CABA | M86: Balvanera | N86: 30 | O86: 6º Secundaria (Prov.) / 5º Media (CABA) | P86: 5 | Q86: 5 | R86: 10 | T86: Si | U86: Si | V86: Jornada completa: turno completo (9:00 a 16.00 hs.) | W86: Jueves 27/4 | BT86: No | BU86: No | BV86: No | BW86: Si | BX86: Si | BY86: Si | BZ86: Si | CA86: Si | CB86: Si | CC86: No | CD86: No | CE86: No | CF86: No | CG86: No | CH86: Si | CI86: Si | CJ86: Si | CK86: Si | CL86: Si | CM86: Si | CN86: Si | CO86: Si | CP86: Si | CQ86: Según los horarios que ustedes dispongan deseamos participar de VISITA GUIADA, ESTACIONES INTERACTIVAS y ARTE MATEMÁTICO.
A87: 45002.472 | B87: nadia.cura@bue.edu.ar | C87: Centro de Formación Profesional nro 10 | D87: 020200700 | E87: 13. Formación permanente de jóvenes y adultos | F87: Bachiller on orientación en Informática | G87: Estatal | H87: Nadia Cura | I87: Fabiana Suanno | J87: Juan Castellarin | K87: nadia.cura@bue.edu.ar | L87: CABA | M87: San Nicolás | N87: 30 | O87: 5º Secundaria (Prov.) / 4º Media (CABA) | P87: 4 | Q87: 1 | R87: 90 | T87: Si | U87: No | V87: Jornada simple: sólo turno mañana (9:00 a 12.30 hs.) | W87: Martes 25/4 | X87: Si | Y87: No | Z87: No | AA87: No | AB87: Si | AC87: No | AD87: No | AE87: No | AF87: No | AG87: No | AH87: No | AI87: No | AJ87: No | AK87: No | AL87: No | AM87: No | AN87: Si | AO87: No | AP87: No | AQ87: No | AR87: No | AS87: No | AT87: No
A88: 45005.635 | B88: secundaria@santiagoapostol.edu.ar | C88: Instituto Argentino Gallego Santiago Apóstol | D88: 020212700 | E88: 9. Liceos / Normales / Colegios / Institutos orientados en ciencias sociales y/o humanidades | F88: Bachiller en Ciencias Sociales y Humanidades | G88: Privada | H88: Ángeles Sananez | I88: Bibiana Rodríguez | J88: Rocío Da Silva | K88: secundaria@santiagoapostol.edu.ar | L88: CABA | M88: Balvanera - Ciudad Autónoma de Buenos Aires | N88: 20 | O88: 6º Secundaria (Prov.) / 5º Media (CABA) | P88: 5 | Q88: 3 | R88: 5 | T88: Si | U88: Si | V88: Jornada completa: turno completo (9:00 a 16.00 hs.) | W88: Miércoles 26/4 | AV88: Si | AW88: Si | AX88: Si | AY88: Si | AZ88: Si | BA88: Si | BB88: Si | BC88: Si | BD88: Si | BE88: Si | BF88: Si | BG88: Si | BH88: Si | BI88: Si | BJ88: Si | BK88: Si | BL88: Si | BM88: Si | BN88: Si | BO88: Si | BP88: Si | BQ88: Si | BR88: Si | BS88: Tildé muchas opciones de turnos para que nos asignen las que ustedes consideren.
A89: 45001.577 | B89: santiago.campagna@bue.edu.ar | C89: Escuela Técnica N° 20 | D89: 020307500 | E89: 2. Técnicas en computación, electrónica, informática | F89: Tecnicatura en Tecnologías de la Información. Tecnicatura en Producción Multimedial. | G89: Estatal | H89: Hita Desposorio | I89: Santiago Nehuen Campagna | K89: santiago.campagna@bue.edu.ar | L89: CABA | M89: Mataderos | N89: 35 | O89: 5º Secundaria (Prov.) / 4º Media (CABA) | P89: 5 | Q89: 2 | R89: 70 | T89: Si | U89: No | V89: Jornada simple: sólo turno mañana (9:00 a 12.30 hs.) | W89: Jueves 27/4 | BT89: Si | BU89: Si | BV89: Si | BW89: Si | BX89: Si | BY89: Si | BZ89: No | CA89: No | CB89: No | CC89: Si | CD89: Si | CE89: Si | CF89: No | CG89: No | CH89: Si | CI89: Si | CJ89: Si | CK89: No | CL89: No | CM89: Si | CN89: Si | CO89: No | CP89: No
A90: 45005.687 | B90: nruderman@gmail.com | C90: Escuela Superior de Comercio Carlos Pellegrini | D90: 029000800 | E90: 9. Liceos / Normales / Colegios / Institutos orientados en ciencias sociales y/o humanidades | F90: Comercial | G90: Estatal | H90: Nicolas Ruderman | I90: Eva Antal | K90: nruderman@gmail.com | L90: CABA | M90: Recoleta | N90: 20 | O90: 6º Secundaria (Prov.) / 5º Media (CABA) | P90: 5 | Q90: 4 | R90: 10 | T90: Si | U90: No | V90: Jornada simple: sólo turno mañana (9:00 a 12.30 hs.) | W90: Jueves 27/4 | BT90: No | BU90: Si | BV90: No | BW90: Si | BX90: No | BY90: No | BZ90: No | CA90: No | CB90: No | CC90: No | CD90: Si | CM90: No | CN90: Si | CO90: No | CP90: No
A91: 45004.538 | B91: mapaulasuarez@yahoo.com.ar | C91: INSTITUTO SOCIAL MILITAR DOCTOR DAMASO CENTENO | D91: 029003000 | E91: 1. Liceos / Normales / Colegios / Institutos orientados en ciencias naturales y/o exactas | F91: CIENCIAS NATURALES | G91: Estatal | H91: FLAVIA TERRIZZANO | I91: ANTONIO VUISSO | J91: ESTEFANIA DENIS | K91: mapaulasuarez@yahoo.com.ar | L91: CABA | M91: CABALLITO | N91: 35 | O91: 6º Secundaria (Prov.) / 5º Media (CABA) | P91: 5 | Q91: 5 | R91: 20 | T91: Si | U91: No | V91: Jornada simple: sólo turno mañana (9:00 a 12.30 hs.) | W91: Jueves 27/4 | BT91: Si | BU91: Si | BV91: No | BW91: Si | BX91: Si | BY91: Si | BZ91: No | CA91: No | CB91: No | CC91: Si | CD91: Si | CE91: Si | CF91: No | CG91: No | CH91: Si | CI91: Si | CJ91: Si | CK91: No | CL91: No | CM91: Si | CN91: Si | CO91: No | CP91: No
A92: 45004.53 | B92: mapaulasuarez@yahoo.com.ar | C92: INSTITUTO SOCIAL MILITAR DOCTOR DAMASO CENTENO | D92: 029003000 | E92: 1. Liceos / Normales / Colegios / Institutos orientados en ciencias naturales y/o exactas | F92: CIENCIAS NATURALES | G92: Estatal | H92: MARIA PAULA SUAREZ | I92: ADRIANA HOZ | J92: BRUNO BAGNIOLE | K92: mapaulasuarez@yahoo.com.ar | L92: CABA | M92: CABALLITO | N92: 40 | O92: 6º Secundaria (Prov.) / 5º Media (CABA) | P92: 5 | Q92: 5 | R92: 20 | T92: Si | U92: No | V92: Jornada simple: sólo turno mañana (9:00 a 12.30 hs.) | W92: Martes 25/4 | X92: Si | Y92: Si | Z92: No | AA92: Si | AB92: Si | AC92: Si | AD92: No | AE92: No | AF92: No | AG92: Si | AH92: Si | AI92: Si | AJ92: No | AK92: No | AL92: Si | AM92: Si | AN92: Si | AO92: No | AP92: No | AQ92: Si | AR92: Si | AS92: No | AT92: No | AU92: COMO TODOS LOS AÑOS, ESPERAMOS PODER VISITARLOS CON ESTE NUEVO GRUPO DE ALUMNOS
A93: 45004.534 | B93: mapaulasuarez@yahoo.com.ar | C93: INSTITUTO SOCIAL MILITAR DOCTOR DAMASO CENTENO | D93: 029003000 | E93: 1. Liceos / Normales / Colegios / Institutos orientados en ciencias naturales y/o exactas | F93: CIENCIAS NATURALES | G93: Estatal | H93: LISETTE MENDEZ | I93: FLORENCIA LOPEZ DE VOLVER | J93: ALVARO CORTES CONTI | K93: mapaulasuarez@yahoo.com.ar | L93: CABA | M93: CABALLITO | N93: 40 | O93: 6º Secundaria (Prov.) / 5º Media (CABA) | P93: 5 | Q93: 5 | R93: 20 | T93: Si | U93: No | V93: Jornada simple: sólo turno mañana (9:00 a 12.30 hs.) | W93: Miércoles 26/4 | AV93: Si | AW93: Si | AX93: No | AY93: Si | AZ93: Si | BA93: Si | BB93: No | BC93: No | BD93: No | BE93: Si | BF93: Si | BG93: Si | BH93: No | BI93: No | BJ93: Si | BK93: Si | BL93: Si | BM93: No | BN93: No | BO93: Si | BP93: Si | BQ93: No | BR93: No
A94: 45006.405 | B94: milagrosmcervio@gmail.com | C94: INSTITUTO NUESTRA SEÑORA DE LUJAN | D94: 060266000 | E94: 10. Liceos / Normales / Colegios / Institutos de otras orientaciones | F94: Economía y Administración de Empresas | G94: Privada | H94: Milagros María Clara Cervio | I94: Claudia Wavrenchuk | J94: Nazareno Lazaro | K94: milagrosmcervio@gmail.com | L94: ÁREA METROPOLITANA DE BUENOS AIRES | M94: Adrogué | N94: 34 | O94: 6º Secundaria (Prov.) / 5º Media (CABA) | P94: 3 | Q94: 3 | R94: 0 | T94: Si | U94: Si | V94: Jornada completa: turno completo (9:00 a 16.00 hs.) | W94: Jueves 27/4 | BT94: Si | BU94: Si | BV94: No | BW94: No | BX94: Si | BY94: No | BZ94: Si | CA94: No | CB94: No | CF94: Si | CL94: Si
A95: 45001.828 | B95: zelayaandrea@hotmail.com | C95: Escuela el Ave Maria | D95: 060364300 | E95: 13. Formación permanente de jóvenes y adultos | F95: Bachiller | G95: Privada | H95: Zelaya maria Andrea | I95: Pedro Paredes | K95: Zelayaandrea@hotmail.com | L95: INTERIOR DE LA PROVINCIA DE BUENOS AIRES | M95: Claypole, Almirante Brown | N95: 30 | O95: 6º Secundaria (Prov.) / 5º Media (CABA) | P95: 5 | Q95: 4 | R95: 30 | S95: Queremos participar de la semana de las coencias con nuestros estudiantes! | T95: Si | U95: No | V95: Jornada simple: sólo turno mañana (9:00 a 12.30 hs.) | W95: Jueves 27/4 | BT95: Si | BU95: No | BV95: No | BW95: Si | BX95: No | BY95: Si | BZ95: No | CA95: No | CB95: No | CC95: Si | CD95: No | CE95: No | CF95: No | CG95: No | CH95: Si | CI95: Si | CJ95: No | CK95: No | CL95: No | CN95: Si
A96: 45000.811 | B96: analiabarrionuevo@proyeccionxxi.com.ar | C96: Instituto Proyección XXI | D96: 060455500 | E96: 9. Liceos / Normales / Colegios / Institutos orientados en ciencias sociales y/o humanidades | F96: Sociales | G96: Privada | H96: Analía Barrionuevo | I96: Paola Flosi | K96: analiabarrionuevo@proyeccionxxi.com.ar | L96: ÁREA METROPOLITANA DE BUENOS AIRES | M96: Bernal Oeste | N96: 30 | O96: 5º Secundaria (Prov.) / 4º Media (CABA) | P96: 5 | Q96: 2 | R96: 15 | T96: No | U96: Si | V96: Jornada simple: sólo turno tarde (12.30 a 16:00 hs.) | W96: Jueves 27/4 | BT96: No | BU96: No | BV96: No | BW96: No | BX96: No | BY96: No | BZ96: No | CA96: Si | CB96: Si | CC96: No | CD96: No | CE96: No | CF96: Si | CG96: Si | CH96: No | CI96: No | CJ96: No | CK96: Si | CL96: Si | CM96: No | CN96: No | CO96: No | CP96: Si
A97: 45001.648 | B97: valeriatardioli@gmail.com | C97: Instituto Proyección XXI | D97: 060455500 | E97: 1. Liceos / Normales / Colegios / Institutos orientados en ciencias naturales y/o exactas | F97: Sociales | G97: Privada | H97: Paola Flossi | I97: Estrella Lopez | J97: Valeria Tardioli | K97: valeriatardioli@gmail.com | L97: ÁREA METROPOLITANA DE BUENOS AIRES | M97: Bernal oeste | N97: 31 | O97: 6º Secundaria (Prov.) / 5º Media (CABA) | P97: 4 | Q97: 1 | R97: 25 | T97: Si | U97: Si | V97: Jornada completa: turno completo (9:00 a 16.00 hs.) | W97: Jueves 27/4 | BT97: No | BU97: No | BV97: Si | BW97: Si | BX97: No | BY97: No | BZ97: No | CA97: No | CB97: No | CC97: No | CD97: No | CE97: Si | CF97: No | CG97: No | CH97: No | CI97: Si | CJ97: No | CK97: No | CL97: No | CM97: Si | CN97: No | CO97: No | CP97: No
A98: 45001.649 | B98: valeriatardioli@gmail.com | C98: Instituto Proyección XXI | D98: 060455500 | E98: 1. Liceos / Normales / Colegios / Institutos orientados en ciencias naturales y/o exactas | F98: Sociales | G98: Privada | H98: Paola Flossi | I98: Estrella Lopez | J98: Valeria Tardioli | K98: valeriatardioli@gmail.com | L98: ÁREA METROPOLITANA DE BUENOS AIRES | M98: Bernal Oeste | N98: 25 | O98: 6º Secundaria (Prov.) / 5º Media (CABA) | P98: 4 | Q98: 1 | R98: 25 | T98: Si | U98: Si | V98: Jornada completa: turno completo (9:00 a 16.00 hs.) | W98: Jueves 27/4 | BT98: No | BU98: No | BV98: Si | BW98: Si | BX98: No | BY98: No | BZ98: No | CA98: No | CB98: No | CC98: No | CD98: No | CE98: Si | CF98: No | CG98: No | CH98: No | CI98: Si | CJ98: No | CK98: No | CL98: No | CM98: Si | CN98: No | CO98: No | CP98: No
A99: 45002.465 | B99: baini.jesica@sanpablo-virreyes.edu.ar | C99: COLEGIO PARROQUIAL SAN PABLO | D99: 060486800 | E99: 10. Liceos / Normales / Colegios / Institutos de otras orientaciones | F99: Secundaria Básica | G99: Privada | H99: Jesica Baini | I99: Stefania Gabba | J99: Yesica Gimenéz | K99: baini.jesica@sanpablo-virreyes.edu.ar | L99: ÁREA METROPOLITANA DE BUENOS AIRES | M99: Virreyes | N99: 35 | O99: 3º Secundaria (Prov.) / 2º Media (CABA) | P99: 1 | Q99: 1 | R99: 49 | T99: Si | U99: Si | V99: Jornada completa: turno completo (9:00 a 16.00 hs.) | W99: Martes 25/4 | X99: Si | Y99: Si | Z99: No | AA99: Si | AB99: Si | AC99: Si | AD99: Si | AE99: No | AF99: No | AG99: Si | AH99: Si | AI99: Si | AJ99: No | AK99: No | AL99: No | AM99: No | AN99: No | AO99: No | AP99: No | AQ99: No | AR99: No | AS99: No | AT99: No
A100: 45002.452 | B100: gabba.stefania@sanpablo-virreyes.edu.ar | C100: COLEGIO PARROQUIAL SAN PABLO | D100: 060486800 | E100: 10. Liceos / Normales / Colegios / Institutos de otras orientaciones | F100: Secunaria Básica | G100: Privada | H100: Stefania Gabba | I100: Baini Jesica | J100: Yesica Gimenéz | K100: gabba.stefania@sanpablo-virreyes.edu.ar | L100: ÁREA METROPOLITANA DE BUENOS AIRES | M100: Virreyes | N100: 35 | O100: 3º Secundaria (Prov.) / 2º Media (CABA) | P100: 1 | Q100: 1 | R100: 50 | T100: Si | U100: Si | V100: Jornada completa: turno completo (9:00 a 16.00 hs.) | W100: Jueves 27/4 | BT100: Si | BU100: Si | BV100: No | BW100: Si | BX100: Si | BY100: Si | BZ100: Si | CA100: No | CB100: No | CC100: Si | CD100: No | CE100: Si | CF100: No | CG100: No | CH100: No | CI100: No | CJ100: No | CK100: No | CL100: No | CM100: No | CN100: No | CO100: No | CP100: No
...

Sheet Hoja 6
A1: 10 | B1: Liceos / Normales / Colegios / Institutos de otras orientaciones | C1: 10. Liceos / Normales / Colegios / Institutos de otras orientaciones
A2: 5 | B2: Técnicas área producción (electromecánica, mecánica, metalurgia, electricidad, automotores, refrigeración, construcciones, maestro mayor de obras, aeronáutica, naval, aviónico, óptico, en geografía matemática) | C2: 5. Técnicas área producción (electromecánica, mecánica, metalurgia, electricidad, automotores, refrigeración, construcciones, maestro mayor de obras, aeronáutica, naval, aviónico, óptico, en geografía matemática)
A3: 1 | B3: Liceos / Normales / Colegios / Institutos orientados en ciencias naturales y/o exactas | C3: 1. Liceos / Normales / Colegios / Institutos orientados en ciencias naturales y/o exactas
A4: 2 | B4: Técnicas en computación, electrónica, informática | C4: 2. Técnicas en computación, electrónica, informática
A5: 9 | B5: Liceos / Normales / Colegios / Institutos orientados en ciencias sociales y/o humanidades | C5: 9. Liceos / Normales / Colegios / Institutos orientados en ciencias sociales y/o humanidades
A6: 3 | B6: Técnicas en administración de empresas, administración de las organizaciones, servicios turísticos, multimedios | C6: 3. Técnicas en administración de empresas, administración de las organizaciones, servicios turísticos, multimedios
A7: 4 | B7: Artísticas de todas las orientaciones | C7: 4. Artísticas de todas las orientaciones
A8: 13 | B8: Formación permanente de jóvenes y adultos | C8: 13. Formación permanente de jóvenes y adultos
A9: 11 | B9: Rurales de todas las orientaciones | C9: 11. Rurales de todas las orientaciones

Sheet Corrida de prioridades
A1: Marca temporal | B1: Dirección de correo electrónico | C1: Nombre OFICIAL y COMPLETO de la institución educativa | D1: Código Único de Escuela (CUE) | E1: Tipo de escuela y orientación | F1: Especifique su orientación | G1: Gestión | H1: Nombre y apellido del/la docente responsable de la visita | I1: Nombre y apellido del/la docente acompañante 1 | J1: Nombre y apellido del/la docente acompañante 2 | K1: Dirección de correo electrónico para recibir resultado de la asignación | L1: Ubicación general de la escuela | M1: Barrio/Localidad de la escuela | N1: Cantidad de alumnos que asistirán | O1: Curso que asistirá | P1: Conectividad en la institución | Q1: Acceso a las ciencias exactas y naturales | R1: Porcentaje aproximado de estudiantes de familias de bajos recursos | S1: Exprese observaciones o comentarios que considere pertinentes | T1: Turno/s solicitado/s [Turno mañana (9:00 a 12.30 hs.)] | U1: Turno/s solicitado/s [Turno tarde (12.30 a 16:00 hs.)] | V1: Fecha solicitada | W1: CHARLAS [9:30 Redes sociales: la matemática detrás de los "influencers". Rocío Balderrama] | X1: CHARLAS [11:30 La Biblio junto a... la calculadora. Historias que no hacen historia. Juan Carlos Pedraza] | Y1: CHARLAS [14:00 ¿Cómo hacer ciencia con Twitter? Sofía del Pozo] | Z1: ESTACIONES INTERACTIVAS [9:30] | AA1: ESTACIONES INTERACTIVAS [10:30] | AB1: ESTACIONES INTERACTIVAS [11:30] | AC1: ESTACIONES INTERACTIVAS [13:00] | AD1: ESTACIONES INTERACTIVAS [14:00] | AE1: ESTACIONES INTERACTIVAS [15:00] | AF1: TALLERES [9:30] | AG1: TALLERES [10:30] | AH1: TALLERES [11:30] | AI1: TALLERES [14:00] | AJ1: TALLERES [15:00] | AK1: ARTE MATEMÁTICO [9:30] | AL1: ARTE MATEMÁTICO [10:30] | AM1: ARTE MATEMÁTICO [11:30] | AN1: ARTE MATEMÁTICO [14:00] | AO1: ARTE MATEMÁTICO [15:00] | AP1: VISITAS GUIADAS TEMÁTICAS [10:30] | AQ1: VISITAS GUIADAS TEMÁTICAS [11:30] | AR1: VISITAS GUIADAS TEMÁTICAS [14:00] | AS1: VISITAS GUIADAS TEMÁTICAS [15:00] | AT1: Exprese cualquier aclaración sobre la solicitud de inscripción que facilite la administración de vacantes. | AU1: CHARLAS [9:30 Desorden ordenado, ¡qué caos es esto! Paula Kuna] | AV1: CHARLAS [11:30 ¿Tenés una idea para cambiar el mundo? Primero simulalo. Rodrigo Castro] | AW1: CHARLAS [14:00 Embaldosados Fractales. Ursula Molter] | AX1: ESTACIONES INTERACTIVAS [9:30] | AY1: ESTACIONES INTERACTIVAS [10:30] | AZ1: ESTACIONES INTERACTIVAS [11:30] | BA1: ESTACIONES INTERACTIVAS [13:00] | BB1: ESTACIONES INTERACTIVAS [14:00] | BC1: ESTACIONES INTERACTIVAS [15:00] | BD1: TALLERES [9.30] | BE1: TALLERES [10:30] | BF1: TALLERES [11:30] | BG1: TALLERES [14:00] | BH1: TALLERES [15:00] | BI1: ARTE MATEMÁTICO [9:30] | BJ1: ARTE MATEMÁTICO [10:30] | BK1: ARTE MATEMÁTICO [11:30] | BL1: ARTE MATEMÁTICO [14:00] | BM1: ARTE MATEMÁTICO [15:00] | BN1: VISITA GUIADA [10:30] | BO1: VISITA GUIADA [11:30] | BP1: VISITA GUIADA [14:00] | BQ1: VISITA GUIADA [15:00] | BR1: Exprese cualquier aclaración sobre la solicitud de inscripción que facilite la administración de vacantes. | BS1: CHARLAS [9:30 Geometría proyectiva, fotografía y la final del mundo. Charly Di Fiore] | BT1: CHARLAS [11:30 Detective de datos. Guillermo Solovey] | BU1: CHARLAS [14:00 Datos y deportes. Iván Monardo] | BV1: ESTACIONES INTERACTIVAS [9:30] | BW1: ESTACIONES INTERACTIVAS [10:30] | BX1: ESTACIONES INTERACTIVAS [11:30] | BY1: ESTACIONES INTERACTIVAS [13:00] | BZ1: ESTACIONES INTERACTIVAS [14:00] | CA1: ESTACIONES INTERACTIVAS [15:00] | CB1: TALLERES [9:30] | CC1: TALLERES [10:30 ] | CD1: TALLERES [11:30] | CE1: TALLERES [14:00] | CF1: TALLERES [15:00] | CG1: ARTE MATEMÁTICO [9:30] | CH1: ARTE MATEMÁTICO [10:30] | CI1: ARTE MATEMÁTICO [11:30] | CJ1: ARTE MATEMÁTICO [14:00] | CK1: ARTE MATEMÁTICO [15:00] | CL1: VISITA GUIADA [10:30] | CM1: VISITA GUIADA [11:30] | CN1: VISITA GUIADA [14:00] | CO1: VISITA GUIADA [15:00] | CP1: Exprese cualquier aclaración sobre la solicitud de inscripción que facilite la administración de vacantes.
A2: 45003.815 | B2: malarcon1012@gmail.com | C2: Escuela de Educación Secundaria Técnica Nª1 | D2: 061213800 | E2: 5. Técnicas área producción (electromecánica, mecánica, metalurgia, electricidad, automotores, refrigeración, construcciones, maestro mayor de obras, aeronáutica, naval, aviónico, óptico, en geografía matemática) | F2: en construcción .los alumnos egresan con el titulo Maestro Mayor de Obra | G2: Estatal | H2: Mirna Alarcón | I2: Sandra Casan | J2: Roberto Tignianelli | K2: malarcon1012@gmail.com | L2: INTERIOR DE LA PROVINCIA DE BUENOS AIRES | M2: San Isidro | N2: 34 | O2: 7º Técnica (Prov.) / 6º Técnica (CABA) | P2: 3 | Q2: 3 | R2: 88 | S2: La mayoría de los alumnos son de barrios carenciados | T2: No | U2: Si | V2: Martes 25/4 | W2: No | X2: No | Y2: Si | Z2: No | AA2: No | AB2: Si | AC2: Si | AD2: No | AE2: No | AJ2: Si | AO2: Si | AP2: Si | AT2: Estaremos muy satisfecho, en las aérea o talleres que uds nos designen
A3: 45000.682 | B3: reboiras.juan@colegioesclavas.edu.ar | C3: Instituto Esclavas del Sagrado Corazón de Jesús (A-14) | D3: 020094900 | E3: 1. Liceos / Normales / Colegios / Institutos orientados en ciencias naturales y/o exactas | F3: Ciencias Naturales | G3: Privada | H3: Juan Martín Reboiras | I3: Patricia Julia Castro | K3: reboiras.juan@colegioesclavas.edu.ar | L3: CABA | M3: Belgrano | N3: 30 | O3: 6º Secundaria (Prov.) / 5º Media (CABA) | P3: 2 | Q3: 3 | R3: 0 | T3: Si | U3: Si | V3: Jueves 27/4 | BS3: Si | BT3: Si | BU3: Si | BV3: Si | BW3: Si | BX3: Si | BY3: Si | BZ3: Si | CA3: Si | CB3: Si | CC3: Si | CD3: Si | CE3: Si | CF3: Si | CG3: Si | CH3: Si | CI3: Si | CJ3: Si | CK3: Si | CL3: Si | CM3: Si | CN3: Si | CO3: Si
A4: 45005.59 | B4: auniversidad@goethe.edu.ar | C4: INSTITUTO ESCOLAR GOETHE | D4: 061215200 | E4: 1. Liceos / Normales / Colegios / Institutos orientados en ciencias naturales y/o exactas | F4: Ciencias Naturales | G4: Privada | H4: Tatiana Wolff | I4: Melina Seifert | J4: Matthias FaBit | K4: auniversidad@goethe.edu.ar | L4: ÁREA METROPOLITANA DE BUENOS AIRES | M4: San Isidro | N4: 35 | O4: 6º Secundaria (Prov.) / 5º Media (CABA) | P4: 5 | Q4: 5 | R4: 0 | T4: Si | U4: Si | V4: Martes 25/4 | W4: Si | X4: No | Y4: Si | Z4: No | AA4: No | AB4: No | AC4: No | AD4: No | AE4: Si | AF4: No | AG4: Si | AH4: No | AI4: No | AJ4: No | AK4: No | AL4: No | AM4: No | AN4: No | AO4: No | AP4: No | AQ4: Si | AR4: No | AS4: No
A5: 45001.578 | B5: gabriela.gonzalog@gmail.com | C5: Colegio irlandes | D5: 061602200 | E5: 1. Liceos / Normales / Colegios / Institutos orientados en ciencias naturales y/o exactas | F5: Ciencias sociales | G5: Privada | H5: Maria Gabriela Gonzalo Grilo | I5: Sabrina alvarenga | J5: Romina ramos | K5: gabriela.gonzalog@gmail.com | L5: ÁREA METROPOLITANA DE BUENOS AIRES | M5: Almirante brown | N5: 28 | O5: 6º Secundaria (Prov.) / 5º Media (CABA) | P5: 5 | Q5: 3 | R5: 0 | T5: Si | U5: No | V5: Miércoles 26/4 | AU5: Si | AV5: No | AW5: No | AX5: No | AY5: No | AZ5: Si | BA5: No | BB5: No | BC5: No | BD5: No | BE5: No | BF5: No | BG5: No | BH5: No | BI5: No | BJ5: Si | BK5: No | BL5: No | BM5: No | BN5: No | BO5: No | BP5: No | BQ5: No
A6: 45001.629 | B6: laura_p_lencina@yahoo.com.ar | C6: Instituto santa ana | D6: 061123600 | E6: 1. Liceos / Normales / Colegios / Institutos orientados en ciencias naturales y/o exactas | F6: Cs Nat | G6: Privada | H6: Laura Lencina | I6: Cecilia Gagliano | K6: laura_p_lencina@yahoo.com.ar | L6: ÁREA METROPOLITANA DE BUENOS AIRES | M6: Villa Ballester | N6: 35 | O6: 6º Secundaria (Prov.) / 5º Media (CABA) | P6: 5 | Q6: 4 | R6: 2 | T6: Si | U6: No | V6: Martes 25/4 | W6: Si | X6: No | Y6: No | Z6: No | AA6: Si | AB6: No | AC6: No | AD6: No | AE6: No | AG6: Si | AH6: Si | AM6: Si
A7: 45001.625 | B7: laura_p_lencina@yahoo.com.ar | C7: Instituto Santa Ana | D7: 061123600 | E7: 1. Liceos / Normales / Colegios / Institutos orientados en ciencias naturales y/o exactas | F7: Cs sociales | G7: Privada | H7: Lencina Laura | I7: Gagliano Cecilia | K7: laura_p_lencina@yahoo.com.ar | L7: ÁREA METROPOLITANA DE BUENOS AIRES | M7: Villa Ballester | N7: 35 | O7: 6º Secundaria (Prov.) / 5º Media (CABA) | P7: 5 | Q7: 4 | R7: 2 | T7: Si | U7: No | V7: Martes 25/4 | W7: Si | X7: No | Y7: No | Z7: No | AA7: Si | AB7: No | AC7: No | AD7: No | AE7: No | AG7: Si | AH7: Si | AM7: Si | AP7: Si | AQ7: Si | AR7: No | AS7: No
A8: 45001.66 | B8: laura_p_lencina@yahoo.com.ar | C8: Instituto santa ana | D8: 061123600 | E8: 1. Liceos / Normales / Colegios / Institutos orientados en ciencias naturales y/o exactas | F8: Economía | G8: Privada | H8: Lencina Laura | I8: Gagliano Cecilia | J8: Cintia Merchan | K8: laura_p_lencina@yahoo.com.ar | L8: ÁREA METROPOLITANA DE BUENOS AIRES | M8: Villa Ballester | N8: 35 | O8: 6º Secundaria (Prov.) / 5º Media (CABA) | P8: 5 | Q8: 4 | R8: 2 | T8: Si | U8: No | V8: Martes 25/4 | W8: Si | X8: No | Y8: No | Z8: No | AA8: Si | AB8: Si | AC8: No | AD8: No | AE8: No | AG8: Si | AL8: Si | AM8: Si
A9: 45005.919 | B9: vicedireccionsagradocorazon@gmail.com | C9: Colegio Sagrado Corazon de jesus | D9: 061607500 | E9: 1. Liceos / Normales / Colegios / Institutos orientados en ciencias naturales y/o exactas | F9: Economía y Administración | G9: Privada | H9: Claudio Bedoya | I9: Gabriela Lujan | J9: Ileana Benedetti | K9: vicedireccionsagradocorazon@gmail.com | L9: CABA | M9: Quilmes | N9: 29 | O9: 6º Secundaria (Prov.) / 5º Media (CABA) | P9: 4 | Q9: 4 | R9: 5 | T9: Si | U9: No | V9: Miércoles 26/4 | AU9: Si | AV9: Si | AW9: No | AX9: No | AY9: Si | AZ9: No | BA9: No | BB9: No | BC9: No | BD9: No | BE9: No | BF9: No | BG9: Si | BH9: No | BI9: No | BJ9: No | BK9: No | BL9: No | BM9: Si | BN9: Si | BO9: No | BP9: No | BQ9: No | BR9: De ser necesario, para poder aprovechar todas las actividades, podemos quedarnos en el turno tarde también.
A10: 45000.828 | B10: d.ana.gomez@sanrafael.esc.edu.ar | C10: Instituto San Rafael (A-120) | D10: 020133700 | E10: 1. Liceos / Normales / Colegios / Institutos orientados en ciencias naturales y/o exactas | F10: Administración | G10: Privada | H10: Ana Paula Gómez Tascón | I10: Gabriel Giberti | K10: d.ana.gomez@sanrafael.esc.edu.ar | L10: CABA | M10: Villa Devoto | N10: 30 | O10: 6º Secundaria (Prov.) / 5º Media (CABA) | P10: 3 | Q10: 1 | R10: 10 | T10: Si | U10: No | V10: Miércoles 26/4 | AU10: No | AV10: Si | AW10: No | AX10: No | AY10: No | AZ10: No | BA10: No | BB10: No | BC10: No | BD10: Si | BI10: No | BJ10: No | BK10: No | BL10: No | BM10: No | BN10: Si | BO10: No | BP10: No | BQ10: No | BR10: Me encantaría q los estudiantes de 5to año vean algo de fractales pero si cada posta es de una hora, no nos darán los tiempos. Muchas gracias
A11: 45005.811 | B11: cami_zabala@yahoo.com.ar | C11: Instituto Madre Maria Luisa Clarac | D11: 060703300 | E11: 1. Liceos / Normales / Colegios / Institutos orientados en ciencias naturales y/o exactas | F11: Ciencias Naturales | G11: Privada | H11: Camila Zabala Lindermann | I11: Fernandez Mariela | J11: Gutierrez Karina | K11: cami_zabala@yahoo.com.ar | L11: ÁREA METROPOLITANA DE BUENOS AIRES | M11: Gregorio de Laferrere | N11: 38 | O11: 6º Secundaria (Prov.) / 5º Media (CABA) | P11: 3 | Q11: 4 | R11: 10 | T11: Si | U11: Si | V11: Martes 25/4 | W11: Si | X11: Si | Y11: Si | Z11: Si | AA11: Si | AB11: Si | AC11: Si | AD11: No | AE11: No | AF11: Si | AG11: Si | AH11: Si | AI11: No | AJ11: No | AK11: Si | AL11: Si | AM11: Si | AN11: No | AO11: No | AP11: Si | AQ11: Si | AR11: Si | AS11: No
A12: 45006.488 | B12: mpflosi@gmail.com | C12: Escuela del Sol | D12: 061296100 | E12: 1. Liceos / Normales / Colegios / Institutos orientados en ciencias naturales y/o exactas | F12: Ciencias naturales | G12: Privada | H12: Flosi Maria Paola | I12: Liliana Zacarías | J12: Ayelen Ferreyra | K12: mpflosi@gmail.com | L12: ÁREA METROPOLITANA DE BUENOS AIRES | M12: Berazategui | N12: 34 | O12: 6º Secundaria (Prov.) / 5º Media (CABA) | P12: 3 | Q12: 3 | R12: 10 | T12: Si | U12: No | V12: Martes 25/4 | W12: Si | X12: No | Y12: No | Z12: No | AA12: No | AB12: Si | AC12: No | AD12: No | AE12: No | AF12: No | AG12: No | AH12: No | AI12: Si | AJ12: No | AK12: No | AL12: No | AM12: Si | AN12: No | AO12: No | AP12: Si
A13: 45001.938 | B13: gonzalez.mercedes.sango@gmail.com | C13: Instituto San José | D13: 020169900 | E13: 1. Liceos / Normales / Colegios / Institutos orientados en ciencias naturales y/o exactas | F13: Gestión | G13: Privada | H13: Mercedes GONZALEZ | I13: Carolina Malter | J13: Diego Pozzi | K13: gonzalez.mercedes.sanjo@gmail.com | L13: CABA | M13: Balvanera | N13: 25 | O13: 6º Secundaria (Prov.) / 5º Media (CABA) | P13: 5 | Q13: 5 | R13: 10 | T13: Si | U13: Si | V13: Jueves 27/4 | BS13: No | BT13: No | BU13: No | BV13: No | BW13: No | BX13: Si | BY13: Si | BZ13: Si | CA13: Si | CB13: No | CC13: No | CD13: No | CE13: No | CF13: No | CG13: Si | CH13: Si | CI13: Si | CJ13: Si | CK13: Si | CL13: Si | CM13: Si | CN13: Si | CO13: Si | CP13: Según el horario que ustedes nos otorguen deseamos realizar una visita guiada, participar de las estaciones interactivas y del Arte Matemático.
A14: 45001.944 | B14: gonzalez.mercedes.sanjo@gmail.com | C14: Instituto San José | D14: 020169900 | E14: 1. Liceos / Normales / Colegios / Institutos orientados en ciencias naturales y/o exactas | F14: Gestión y economía | G14: Privada | H14: Mercedes Gonzalez | I14: Carolina Malter | J14: Diego Pozzi | K14: gonzalez.mercedes.sanjo@gmail.com | L14: CABA | M14: Balvanera | N14: 30 | O14: 6º Secundaria (Prov.) / 5º Media (CABA) | P14: 5 | Q14: 5 | R14: 10 | T14: Si | U14: Si | V14: Jueves 27/4 | BS14: No | BT14: No | BU14: No | BV14: Si | BW14: Si | BX14: Si | BY14: Si | BZ14: Si | CA14: Si | CB14: No | CC14: No | CD14: No | CE14: No | CF14: No | CG14: Si | CH14: Si | CI14: Si | CJ14: Si | CK14: Si | CL14: Si | CM14: Si | CN14: Si | CO14: Si | CP14: Según los horarios que ustedes dispongan deseamos participar de VISITA GUIADA, ESTACIONES INTERACTIVAS y ARTE MATEMÁTICO.
A15: 45002.413 | B15: yaninasdiaz86@gmail.com | C15: ENS N°2 "Mariano Acosta" | D15: 020086600 | E15: 1. Liceos / Normales / Colegios / Institutos orientados en ciencias naturales y/o exactas | F15: Normal | G15: Estatal | H15: Diaz Yanina | I15: Redin Clarisa | J15: Grandal Natalia | K15: yaninas.diaz@bue.edu.ar | L15: CABA | M15: Balvanera | N15: 35 | O15: 6º Secundaria (Prov.) / 5º Media (CABA) | P15: 4 | Q15: 4 | R15: 10 | T15: Si | U15: Si | V15: Martes 25/4 | W15: Si | X15: No | Y15: No | Z15: No | AA15: No | AB15: Si | AC15: Si | AD15: No | AE15: No | AF15: No | AG15: Si | AH15: Si | AI15: No | AJ15: No | AK15: No | AL15: Si | AM15: Si | AN15: No | AO15: No | AP15: Si | AQ15: Si | AR15: No | AS15: No
A16: 45002.44 | B16: gabrielanet@liceobrown.edu.ar | C16: LICEO NAVAL MILITAR ALMIRANTE GUILLERMO BROWN | D16: 069003200 | E16: 1. Liceos / Normales / Colegios / Institutos orientados en ciencias naturales y/o exactas | F16: Ciencias Naturales | G16: Estatal | H16: Gabriela Patricia Net | I16: Ariel Brandani | J16: Cynthia Castro | K16: gabrielanet@liceobrown.edu.ar | L16: ÁREA METROPOLITANA DE BUENOS AIRES | M16: Vicente López | N16: 23 | O16: 6º Secundaria (Prov.) / 5º Media (CABA) | P16: 4 | Q16: 3 | R16: 15 | T16: Si | U16: No | V16: Jueves 27/4 | BS16: Si | BT16: Si | BU16: No | BV16: Si | BW16: Si | BX16: No | BY16: No | BZ16: No | CA16: No | CB16: Si | CC16: Si | CD16: No | CE16: No | CF16: No | CG16: Si | CH16: Si | CI16: No | CJ16: No | CK16: No | CL16: Si | CM16: No | CN16: No | CO16: No
A17: 45004.53 | B17: mapaulasuarez@yahoo.com.ar | C17: INSTITUTO SOCIAL MILITAR DOCTOR DAMASO CENTENO | D17: 029003000 | E17: 1. Liceos / Normales / Colegios / Institutos orientados en ciencias naturales y/o exactas | F17: CIENCIAS NATURALES | G17: Estatal | H17: MARIA PAULA SUAREZ | I17: ADRIANA HOZ | J17: BRUNO BAGNIOLE | K17: mapaulasuarez@yahoo.com.ar | L17: CABA | M17: CABALLITO | N17: 40 | O17: 6º Secundaria (Prov.) / 5º Media (CABA) | P17: 5 | Q17: 5 | R17: 20 | T17: Si | U17: No | V17: Martes 25/4 | W17: Si | X17: Si | Y17: No | Z17: Si | AA17: Si | AB17: Si | AC17: No | AD17: No | AE17: No | AF17: Si | AG17: Si | AH17: Si | AI17: No | AJ17: No | AK17: Si | AL17: Si | AM17: Si | AN17: No | AO17: No | AP17: Si | AQ17: Si | AR17: No | AS17: No | AT17: COMO TODOS LOS AÑOS, ESPERAMOS PODER VISITARLOS CON ESTE NUEVO GRUPO DE ALUMNOS
A18: 45004.534 | B18: mapaulasuarez@yahoo.com.ar | C18: INSTITUTO SOCIAL MILITAR DOCTOR DAMASO CENTENO | D18: 029003000 | E18: 1. Liceos / Normales / Colegios / Institutos orientados en ciencias naturales y/o exactas | F18: CIENCIAS NATURALES | G18: Estatal | H18: LISETTE MENDEZ | I18: FLORENCIA LOPEZ DE VOLVER | J18: ALVARO CORTES CONTI | K18: mapaulasuarez@yahoo.com.ar | L18: CABA | M18: CABALLITO | N18: 40 | O18: 6º Secundaria (Prov.) / 5º Media (CABA) | P18: 5 | Q18: 5 | R18: 20 | T18: Si | U18: No | V18: Miércoles 26/4 | AU18: Si | AV18: Si | AW18: No | AX18: Si | AY18: Si | AZ18: Si | BA18: No | BB18: No | BC18: No | BD18: Si | BE18: Si | BF18: Si | BG18: No | BH18: No | BI18: Si | BJ18: Si | BK18: Si | BL18: No | BM18: No | BN18: Si | BO18: Si | BP18: No | BQ18: No
A19: 45004.538 | B19: mapaulasuarez@yahoo.com.ar | C19: INSTITUTO SOCIAL MILITAR DOCTOR DAMASO CENTENO | D19: 029003000 | E19: 1. Liceos / Normales / Colegios / Institutos orientados en ciencias naturales y/o exactas | F19: CIENCIAS NATURALES | G19: Estatal | H19: FLAVIA TERRIZZANO | I19: ANTONIO VUISSO | J19: ESTEFANIA DENIS | K19: mapaulasuarez@yahoo.com.ar | L19: CABA | M19: CABALLITO | N19: 35 | O19: 6º Secundaria (Prov.) / 5º Media (CABA) | P19: 5 | Q19: 5 | R19: 20 | T19: Si | U19: No | V19: Jueves 27/4 | BS19: Si | BT19: Si | BU19: No | BV19: Si | BW19: Si | BX19: Si | BY19: No | BZ19: No | CA19: No | CB19: Si | CC19: Si | CD19: Si | CE19: No | CF19: No | CG19: Si | CH19: Si | CI19: Si | CJ19: No | CK19: No | CL19: Si | CM19: Si | CN19: No | CO19: No
A20: 45000.748 | B20: patferre@gmail.com | C20: Colegio de la Reconquista | D20: 061629100 | E20: 1. Liceos / Normales / Colegios / Institutos orientados en ciencias naturales y/o exactas | F20: Cs Naturales | G20: Privada | H20: Patricia Ferreyra | I20: Karina Barrientos | J20: Liliana Descalzo | K20: patferre@gmail.com | L20: ÁREA METROPOLITANA DE BUENOS AIRES | M20: Tigre/Tigre | N20: 30 | O20: 6º Secundaria (Prov.) / 5º Media (CABA) | P20: 5 | Q20: 1 | R20: 20 | T20: Si | U20: No | V20: Martes 25/4 | W20: Si | X20: No | Y20: Si | Z20: No | AA20: Si | AB20: Si | AC20: Si | AD20: No | AE20: No | AF20: No | AG20: No | AH20: Si | AI20: No | AJ20: No | AK20: No | AL20: Si | AM20: Si | AN20: Si | AO20: No
A21: 45001.648 | B21: valeriatardioli@gmail.com | C21: Instituto Proyección XXI | D21: 060455500 | E21: 1. Liceos / Normales / Colegios / Institutos orientados en ciencias naturales y/o exactas | F21: Sociales | G21: Privada | H21: Paola Flossi | I21: Estrella Lopez | J21: Valeria Tardioli | K21: valeriatardioli@gmail.com | L21: ÁREA METROPOLITANA DE BUENOS AIRES | M21: Bernal oeste | N21: 31 | O21: 6º Secundaria (Prov.) / 5º Media (CABA) | P21: 4 | Q21: 1 | R21: 25 | T21: Si | U21: Si | V21: Jueves 27/4 | BS21: No | BT21: No | BU21: Si | BV21: Si | BW21: No | BX21: No | BY21: No | BZ21: No | CA21: No | CB21: No | CC21: No | CD21: Si | CE21: No | CF21: No | CG21: No | CH21: Si | CI21: No | CJ21: No | CK21: No | CL21: Si | CM21: No | CN21: No | CO21: No
A22: 45001.649 | B22: valeriatardioli@gmail.com | C22: Instituto Proyección XXI | D22: 060455500 | E22: 1. Liceos / Normales / Colegios / Institutos orientados en ciencias naturales y/o exactas | F22: Sociales | G22: Privada | H22: Paola Flossi | I22: Estrella Lopez | J22: Valeria Tardioli | K22: valeriatardioli@gmail.com | L22: ÁREA METROPOLITANA DE BUENOS AIRES | M22: Bernal Oeste | N22: 25 | O22: 6º Secundaria (Prov.) / 5º Media (CABA) | P22: 4 | Q22: 1 | R22: 25 | T22: Si | U22: Si | V22: Jueves 27/4 | BS22: No | BT22: No | BU22: Si | BV22: Si | BW22: No | BX22: No | BY22: No | BZ22: No | CA22: No | CB22: No | CC22: No | CD22: Si | CE22: No | CF22: No | CG22: No | CH22: Si | CI22: No | CJ22: No | CK22: No | CL22: Si | CM22: No | CN22: No | CO22: No
A23: 45001.395 | B23: betsabescerba@gmail.com | C23: EES N°15 | D23: 061805000 | E23: 1. Liceos / Normales / Colegios / Institutos orientados en ciencias naturales y/o exactas | F23: Ciencias naturales | G23: Estatal | H23: Aldana Scerba | I23: Griselda Mendez | J23: Romina Grillo | K23: betsabescerba@gmail.com | L23: ÁREA METROPOLITANA DE BUENOS AIRES | M23: Hurlingham | N23: 11 | O23: 6º Secundaria (Prov.) / 5º Media (CABA) | P23: 2 | Q23: 1 | R23: 30 | T23: Si | U23: No | V23: Jueves 27/4 | BS23: Si | BT23: No | BU23: No | BV23: No | BW23: Si | BX23: No | BY23: No | BZ23: No | CA23: No | CB23: No | CC23: No | CD23: No | CE23: No | CF23: No | CG23: No | CH23: No | CI23: Si | CJ23: No | CK23: No | CL23: No | CM23: No | CN23: No | CO23: No
A24: 45005.965 | B24: mcappussi@yahoo.com.ar | C24: EES n 2 Francisco Ramírez | D24: 061024600 | E24: 1. Liceos / Normales / Colegios / Institutos orientados en ciencias naturales y/o exactas | F24: Economia | G24: Estatal | H24: Mercedes Cappussi | I24: Guillen Herrera Marisol | K24: mcappussi@yahoo.com.ar | L24: ÁREA METROPOLITANA DE BUENOS AIRES | M24: Lanus | N24: 25 | O24: 6º Secundaria (Prov.) / 5º Media (CABA) | P24: 4 | Q24: 5 | R24: 30 | T24: Si | U24: Si | V24: Miércoles 26/4 | AU24: No | AV24: Si | AW24: No | AX24: Si | AY24: No | AZ24: No | BA24: No | BB24: No | BC24: No | BD24: No | BE24: Si | BF24: Si | BG24: No | BH24: No | BL24: Si | BQ24: Si
A25: 45000.835 | B25: Anabella.caceres@bue.edu.ar | C25: Escuela Normal Superior n5 "Martin Miguel de Güemes" | D25: 020132800 | E25: 1. Liceos / Normales / Colegios / Institutos orientados en ciencias naturales y/o exactas | F25: Matematica y Fisica | G25: Estatal | H25: A. Carolina Cáceres | I25: Lorena Paniagua | J25: Gustavo Catuara | K25: Anabella.caceres@bue.edu.ar | L25: CABA | M25: Barracas | N25: 15 | O25: 6º Secundaria (Prov.) / 5º Media (CABA) | P25: 3 | Q25: 3 | R25: 30 | T25: Si | U25: No | V25: Martes 25/4 | W25: Si | X25: No | Y25: No | Z25: No | AA25: No | AB25: Si | AC25: Si | AD25: No | AE25: No | AH25: Si | AL25: Si | AR25: Si
A26: 45005.835 | B26: mcappussi@yahoo.com.ar | C26: E.E.S N°2 Francisco Ramírez | D26: 061024600 | E26: 1. Liceos / Normales / Colegios / Institutos orientados en ciencias naturales y/o exactas | F26: Naturales y Economía | G26: Estatal | H26: Mercedes Cappussi | I26: Romina Fonés | K26: mcappussi@yahoo.com.ar | L26: ÁREA METROPOLITANA DE BUENOS AIRES | M26: Lanus | N26: 35 | O26: 6º Secundaria (Prov.) / 5º Media (CABA) | P26: 4 | Q26: 5 | R26: 30 | T26: Si | U26: Si | V26: Miércoles 26/4 | AU26: No | AV26: Si | AW26: No | AX26: Si | AY26: No | AZ26: No | BA26: No | BB26: No | BC26: No | BD26: No | BE26: Si | BF26: Si | BG26: No | BH26: No | BL26: Si | BQ26: Si | BR26: Es Sexto con Orientación a Naturales
A27: 45000.738 | B27: silveiga@yahoo.com.ar | C27: ENS Nº 4 ESTANISLAO ZEBALLOS | D27: 020129700 | E27: 1. Liceos / Normales / Colegios / Institutos orientados en ciencias naturales y/o exactas | F27: Matemática y física | G27: Estatal | H27: Silvia Ana Veiga | I27: Gisela Serrano | J27: Mónica Sivila | K27: silveiga@yahoo.com.ar | L27: CABA | M27: Caballito | N27: 23 | O27: 6º Secundaria (Prov.) / 5º Media (CABA) | P27: 4 | Q27: 4 | R27: 50 | S27: Vamos a la semana de la Matemática todos los años con nuestros 5º bach matemática y Física | T27: Si | U27: No | V27: Martes 25/4 | W27: Si | X27: No | Y27: No | Z27: No | AA27: Si | AB27: No | AC27: No | AD27: No | AE27: No | AF27: No | AG27: No | AH27: Si | AI27: No | AJ27: No | AK27: No | AL27: No | AM27: No | AN27: No | AO27: No | AP27: No | AQ27: No | AR27: No | AS27: No | AT27: Vamos con los chicos de 5º orientación Matemática y Física todos los años desde que comenzó la semana de la Matemática.
A28: 45001.521 | B28: mariade.castro@bue.edu.ar | C28: Colegio N° 19 DE 17 "Luis Pasteur" | D28: 020014300 | E28: 1. Liceos / Normales / Colegios / Institutos orientados en ciencias naturales y/o exactas | F28: Naturales | G28: Estatal | H28: Ángeles Castro | I28: Verónica Marrano | K28: mariade.castro@bue.edu.ar | L28: CABA | M28: Villa Devoto | N28: 35 | O28: 6º Secundaria (Prov.) / 5º Media (CABA) | P28: 4 | Q28: 1 | R28: 50 | T28: No | U28: Si | V28: Jueves 27/4 | BS28: No | BT28: Si | BU28: Si | BV28: No | BW28: No | BX28: No | BY28: Si | BZ28: No | CA28: No | CB28: No | CC28: No | CD28: No | CE28: No | CF28: Si | CG28: No | CH28: No | CI28: No | CJ28: No | CK28: Si | CL28: No | CM28: No | CN28: No | CO28: Si
A29: 45001.84 | B29: jesihoyos@hotmail.com | C29: Instituto Manuel Dorrego | D29: 061270500 | E29: 1. Liceos / Normales / Colegios / Institutos orientados en ciencias naturales y/o exactas | F29: Sociales | G29: Privada | H29: Jesica Hoyos | I29: Claudia Palumbo | J29: Horacio Giordano | K29: jesihoyos@hotmail.com | L29: ÁREA METROPOLITANA DE BUENOS AIRES | M29: Bella Vista | N29: 20 | O29: 6º Secundaria (Prov.) / 5º Media (CABA) | P29: 4 | Q29: 3 | R29: 50 | T29: Si | U29: No | V29: Miércoles 26/4 | AU29: Si | AV29: Si | AW29: Si | AX29: No | AY29: Si | AZ29: No | BA29: Si | BB29: No | BC29: No | BD29: No | BE29: Si | BF29: Si | BG29: No | BH29: No | BJ29: Si | BK29: Si | BN29: Si | BO29: Si
A30: 45003.708 | B30: gustavo.rolhaiser@hotmail.com | C30: Dr Manuel Obarrio EESN° 13 | D30: 061228000 | E30: 1. Liceos / Normales / Colegios / Institutos orientados en ciencias naturales y/o exactas | F30: Ciencias Naturales | G30: Estatal | H30: Rolhaiser Gustavo Nicolás | I30: Quiroga Valeria Rocío | J30: Mango María de los Ángeles | K30: gustavo.rolhaiser@hotmail.com | L30: ÁREA METROPOLITANA DE BUENOS AIRES | M30: San Isidro | N30: 30 | O30: 6º Secundaria (Prov.) / 5º Media (CABA) | P30: 1 | Q30: 4 | R30: 60 | T30: Si | U30: No | V30: Martes 25/4 | W30: Si | X30: Si | Y30: No | Z30: Si | AA30: Si | AB30: Si | AC30: No | AD30: No | AE30: No | AF30: Si | AG30: Si | AH30: Si | AI30: No | AJ30: No | AK30: Si | AL30: Si | AM30: Si | AN30: No | AO30: No | AP30: Si | AQ30: Si | AR30: No | AS30: No | AT30: Ingrese los mismos horarios en todos los talleres, ya que en dónde quede lugar disponible para que podamos asistir y participar, les agradecemos.
A31: 45001.751 | B31: valeria.shuman@bue.edu.ar | C31: Ens 6 Vicente Lopez y PlaneS | D31: 020071700 | E31: 1. Liceos / Normales / Colegios / Institutos orientados en ciencias naturales y/o exactas | F31: Matemática y Fisica | G31: Estatal | H31: Valeria Shuman | I31: Monica Robledo | J31: Kelly Dabek | K31: valeria.shuman@bue.edu.ar | L31: CABA | M31: Palermo | N31: 27 | O31: 6º Secundaria (Prov.) / 5º Media (CABA) | P31: 4 | Q31: 3 | R31: 60 | T31: Si | U31: No | V31: Miércoles 26/4 | AU31: Si | AV31: No | AW31: No | AX31: No | AY31: Si | AZ31: No | BA31: No | BB31: No | BC31: No | BD31: No | BE31: No | BF31: Si | BG31: No | BH31: No | BI31: No | BJ31: No | BK31: Si | BL31: No | BM31: No | BN31: No | BO31: No | BP31: No | BQ31: No
A32: 45005.52 | B32: macharreun@yahoo.com.ar | C32: Escuela Secundaria N°11 Martin Miguel de Guemes | D32: 060766200 | E32: 1. Liceos / Normales / Colegios / Institutos orientados en ciencias naturales y/o exactas | F32: Bachiller en ciencias naturales | G32: Estatal | H32: Charreun Monica | I32: Paola Moccia | K32: macharreun@yahoo.com.ar | L32: ÁREA METROPOLITANA DE BUENOS AIRES | M32: Monte Chingolo. Lanús Este | N32: 30 | O32: 6º Secundaria (Prov.) / 5º Media (CABA) | P32: 3 | Q32: 3 | R32: 70 | T32: No | U32: No | V32: Jueves 27/4 | BS32: Si | BT32: Si | BU32: Si | BV32: No | BW32: No | BX32: No | BY32: Si | BZ32: No | CA32: No | CB32: No | CC32: No | CD32: No | CE32: No | CF32: Si | CJ32: Si | CM32: No | CP32: En el mes de febrero se solicitó el subsidio para poder ir con los alumnos, ya que se nos hace muy dificil economicamente solventar el alquiler de un micro.
A33: 45000.686 | B33: andreromero6@abc.gob.ar | C33: Secundaria 2 "Hernando Arias de Saavedra" | D33: 060765300 | E33: 1. Liceos / Normales / Colegios / Institutos orientados en ciencias naturales y/o exactas | F33: Ciencias Naturales | G33: Estatal | H33: ROMERO ANDREA | I33: QUINTANA ANDREA | J33: VARGAS ELIZABETH | K33: andreromero6@abc.gob.ar | L33: ÁREA METROPOLITANA DE BUENOS AIRES | M33: Victoria, San Fernando | N33: 34 | O33: 6º Secundaria (Prov.) / 5º Media (CABA) | P33: 2 | Q33: 2 | R33: 75 | T33: Si | U33: No | V33: Miércoles 26/4 | AU33: Si | AV33: Si | AW33: Si | AX33: Si | AY33: Si | AZ33: Si | BA33: Si | BB33: Si | BC33: No | BD33: Si | BE33: Si | BF33: Si | BG33: Si | BI33: Si | BJ33: Si | BK33: Si | BL33: Si | BN33: Si | BO33: Si | BP33: Si
A34: 45000.853 | B34: santiagoandreanoemi@gmail.com | C34: Escuela de Educación Secundaria N °3 Francisco Salustio | D34: 061000200 | E34: 1. Liceos / Normales / Colegios / Institutos orientados en ciencias naturales y/o exactas | F34: Bachillerato en Cs Sociales y en Cs Naturales | G34: Estatal | H34: Andrea Santiago | I34: Desireé Mandile | J34: Gabriela Cortés | K34: santiagoandreanoemi@gmail.com | L34: ÁREA METROPOLITANA DE BUENOS AIRES | M34: Quilmes Oeste | N34: 35 | O34: 6º Secundaria (Prov.) / 5º Media (CABA) | P34: 2 | Q34: 3 | R34: 80 | S34: La salida educativa es parte del proyecto institucional "Matemática: vocación científica posible" | T34: Si | U34: Si | V34: Martes 25/4 | W34: Si | X34: Si | Y34: Si | Z34: No | AA34: No | AB34: No | AC34: Si | AD34: No | AE34: No | AF34: No | AG34: Si | AH34: No | AI34: No | AJ34: No | AK34: No | AL34: No | AM34: No | AN34: No | AO34: Si | AP34: No | AQ34: No | AR34: Si | AS34: No | AT34: Priorizo visita antes que charla a las 14 hs
A35: 45005.879 | B35: abasoalto@abc.gob.ar | C35: ESCUELA DE EDUCACIÓN SECUNDARIA Nº21 JOSÉ HERNANDEZ | D35: 060861200 | E35: 1. Liceos / Normales / Colegios / Institutos orientados en ciencias naturales y/o exactas | F35: Ciencias Naturales | G35: Estatal | H35: Ana Vanina Basoalto | I35: Noelia Colman | J35: Claudia Escudero | K35: basoaltoanav@gmail.com | L35: ÁREA METROPOLITANA DE BUENOS AIRES | M35: Castelar | N35: 35 | O35: 6º Secundaria (Prov.) / 5º Media (CABA) | P35: 5 | Q35: 5 | R35: 80 | S35: Esperamos la asignación de la inscripción dado que son muchos los estudiantes que desean continuar sus estudios en Exactas | T35: Si | U35: Si | V35: Martes 25/4 | W35: Si | X35: No | Y35: No | Z35: No | AA35: Si | AB35: No | AC35: Si | AD35: No | AE35: No | AH35: Si | AN35: Si | AS35: Si
A36: 45006.47 | B36: abasoalto@abc.gob.ar | C36: ESCUELA DE EDUCACIÓN SECUNDARIA Nº21 JOSÉ HERNANDEZ | D36: 060861200 | E36: 1. Liceos / Normales / Colegios / Institutos orientados en ciencias naturales y/o exactas | F36: Ciencias Naturales | G36: Estatal | H36: Ana Basoalto | I36: Noelia Colman | J36: Gustavo Oliveira | K36: abasoalto@abc.gob.ar | L36: ÁREA METROPOLITANA DE BUENOS AIRES | M36: Castelar | N36: 35 | O36: 6º Secundaria (Prov.) / 5º Media (CABA) | P36: 5 | Q36: 5 | R36: 80 | S36: Esperamos la asignación de la inscripción dado que son muchos los estudiantes que desean continuar sus estudios en Exactas | T36: Si | U36: Si | V36: Martes 25/4 | W36: Si | X36: Si | Y36: No | Z36: Si | AA36: No | AB36: Si | AC36: No | AD36: Si | AE36: No | AG36: Si | AI36: Si | AK36: Si | AN36: Si | AO36: Si | AR36: Si | AS36: Si
A37: 45001.377 | B37: mariaa.sosa@bue.edu.ar | C37: Liceo N° 01 Jose Figueroa Alcorta DE 02 | D37: 020074400 | E37: 1. Liceos / Normales / Colegios / Institutos orientados en ciencias naturales y/o exactas | F37: Ciencias Naturales y Exactas | G37: Estatal | H37: Jonathan España | I37: Maria Andrea Sosa | J37: Nicolas Lovece | K37: mariaa.sosa@bue.edu.ar | L37: CABA | M37: Barrio Norte | N37: 40 | O37: 6º Secundaria (Prov.) / 5º Media (CABA) | P37: 4 | Q37: 3 | R37: 80 | T37: Si | U37: Si | V37: Jueves 27/4 | BS37: Si | BT37: Si | BU37: Si | BV37: Si | BW37: Si | BX37: Si | BY37: Si | BZ37: Si | CA37: Si | CB37: Si | CC37: Si | CD37: Si | CE37: Si | CF37: Si | CG37: No | CH37: No | CI37: No | CJ37: No | CK37: No | CL37: Si | CM37: Si | CN37: Si | CO37: Si
A38: 45002.813 | B38: gebs2323@gmail.com | C38: Cant. 2021 Buenos Aires 61856700 ESCUELA DE EDUCACIÓN SECUNDARIA Nº108 REAÑO 6748 LA LOMA GREGORIO DE LAFERRERE LA MATANZA Urbano Estatal Ed. Común Secundaria Común Sin datos 1 | D38: 061856700 | E38: 1. Liceos / Normales / Colegios / Institutos orientados en ciencias naturales y/o exactas | F38: Comunicación | G38: Estatal | H38: Noelia Lezica | I38: Gloria Benítez | J38: Mariela Soto | K38: gebs2323@gmail.com | L38: ÁREA METROPOLITANA DE BUENOS AIRES | M38: La Loma/ Gregorio de Laferrere | N38: 35 | O38: 6º Secundaria (Prov.) / 5º Media (CABA) | P38: 2 | Q38: 3 | R38: 80 | S38: Son chicos que demuestran interés y curiosidad por conocer y progresar. La falta de conectividad los límita para investigar. Ellos plantearon también la posibilidad de visitar y conocer universidades y ofertas académicas. | T38: No | U38: Si | V38: Jueves 27/4 | BS38: No | BT38: Si | BU38: Si | BV38: No | BW38: No | BX38: Si | BY38: Si | BZ38: Si | CA38: Si | CB38: No | CC38: No | CD38: Si | CE38: Si | CF38: Si | CG38: No | CH38: Si | CI38: Si | CJ38: Si | CK38: Si | CL38: No | CM38: Si | CN38: Si | CO38: Si | CP38: Debido a la distancia y tiempo de viaje estimamos no llegar para las actividades de las 9 30 hs. Si la charla de geometría proyectiva se presenta también en otro horario nos gustaría participar.
A39: 45005.923 | B39: marisofernandez3@abc.gob.ar | C39: E.E.S N°45 | D39: 061804300 | E39: 1. Liceos / Normales / Colegios / Institutos orientados en ciencias naturales y/o exactas | F39: MATEMATICA | G39: Estatal | H39: CLAUDIA PACHECO | I39: FERNADEZ MARISOL | J39: TERESA CULLARI | K39: marisofernandez3@abc.gob.ar | L39: ÁREA METROPOLITANA DE BUENOS AIRES | M39: villa sarmiento | N39: 28 | O39: 6º Secundaria (Prov.) / 5º Media (CABA) | P39: 3 | Q39: 3 | R39: 80 | T39: Si | U39: No | V39: Jueves 27/4 | BS39: Si | BT39: Si | BU39: Si | BV39: No | BW39: Si | BX39: Si | BY39: Si | BZ39: Si | CA39: No | CC39: Si | CD39: Si | CE39: Si | CH39: Si | CI39: Si | CJ39: Si | CL39: Si | CM39: Si | CN39: Si
A40: 45004.017 | B40: a.m.sosa@hotmail.com | C40: Escuela de Educación Secundaria N° 120 | D40: 061846600 | E40: 1. Liceos / Normales / Colegios / Institutos orientados en ciencias naturales y/o exactas | F40: Ciencias Naturales | G40: Estatal | H40: Álvaro Miguel Sosa | I40: Jorge Andrada | J40: Silvana Alderete | K40: a.m.sosa@hotmail.com | L40: ÁREA METROPOLITANA DE BUENOS AIRES | M40: Virrey del Pino | N40: 35 | O40: 6º Secundaria (Prov.) / 5º Media (CABA) | P40: 2 | Q40: 2 | R40: 90 | S40: Estamos con muchas ganas de asistir nuevamente a la facultad, es de gran aprendizaje la experiencia para mis alumnos, dado que no tienen la posibilidad de ir por sus propios medios. Ojalá nos den una vacante para la visita, ya que sería nuestra primera semana de la Matemática. Saludos. | T40: Si | U40: No | V40: Miércoles 26/4 | AU40: No | AV40: Si | AW40: No | AX40: No | AY40: Si | AZ40: No | BA40: No | BB40: No | BC40: No | BD40: Si | BE40: No | BF40: No | BG40: No | BH40: No | BI40: Si | BJ40: No | BK40: No | BL40: No | BM40: No | BN40: No | BO40: No | BP40: No | BQ40: No | BR40: Me anote en el mismo horario en talleres y Arte matemático porque indican que el cupo es reducido. Voy a ir con 35 alumnos que podrían dividirse en dos grupos para participar en ambos talleres.
A41: 45006.449 | B41: gallinamensajera@hotmail.com | C41: Escuela de educación secundaria n° 2 " Juan Lavalle" | D41: 060554600 | E41: 1. Liceos / Normales / Colegios / Institutos orientados en ciencias naturales y/o exactas | F41: Ciencias naturales | G41: Estatal | H41: Cristina morandi | I41: Juan ceballos | J41: Vanesa | K41: gallinamensajera@hotmail.com | L41: ÁREA METROPOLITANA DE BUENOS AIRES | M41: Villa tesei | N41: 35 | O41: 6º Secundaria (Prov.) / 5º Media (CABA) | P41: 3 | Q41: 2 | R41: 90 | T41: Si | U41: Si | V41: Miércoles 26/4 | AU41: No | AV41: Si | AW41: No | AX41: No | AY41: Si | AZ41: Si | BA41: Si | BB41: No | BC41: No | BD41: No | BE41: Si | BF41: No | BG41: No | BH41: No | BI41: No | BJ41: No | BK41: No | BL41: No | BM41: No | BN41: Si | BO41: Si | BP41: No | BQ41: No
A42: 45000.897 | B42: analiairiel1985@gmail.com | C42: Escuela de Educación Secundaria nro 32 | D42: 061849500 | E42: 1. Liceos / Normales / Colegios / Institutos orientados en ciencias naturales y/o exactas | F42: Economía y Administración/ arte-musica | G42: Estatal | H42: Romero Iriel | I42: Villaroya Mirta | J42: Paola Juarez | K42: analiairiel1985@gmail.com | L42: ÁREA METROPOLITANA DE BUENOS AIRES | M42: Berazategui | N42: 35 | O42: 6º Secundaria (Prov.) / 5º Media (CABA) | P42: 4 | Q42: 1 | R42: 95 | S42: Venimos en transporte público ya que no nos salió el subsidio. Por favor considerar eso a la hora de asignar las actividades. Grqcias | T42: Si | U42: Si | V42: Jueves 27/4 | BS42: No | BT42: No | BU42: Si | BV42: No | BW42: No | BX42: No | BY42: Si | BZ42: No | CA42: No | CB42: No | CC42: No | CD42: Si | CE42: No | CF42: No | CG42: No | CH42: Si | CI42: No | CJ42: No | CK42: No | CL42: No | CM42: No | CN42: No | CO42: Si | CP42: Ojalá podamos participar en todo gracias
A43: 45005.589 | B43: rosana.dionisio@bue.edu.ar | C43: ESC. DE COM. N° 33 MAIPU DE 18 -Prof Rosana Dionisio | D43: 020068000 | E43: 10. Liceos / Normales / Colegios / Institutos de otras orientaciones | F43: Administración y economía | G43: Estatal | H43: Dionisio Rosana | I43: Zarlenga Silvina | J43: Zambonini Verónica | K43: rosana.dionisio@bue.edu.ar | L43: CABA | M43: Monte Castro | N43: 35 | O43: 6º Secundaria (Prov.) / 5º Media (CABA) | P43: 4 | Q43: 4 | R43: 40 | T43: Si | U43: No | V43: Jueves 27/4 | BS43: Si | BT43: No | BU43: No | BV43: No | BW43: Si | BX43: No | BY43: No | BZ43: No | CA43: No | CB43: No | CC43: No | CD43: Si | CE43: No | CF43: No | CG43: No | CH43: No | CI43: No | CJ43: No | CK43: No | CL43: Si | CM43: Si | CN43: No | CO43: No
A44: 45003.415 | B44: yesicagambino@cesfj.edu.ar | C44: CENTRO EDUCATIVO SAN FRANCISCO JAVIER (A-136) | D44: 020010000 | E44: 10. Liceos / Normales / Colegios / Institutos de otras orientaciones | F44: Bachiller con orientación en Economía y Administración | G44: Privada | H44: Yesica Paola Gambino | I44: Daniela Menzulio | J44: Marcos Cayol | K44: yesicagambino@cesfj.edu.ar | L44: CABA | M44: Palermo | N44: 15 | O44: 6º Secundaria (Prov.) / 5º Media (CABA) | P44: 3 | Q44: 2 | R44: 40 | S44: Se trata de un colegio parroquial con 100% de subvención estatal. | T44: No | U44: Si | V44: Jueves 27/4 | BS44: No | BT44: No | BU44: Si | BV44: No | BW44: No | BX44: No | BY44: No | BZ44: Si | CA44: Si | CB44: No | CC44: No | CD44: No | CE44: Si | CF44: Si | CG44: No | CH44: No | CI44: No | CJ44: Si | CK44: Si | CL44: No | CM44: No | CN44: Si | CO44: Si
A45: 45005.865 | B45: barrioluis92@gmail.com | C45: ESC. DE COM. Nº 20 DR. JUAN AGUSTIN GARCIA DE 14 | D45: 020015900 | E45: 10. Liceos / Normales / Colegios / Institutos de otras orientaciones | F45: Comercial | G45: Estatal | H45: Luis Octavio Barrio | I45: Mirta Filgueira | K45: barrioluis92@gmail.com | L45: CABA | M45: Paternal | N45: 20 | O45: 6º Secundaria (Prov.) / 5º Media (CABA) | P45: 4 | Q45: 2 | R45: 40 | T45: Si | U45: No | V45: Miércoles 26/4 | AU45: Si | AV45: Si | AW45: No | AX45: Si | AY45: Si | AZ45: Si | BA45: No | BB45: No | BC45: No | BD45: Si | BE45: Si | BF45: Si | BG45: No | BH45: No | BI45: No | BJ45: No | BK45: No | BL45: No | BM45: No | BN45: Si | BO45: Si | BR45: Actividades prioritarias: 9:30: Desorden ordenado, ¡qué caos es esto! 10:30: ESTACIONES INTERACTIVAS 11:30: VISITA GUIADA
A46: 45000.705 | B46: mariadelcarmencandeloro1@gmail.com | C46: INSTITUTO SAGRADA FAMILIA A 70 | D46: 020100400 | E46: 10. Liceos / Normales / Colegios / Institutos de otras orientaciones | F46: Economía y Administración | G46: Privada | H46: María del Carmen Candeloro | I46: Guadalupe Dominguez | J46: Victor Sacco | K46: mariadelcarmencandeloro1@gmail.com | L46: CABA | M46: Villa General Mitre | N46: 30 | O46: 6º Secundaria (Prov.) / 5º Media (CABA) | P46: 2 | Q46: 1 | R46: 40 | T46: Si | U46: No | V46: Miércoles 26/4 | AU46: Si | AV46: No | AW46: No | AX46: No | AY46: Si | AZ46: No | BA46: No | BB46: No | BC46: No | BD46: No | BE46: No | BF46: No | BG46: No | BH46: No | BI46: No | BJ46: No | BK46: Si | BL46: No | BM46: No | BN46: No | BO46: No | BP46: No | BQ46: No
A47: 45000.708 | B47: mariadelcarmencandeloro1@gmail.com | C47: INSTITUTO SAGRADA FAMILIA A 70 | D47: 020100400 | E47: 9. Liceos / Normales / Colegios / Institutos orientados en ciencias sociales y/o humanidades | F47: Sociales y Humanidades | G47: Privada | H47: María del Carmen Candeloro | I47: Guadalupe Dominguez | J47: Victor Sacco | K47: mariadelcarmencandeloro1@gmail.com | L47: CABA | M47: Villa General Mitre | N47: 30 | O47: 6º Secundaria (Prov.) / 5º Media (CABA) | P47: 2 | Q47: 1 | R47: 40 | T47: Si | U47: No | V47: Miércoles 26/4 | AU47: Si | AV47: No | AW47: No | AX47: No | AY47: Si | AZ47: No | BA47: No | BB47: No | BC47: No | BD47: No | BE47: No | BF47: No | BG47: No | BH47: No | BI47: No | BJ47: No | BK47: Si | BL47: No | BM47: No | BN47: No | BO47: No | BP47: No | BQ47: No
A48: 45003.74 | B48: secretaria.secundaria@sangregorio.edu.ar | C48: instituto educativo san gregorio el iluminador | D48: 020074000 | E48: 10. Liceos / Normales / Colegios / Institutos de otras orientaciones | F48: Economía y administración | G48: Privada | H48: Adriana Margossian | I48: Adriana Margossian | J48: Mariana crespo | K48: secretaria.secundaria@sangregorio.edu.ar | L48: CABA | M48: Palermo | N48: 25 | O48: 6º Secundaria (Prov.) / 5º Media (CABA) | P48: 4 | Q48: 4 | R48: 30 | S48: A pesar de tener la orientación de economía y administración, tenes alumnos interesados en carreras de ciencias exactas y naturales, y desde las materias matematica y química y física fomentamos estas ciencias | T48: Si | U48: No | V48: Martes 25/4 | W48: Si | X48: No | Y48: No | Z48: No | AA48: Si | AB48: Si | AC48: No | AD48: No | AE48: No | AF48: No | AG48: Si | AH48: Si | AI48: No | AJ48: No | AK48: No | AL48: Si | AM48: Si | AN48: No | AO48: No | AP48: Si | AQ48: Si | AR48: No | AS48: No
A49: 45002.545 | B49: secretaria.secundaria@sangregorio.edu.ar | C49: Instituto educativo san gregorio el iluminador | D49: 020074000 | E49: 10. Liceos / Normales / Colegios / Institutos de otras orientaciones | F49: Economía y administración | G49: Privada | H49: Adriana Margossian | I49: Adriana Maegossian | J49: Mariana Crespo | K49: secretaria.secundaria@sangregorio.edu.ar | L49: CABA | M49: Palermo | N49: 24 | O49: 6º Secundaria (Prov.) / 5º Media (CABA) | P49: 4 | Q49: 4 | R49: 30 | S49: A pesar de tener la orientación de economía y administración, tenes alumnos interesados en carreras de ciencias exactas y naturales, y desde las materias matematica y química y física fomentamos estas ciencias | T49: Si | U49: No | V49: Martes 25/4 | W49: Si | X49: No | Y49: Si | Z49: No | AA49: Si | AB49: Si | AC49: No | AD49: No | AE49: No | AF49: No | AG49: Si | AH49: Si | AI49: No | AJ49: No | AK49: No | AL49: Si | AM49: Si | AN49: No | AO49: No | AP49: Si | AQ49: Si | AR49: No | AS49: No
A50: 45000.77 | B50: natalia.grandal@bue.edu.ar | C50: ENS EN LENGUAS VIVAS Nº 02 MARIANO ACOSTA DE 06 | D50: 020086600 | E50: 9. Liceos / Normales / Colegios / Institutos orientados en ciencias sociales y/o humanidades | F50: Físico-Matemático | G50: Estatal | H50: Natalia Grandal | I50: Clarisa Redin | K50: natalia.grandal@bue.edu.ar | L50: CABA | M50: Balvanera | N50: 10 | O50: 6º Secundaria (Prov.) / 5º Media (CABA) | P50: 4 | Q50: 3 | R50: 30 | T50: Si | U50: Si | V50: Jueves 27/4 | BS50: Si | BT50: No | BU50: Si | BV50: No | BW50: No | BX50: No | BY50: Si | BZ50: No | CA50: No | CB50: No | CC50: No | CD50: Si | CE50: No | CF50: No | CG50: No | CH50: No | CI50: No | CJ50: Si | CK50: Si
A51: 45001.605 | B51: borellocecilia@gmail.com | C51: Colegio parroquial nuestra señora de la merced | D51: 062222700 | E51: 9. Liceos / Normales / Colegios / Institutos orientados en ciencias sociales y/o humanidades | F51: Sociales | G51: Privada | H51: Borello cecilia | I51: Gaetani magali | J51: Vanini maximiliano | K51: borellocecilia@gmail.com | L51: ÁREA METROPOLITANA DE BUENOS AIRES | M51: Villa ballester | N51: 39 | O51: 6º Secundaria (Prov.) / 5º Media (CABA) | P51: 3 | Q51: 2 | R51: 30 | T51: Si | U51: No | V51: Martes 25/4 | W51: Si | X51: No | Y51: No | Z51: No | AA51: No | AB51: Si | AC51: No | AD51: No | AE51: No | AF51: No | AG51: No | AH51: No | AI51: No | AJ51: No | AK51: No | AL51: No | AM51: No | AN51: No | AO51: No | AP51: Si
A52: 45002.571 | B52: agustina.cafiero@ort.edu.ar | C52: Escuela ORT N°2 | D52: 020149400 | E52: 9. Liceos / Normales / Colegios / Institutos orientados en ciencias sociales y/o humanidades | F52: TIC/HUMANIDADES | G52: Privada | H52: Luis Perez | I52: Mariana Gartner | K52: agustina.cafiero@ort.edu.ar | L52: CABA | M52: Nuñez | N52: 35 | O52: 6º Secundaria (Prov.) / 5º Media (CABA) | P52: 5 | Q52: 5 | R52: 30 | S52: Los grupos estarán conformados por alumnos de 3ro, 4to y 5to (ciclo superior) | T52: Si | U52: No | V52: Miércoles 26/4 | AU52: No | AV52: Si | AW52: No | AX52: Si | AY52: Si | AZ52: Si | BA52: No | BB52: No | BC52: No | BD52: Si | BE52: Si | BF52: Si | BG52: No | BH52: No | BI52: Si | BJ52: Si | BK52: Si | BL52: No | BM52: No | BN52: No | BO52: No | BP52: No | BQ52: No
A53: 45002.736 | B53: lulizobra@gmail.com | C53: Colegio San Francisco Coll | D53: 020078500 | E53: 10. Liceos / Normales / Colegios / Institutos de otras orientaciones | F53: Economía y Administración | G53: Privada | H53: Lucila Zobra | I53: Silvina Salvia | J53: Macarena Sanguiao | K53: lulizobra@gmail.com | L53: CABA | M53: Villa Urquiza | N53: 31 | O53: 6º Secundaria (Prov.) / 5º Media (CABA) | P53: 4 | Q53: 4 | R53: 25 | T53: Si | U53: No | V53: Martes 25/4 | W53: Si | X53: No | Y53: No | Z53: No | AA53: Si | AB53: Si | AC53: No | AD53: No | AE53: No | AF53: No | AG53: Si | AH53: Si | AI53: No | AJ53: No | AK53: No | AL53: Si | AM53: Si | AN53: No | AO53: No | AP53: No | AQ53: No | AR53: No | AS53: No
A54: 45002.738 | B54: sfc.lucilazobra@gmail.com | C54: Colegio San Francisco Coll | D54: 020078500 | E54: 10. Liceos / Normales / Colegios / Institutos de otras orientaciones | F54: Economía y Administración | G54: Privada | H54: Lucila Zobra | I54: Silvina Salvia | J54: Macarena Sanguiao | K54: sfc.lucilazobra@gmail.com | L54: CABA | M54: Villa Urquiza | N54: 34 | O54: 6º Secundaria (Prov.) / 5º Media (CABA) | P54: 4 | Q54: 4 | R54: 25 | T54: Si | U54: No | V54: Martes 25/4 | W54: Si | X54: No | Y54: No | Z54: No | AA54: Si | AB54: Si | AC54: No | AD54: No | AE54: No | AF54: No | AG54: Si | AH54: Si | AI54: No | AJ54: No | AK54: No | AL54: Si | AM54: Si | AN54: No | AO54: No | AP54: No | AQ54: No | AR54: No | AS54: No
A55: 45005.668 | B55: pamelamartinezz111@gmail.com | C55: Instituto El Castillo | D55: 060863900 | E55: 9. Liceos / Normales / Colegios / Institutos orientados en ciencias sociales y/o humanidades | F55: Ciencias Sociales | G55: Privada | H55: Pamela Martinez | I55: Griselda Almaraz | K55: pamelamartinezz111@gmail.com | L55: ÁREA METROPOLITANA DE BUENOS AIRES | M55: Lanus | N55: 35 | O55: 6º Secundaria (Prov.) / 5º Media (CABA) | P55: 3 | Q55: 2 | R55: 25 | T55: Si | U55: No | V55: Jueves 27/4 | BS55: Si | BT55: Si | BU55: No | BV55: Si | BW55: Si | BX55: Si | BY55: No | BZ55: No | CA55: No | CB55: Si | CC55: Si | CD55: Si | CE55: No | CF55: No | CG55: Si | CH55: Si | CI55: Si | CJ55: No | CK55: No | CL55: Si | CM55: Si | CN55: No | CO55: No
A56: 45001.499 | B56: biblioteca@casasantacatalina.com.ar | C56: Instituto privado santa catalina | D56: 020076800 | E56: 10. Liceos / Normales / Colegios / Institutos de otras orientaciones | F56: comunicacion | G56: Privada | H56: paz rozen | I56: alicia mendella | K56: biblioteca@casasantacatalina.com.ar | L56: CABA | M56: constitcion | N56: 35 | O56: 6º Secundaria (Prov.) / 5º Media (CABA) | P56: 3 | Q56: 2 | R56: 20 | T56: Si | U56: No | V56: Jueves 27/4 | BS56: Si | BT56: Si | BU56: No | BV56: Si | BW56: Si | BX56: Si | BY56: No | BZ56: No | CA56: No | CB56: Si | CC56: Si | CD56: Si | CE56: No | CF56: No | CG56: Si | CH56: Si | CI56: Si | CJ56: No | CK56: No | CL56: Si | CM56: Si | CN56: No | CO56: No
A57: 45005.5 | B57: germanpugliese@yahoo.com.ar | C57: INSTITUTO PIO XII | D57: 060771600 | E57: 10. Liceos / Normales / Colegios / Institutos de otras orientaciones | F57: ECONOMIA Y ADMINISTRACION | G57: Privada | H57: GERMAN OMAR PUGLIESE | I57: FACUNDO PEREYRA | J57: MATIAS RAZZETTO | K57: germanpugliese@yahoo.com.ar | L57: ÁREA METROPOLITANA DE BUENOS AIRES | M57: AVELLANEDA | N57: 35 | O57: 6º Secundaria (Prov.) / 5º Media (CABA) | P57: 1 | Q57: 3 | R57: 20 | T57: Si | U57: No | V57: Martes 25/4 | W57: Si | X57: Si | Y57: No | Z57: No | AA57: No | AB57: No | AC57: No | AD57: No | AE57: No | AF57: No | AG57: No | AH57: No | AI57: No | AJ57: No | AK57: No | AL57: No | AM57: No | AN57: No | AO57: No | AP57: No | AQ57: No | AR57: No | AS57: No
A58: 45002.34 | B58: biblioteca@casasantacatalina.com.ar | C58: Instituto privado santa catalina | D58: 020076800 | E58: 10. Liceos / Normales / Colegios / Institutos de otras orientaciones | F58: Economía y Administración | G58: Privada | H58: Paz Rozen | I58: Alicia Mendella | K58: biblioteca@casasantacatalina.com.ar | L58: CABA | M58: Constitucion | N58: 35 | O58: 6º Secundaria (Prov.) / 5º Media (CABA) | P58: 3 | Q58: 2 | R58: 20 | S58: Este formulario lo complete ayer pero confundi la orientacion del curso. Puse Técnicas en administración de empresas, administración de las organizaciones, servicios turísticos, multimedios en lugar de 10. Liceos / Normales / Colegios / Institutos de otras orientaciones, mil disculpas. | T58: Si | U58: No | V58: Martes 25/4 | W58: Si | X58: Si | Y58: No | Z58: Si | AA58: Si | AB58: Si | AC58: No | AD58: No | AE58: No | AF58: Si | AG58: Si | AH58: Si | AI58: No | AJ58: No | AK58: Si | AL58: Si | AM58: Si | AN58: No | AO58: No | AP58: Si | AQ58: Si | AR58: No | AS58: No
A59: 45005.412 | B59: germanpugliese@yahoo.com.ar | C59: INSTITUTO PIO XII | D59: 060771600 | E59: 9. Liceos / Normales / Colegios / Institutos orientados en ciencias sociales y/o humanidades | F59: CIENCIAS SOCIALES | G59: Privada | H59: German Omar | I59: MATIAS RAZZETTO | J59: AYELEN HAWRYLISZYN | K59: germanpugliese@yahoo.com.ar | L59: ÁREA METROPOLITANA DE BUENOS AIRES | M59: AVELLANEDA | N59: 35 | O59: 6º Secundaria (Prov.) / 5º Media (CABA) | P59: 1 | Q59: 3 | R59: 20 | T59: Si | U59: No | V59: Martes 25/4 | W59: Si | X59: Si | Y59: No | Z59: No | AA59: No | AB59: No | AC59: No | AD59: No | AE59: No | AF59: No | AG59: No | AH59: No | AI59: No | AJ59: No | AK59: No | AL59: No | AM59: No | AN59: No | AO59: No | AP59: No | AQ59: No | AR59: No | AS59: No
A60: 45005.503 | B60: germanpugliese@yahoo.com.ar | C60: INSTITUTO PIO XII | D60: 060771600 | E60: 9. Liceos / Normales / Colegios / Institutos orientados en ciencias sociales y/o humanidades | F60: CIENCIAS SOCIALES | G60: Privada | H60: GERMAN OMAR PUGLIESE | I60: AYELEN HAWRYLISZYN | J60: FACUNDO PEREYRA | K60: germanpugliese@yahoo.com.ar | L60: ÁREA METROPOLITANA DE BUENOS AIRES | M60: AVELLANEDA | N60: 35 | O60: 6º Secundaria (Prov.) / 5º Media (CABA) | P60: 1 | Q60: 3 | R60: 20 | T60: Si | U60: No | V60: Martes 25/4 | W60: Si | X60: Si | Y60: No | Z60: No | AA60: No | AB60: No | AC60: No | AD60: No | AE60: No | AF60: No | AG60: No | AH60: No | AI60: No | AJ60: No | AK60: No | AL60: No | AM60: No | AN60: No | AO60: No | AP60: No | AQ60: No | AR60: No | AS60: No
A61: 45005.741 | B61: lmedina@sanvicenteescobar.edu.ar | C61: Instituto San Vicente de Paul -Escobar | D61: 061310300 | E61: 9. Liceos / Normales / Colegios / Institutos orientados en ciencias sociales y/o humanidades | F61: Ciencias Sociales | G61: Privada | H61: Silvana Morel | I61: Lorena Medina | K61: lmedina@sanvicenteescobar.edu.ar | L61: ÁREA METROPOLITANA DE BUENOS AIRES | M61: Escobar | N61: 31 | O61: 6º Secundaria (Prov.) / 5º Media (CABA) | P61: 5 | Q61: 3 | R61: 20 | T61: Si | U61: No | V61: Jueves 27/4 | BS61: Si | BT61: No | BU61: No | BV61: No | BW61: Si | BX61: Si | BY61: No | BZ61: No | CA61: No | CB61: No | CC61: Si | CD61: Si | CE61: No | CF61: No | CG61: Si | CH61: Si | CJ61: No | CK61: No | CL61: Si | CM61: Si | CN61: No | CO61: No
A62: 45001.494 | B62: patferre@gmail.com | C62: Colegio de la Reconquista | D62: 061629100 | E62: 9. Liceos / Normales / Colegios / Institutos orientados en ciencias sociales y/o humanidades | F62: Comunicación | G62: Privada | H62: Patricia Ferreyra | I62: Lia Baldoma | J62: Liliana Descalzo | K62: patferre@gmail.com | L62: ÁREA METROPOLITANA DE BUENOS AIRES | M62: Tigre/Tigre | N62: 32 | O62: 6º Secundaria (Prov.) / 5º Media (CABA) | P62: 5 | Q62: 1 | R62: 20 | T62: Si | U62: No | V62: Martes 25/4 | W62: Si | X62: No | Y62: No | Z62: No | AA62: Si | AB62: Si | AC62: Si | AD62: No | AE62: No | AF62: No | AG62: No | AH62: Si | AI62: Si | AJ62: No | AK62: No | AL62: Si | AM62: Si | AN62: Si | AO62: No | AT62: Estan muy entusiasmado por ir. Pueden separse en pequeños grupos.
A63: 45004.571 | B63: fbeitia@hotmail.com | C63: INST.EDUC.ARG.NTRA.SRA.DE LUJAN | D63: 020059400 | E63: 10. Liceos / Normales / Colegios / Institutos de otras orientaciones | F63: Bachillerato con orientación en Comunicación Social | G63: Privada | H63: Fernando Beitia | I63: Fernanda Goldaracena | J63: Jéssica Maidana | K63: fbeitia@hotmail.com | L63: CABA | M63: Villa Pueyrredón | N63: 34 | O63: 6º Secundaria (Prov.) / 5º Media (CABA) | P63: 4 | Q63: 4 | R63: 15 | T63: Si | U63: No | V63: Martes 25/4 | W63: Si | X63: Si | Y63: No | Z63: No | AA63: Si | AB63: No | AC63: No | AD63: No | AE63: No | AF63: No | AG63: No | AH63: No | AI63: No | AJ63: No | AK63: No | AL63: No | AM63: No | AN63: No | AO63: No | AP63: No | AQ63: No | AR63: No | AS63: No
A64: 45004.573 | B64: fbeitia@hotmail.com | C64: INST.EDUC.ARG.NTRA.SRA.DE LUJAN | D64: 020059400 | E64: 10. Liceos / Normales / Colegios / Institutos de otras orientaciones | F64: Bachillerato con orientación en Economía y Administración | G64: Privada | H64: Jéssica Maidana | I64: Fernanda Goldaracena | J64: Fernando Beitia | K64: fbeitia@hotmail.com | L64: CABA | M64: Villa Pueyrredón | N64: 35 | O64: 6º Secundaria (Prov.) / 5º Media (CABA) | P64: 4 | Q64: 4 | R64: 15 | T64: Si | U64: No | V64: Martes 25/4 | W64: Si | X64: Si | Y64: No | Z64: No | AA64: Si | AB64: No | AC64: No | AD64: No | AE64: No | AF64: No | AG64: Si | AH64: No | AI64: No | AJ64: No | AK64: No | AL64: No | AM64: No | AN64: No | AO64: No | AP64: No | AQ64: No | AR64: No | AS64: No
A65: 45004.575 | B65: fbeitia@hotmail.com | C65: INST.EDUC.ARG.NTRA.SRA.DE LUJAN | D65: 020059400 | E65: 10. Liceos / Normales / Colegios / Institutos de otras orientaciones | F65: Bachillerato con orientación en Informática | G65: Privada | H65: Jéssica Maidana | I65: Fernanda Goldaracena | J65: Fernando Beitia | K65: fbeitia@hotmail.com | L65: CABA | M65: Villa Pueyrredón | N65: 33 | O65: 6º Secundaria (Prov.) / 5º Media (CABA) | P65: 4 | Q65: 4 | R65: 15 | T65: Si | U65: No | V65: Martes 25/4 | W65: Si | X65: Si | Y65: No | Z65: No | AA65: Si | AB65: No | AC65: No | AD65: No | AE65: No | AF65: No | AG65: Si | AH65: No | AI65: No | AJ65: No | AK65: No | AL65: Si | AM65: No | AN65: No | AO65: No | AP65: No | AQ65: Si | AR65: No | AS65: No
A66: 45000.743 | B66: julieta.ojedasanese@gmail.com | C66: INSTITUTO ESCUELA JUAN PABLO II | D66: 060668300 | E66: 10. Liceos / Normales / Colegios / Institutos de otras orientaciones | F66: Economía y gestión de las organizaciones | G66: Privada | H66: Julieta Ojeda Sanese | I66: Verónica Garay | J66: Camila Castelli | K66: julieta.ojedasanese@gmail.com | L66: ÁREA METROPOLITANA DE BUENOS AIRES | M66: Villa Madero | N66: 35 | O66: 6º Secundaria (Prov.) / 5º Media (CABA) | P66: 4 | Q66: 3 | R66: 10 | T66: Si | U66: No | V66: Martes 25/4 | W66: Si | X66: No | Y66: No | Z66: No | AA66: Si | AB66: No | AC66: No | AD66: No | AE66: No | AM66: Si
A67: 45000.746 | B67: julieta.ojedasanese@gmail.com | C67: INSTITUTO ESCUELA JUAN PABLO II | D67: 060668300 | E67: 10. Liceos / Normales / Colegios / Institutos de otras orientaciones | F67: Economía y gestión de las organizaciones | G67: Privada | H67: Verónica Garay | I67: Julieta Ojeda | J67: Camila Castelli | K67: julieta.ojedasanese@gmail.com | L67: ÁREA METROPOLITANA DE BUENOS AIRES | M67: Villa madero | N67: 25 | O67: 6º Secundaria (Prov.) / 5º Media (CABA) | P67: 4 | Q67: 2 | R67: 10 | T67: Si | U67: No | V67: Martes 25/4 | W67: Si | X67: No | Y67: No | Z67: No | AA67: Si | AB67: No | AC67: No | AD67: No | AE67: No | AM67: Si
A68: 45000.83 | B68: rodrical85@hotmail.com | C68: INSTITUTO COLEGIO DE NUESTRA SEÑORA | D68: 020056500 | E68: 10. Liceos / Normales / Colegios / Institutos de otras orientaciones | F68: Informática | G68: Privada | H68: Ana María Rodríguez | I68: Laura López | J68: Maria Esther Fabbro | K68: rodrical85@hotmail.com | L68: CABA | M68: San Nicolás | N68: 20 | O68: 6º Secundaria (Prov.) / 5º Media (CABA) | P68: 5 | Q68: 4 | R68: 10 | T68: Si | U68: No | V68: Jueves 27/4 | BS68: Si | BT68: No | BU68: No | BV68: No | BW68: No | BX68: Si | BY68: No | BZ68: No | CA68: No | CB68: No | CC68: Si | CD68: No | CE68: No | CF68: No | CG68: No | CH68: No | CI68: No | CJ68: No | CK68: No | CL68: No | CM68: No | CN68: No | CO68: No
A69: 45005.807 | B69: cami_zabala@yahoo.com.ar | C69: Instituto Madre Maria Luisa Clarac | D69: 060703300 | E69: 9. Liceos / Normales / Colegios / Institutos orientados en ciencias sociales y/o humanidades | F69: Ciencias Sociales | G69: Privada | H69: Zabala Lindermann Camila | I69: Fernandez Mariela | J69: Medina Andrea | K69: cami_zabala@yahoo.com.ar | L69: ÁREA METROPOLITANA DE BUENOS AIRES | M69: Gregorio de Laferrere | N69: 33 | O69: 6º Secundaria (Prov.) / 5º Media (CABA) | P69: 3 | Q69: 4 | R69: 10 | T69: Si | U69: Si | V69: Martes 25/4 | W69: Si | X69: Si | Y69: Si | Z69: Si | AA69: Si | AB69: Si | AC69: Si | AD69: No | AE69: No | AF69: Si | AG69: Si | AH69: Si | AI69: No | AJ69: No | AK69: Si | AL69: Si | AM69: Si | AN69: No | AO69: No | AP69: Si | AQ69: Si | AR69: Si | AS69: No
A70: 45000.763 | B70: jacquelineottaviano@gmail.com | C70: COLEGIO PARROQUIAL NUESTRA SEÑORA DEL REFUGIO | D70: 061465900 | E70: 9. Liceos / Normales / Colegios / Institutos orientados en ciencias sociales y/o humanidades | F70: ciencias sociales | G70: Privada | H70: jacqueline ottaviano | I70: florencia ibarra | K70: jacquelineottaviano@gmail.com | L70: ÁREA METROPOLITANA DE BUENOS AIRES | M70: boulogne | N70: 35 | O70: 6º Secundaria (Prov.) / 5º Media (CABA) | P70: 5 | Q70: 3 | R70: 10 | T70: Si | U70: No | V70: Miércoles 26/4 | AU70: Si | AV70: Si | AW70: No | AX70: Si | AY70: Si | AZ70: Si | BA70: Si | BB70: No | BC70: No | BD70: Si | BE70: Si | BF70: Si | BG70: No | BH70: No | BI70: Si | BJ70: Si | BK70: Si | BL70: No | BM70: No | BN70: Si | BO70: Si | BP70: No | BQ70: No | BR70: Puse todas las opciones disponibles
A71: 45005.687 | B71: nruderman@gmail.com | C71: Escuela Superior de Comercio Carlos Pellegrini | D71: 029000800 | E71: 9. Liceos / Normales / Colegios / Institutos orientados en ciencias sociales y/o humanidades | F71: Comercial | G71: Estatal | H71: Nicolas Ruderman | I71: Eva Antal | K71: nruderman@gmail.com | L71: CABA | M71: Recoleta | N71: 20 | O71: 6º Secundaria (Prov.) / 5º Media (CABA) | P71: 5 | Q71: 4 | R71: 10 | T71: Si | U71: No | V71: Jueves 27/4 | BS71: No | BT71: Si | BU71: No | BV71: Si | BW71: No | BX71: No | BY71: No | BZ71: No | CA71: No | CB71: No | CC71: Si | CL71: No | CM71: Si | CN71: No | CO71: No
A72: 45006.433 | B72: marisa_mariani@yahoo.com.ar | C72: INSTITUTO RAUL SCALABRINI ORTIZ | D72: 020086700 | E72: 10. Liceos / Normales / Colegios / Institutos de otras orientaciones | F72: EN ECONOMIA Y ADMINISTRACION | G72: Privada | H72: MARISA MARIANI | I72: PATRICIA MIZRAJI | J72: LAURA VITULLO | K72: marisa_mariani@yahoo.com.ar | L72: CABA | M72: MONSERRAT | N72: 30 | O72: 6º Secundaria (Prov.) / 5º Media (CABA) | P72: 5 | Q72: 4 | R72: 50 | T72: Si | U72: No | V72: Jueves 27/4 | BS72: Si | BT72: No | BU72: No | BV72: No | BW72: Si | BX72: No | BY72: No | BZ72: No | CA72: No | CB72: No | CC72: No | CD72: No | CE72: No | CF72: No | CG72: No | CH72: No | CI72: No | CJ72: No | CK72: No | CL72: No | CM72: Si | CN72: No | CO72: No
A73: 45002.567 | B73: lencinaluisalberto@gmail.com | C73: EES 32 | D73: 061859200 | E73: 10. Liceos / Normales / Colegios / Institutos de otras orientaciones | F73: Artes visuales | G73: Estatal | H73: Lencina Luis Alberto | I73: Malfatto Silvina | K73: lencinaluisalberto@gmail.com | L73: ÁREA METROPOLITANA DE BUENOS AIRES | M73: Adrogué | N73: 35 | O73: 6º Secundaria (Prov.) / 5º Media (CABA) | P73: 3 | Q73: 1 | R73: 75 | T73: Si | U73: No | V73: Martes 25/4 | W73: Si | X73: No | Y73: No | Z73: No | AA73: No | AB73: No | AC73: Si | AD73: Si | AE73: Si | AF73: No | AG73: Si | AH73: No | AI73: No | AJ73: No | AK73: No | AL73: No | AM73: Si | AN73: No | AO73: No | AP73: No | AQ73: No | AR73: Si | AS73: Si
A74: 45002.915 | B74: profesoralezica@gmail.com | C74: Escuela de educacion secundaria N°108 | D74: 061856700 | E74: 10. Liceos / Normales / Colegios / Institutos de otras orientaciones | F74: Arte y Comunicación | G74: Estatal | H74: Noelia Lezica | I74: Graciela Velazquez | J74: Analia Perez | K74: profesoralezica@gmail.com | L74: ÁREA METROPOLITANA DE BUENOS AIRES | M74: Gregorio de Laferrere | N74: 35 | O74: 6º Secundaria (Prov.) / 5º Media (CABA) | P74: 2 | Q74: 3 | R74: 80 | S74: Son estudiantes de bajos recursos que están transitando su último año en la escuela secundaria y solicitan visitar la universidad. Habiendo transitado 4to año en el 2021 en contexto pandemia y restricciones salidas educativas; no tuvieron la experiencia de visitar la semana de la ciencia ni ninguna otra muestra similiar, a la que los estudiantes suelen asistir con sus docentes de matemática, fisica y biologia. Entonces este año estaríamos visitando la semana de la ciencia con la doble finalidad de *Acercar a los estudiantes a la matemática y la ciencia de datos y ; *Que conozcan UBA como una alternativa para sus estudios superiores. | T74: Si | U74: Si | V74: Jueves 27/4 | BS74: No | BT74: Si | BU74: Si | BV74: No | BW74: No | BX74: Si | BY74: Si | BZ74: Si | CA74: Si | CB74: No | CC74: No | CD74: Si | CE74: Si | CF74: Si | CG74: No | CH74: Si | CI74: Si | CJ74: Si | CK74: Si | CL74: No | CM74: Si | CN74: Si | CO74: Si | CP74: Aclaración: Son dos grupos de 35. Por una cuestión de organización, logística y costos ambos, deberían ir el jueves 27 de abril. Marcamos varias opciones de horario y estamos predispuestos a la posibilidad de que mientras un grupo esta en una charla o taller el otro este en otra. Desde ya muchas gracias.
A75: 45005.724 | B75: marescorihuela@abc.gob.ar | C75: Escuela de educación secundaria n 14 "Lola Mora" | D75: 061876300 | E75: 11. Rurales de todas las orientaciones | F75: Artes visuales | G75: Estatal | H75: María Elena Esorihuela | I75: Daniela De Leon | J75: Mónica Mabel Escorihuela | K75: marescorihuela@abc.gob.ar | L75: INTERIOR DE LA PROVINCIA DE BUENOS AIRES | M75: Campos Salles/San Nicolas de los arroyos | N75: 20 | O75: 6º Secundaria (Prov.) / 5º Media (CABA) | P75: 3 | Q75: 2 | R75: 100 | T75: Si | U75: Si | V75: Miércoles 26/4 | AU75: No | AV75: No | AW75: Si | AX75: No | AY75: Si | AZ75: No | BA75: Si | BB75: No | BC75: No | BK75: Si
A76: 45001.828 | B76: zelayaandrea@hotmail.com | C76: Escuela el Ave Maria | D76: 060364300 | E76: 13. Formación permanente de jóvenes y adultos | F76: Bachiller | G76: Privada | H76: Zelaya maria Andrea | I76: Pedro Paredes | K76: Zelayaandrea@hotmail.com | L76: INTERIOR DE LA PROVINCIA DE BUENOS AIRES | M76: Claypole, Almirante Brown | N76: 30 | O76: 6º Secundaria (Prov.) / 5º Media (CABA) | P76: 5 | Q76: 4 | R76: 30 | S76: Queremos participar de la semana de las coencias con nuestros estudiantes! | T76: Si | U76: No | V76: Jueves 27/4 | BS76: Si | BT76: No | BU76: No | BV76: Si | BW76: No | BX76: Si | BY76: No | BZ76: No | CA76: No | CB76: Si | CC76: No | CD76: No | CE76: No | CF76: No | CG76: Si | CH76: Si | CI76: No | CJ76: No | CK76: No | CM76: Si
A77: 45001.832 | B77: zelayaandrea@hotmail.com | C77: Instituto Don Orione | D77: 061338200 | E77: 13. Formación permanente de jóvenes y adultos | F77: Bachiller ,Naturales | G77: Privada | H77: Zelaya maria Andrea | I77: Gluozzi sandra | K77: Zelayaandrea@hotmail.com | L77: INTERIOR DE LA PROVINCIA DE BUENOS AIRES | M77: Florencio Varela | N77: 28 | O77: 6º Secundaria (Prov.) / 5º Media (CABA) | P77: 4 | Q77: 5 | R77: 40 | S77: . | T77: Si | U77: No | V77: Martes 25/4 | W77: No | X77: Si | Y77: No | Z77: Si | AA77: Si | AB77: No | AC77: No | AD77: No | AE77: No | AF77: Si | AK77: Si | AL77: Si | AM77: No | AN77: No | AO77: No | AQ77: No | AT77: .
A78: 45005.822 | B78: r.estrella@instcristomaestro.edu.ar | C78: Instituto Cristo Maestro | D78: 020072300 | E78: 2. Técnicas en computación, electrónica, informática | F78: Bachiller en informática | G78: Privada | H78: Silvana Rocío Estrella | I78: Santiago Mollano | J78: Ana Bardauil | K78: r.estrella@instcristomaestro.edu.ar | L78: CABA | M78: CABA Floresta | N78: 25 | O78: 6º Secundaria (Prov.) / 5º Media (CABA) | P78: 4 | Q78: 3 | R78: 40 | T78: Si | U78: Si | V78: Jueves 27/4 | BS78: Si | BT78: Si | BU78: Si | BV78: No | BW78: Si | BX78: Si | BY78: Si | BZ78: Si | CA78: Si | CB78: No | CC78: Si | CD78: Si | CE78: Si | CF78: Si | CG78: No | CH78: Si | CI78: Si | CJ78: Si | CK78: Si | CL78: Si | CM78: Si | CN78: Si | CO78: Si | CP78: Todo parece muy interesante , las propuestas con cupo serán enriquecedoras cual sea.
A79: 45002.65 | B79: olmosnoe15@gmail.com | C79: ESCUELA DE EDUCACION SECUNDARIA TECNICA N° 1 EDUARDO ADER | D79: 060958100 | E79: 2. Técnicas en computación, electrónica, informática | F79: TECNICO EN PROGRAMACION | G79: Estatal | H79: Noemi Olmos | I79: Insaurralde | K79: olmosnoe15@gmail.com | L79: ÁREA METROPOLITANA DE BUENOS AIRES | M79: Villa Adelina | N79: 18 | O79: 6º Secundaria (Prov.) / 5º Media (CABA) | P79: 4 | Q79: 2 | R79: 40 | T79: No | U79: Si | V79: Miércoles 26/4 | AU79: No | AV79: No | AW79: Si | AX79: No | AY79: No | AZ79: No | BA79: Si | BB79: No | BC79: No | BD79: No | BE79: No | BF79: Si | BG79: No | BH79: No | BI79: No | BJ79: No | BK79: No | BL79: No | BM79: Si | BN79: No | BO79: No | BP79: No | BQ79: Si
A80: 45005.896 | B80: profe.basoalto.math2021@gmail.com | C80: ESCUELA DE EDUCACIÓN SECUNDARIA TÉCNICA Nº1 DR. DALMACIO VELEZ SARSFIELD | D80: 061115600 | E80: 2. Técnicas en computación, electrónica, informática | F80: Electrónica | G80: Estatal | H80: Ana Basoalto | I80: Fernanda Quiroga | K80: profe.basoalto.math2021@gmail.com | L80: ÁREA METROPOLITANA DE BUENOS AIRES | M80: Morón | N80: 35 | O80: 6º Secundaria (Prov.) / 5º Media (CABA) | P80: 5 | Q80: 4 | R80: 80 | T80: Si | U80: Si | V80: Jueves 27/4 | BS80: Si | BT80: No | BU80: Si | BV80: No | BW80: Si | BX80: No | BY80: Si | BZ80: No | CA80: Si | CD80: Si | CE80: Si | CH80: Si | CK80: Si | CN80: Si | CP80: Muchos estudiantes quieren continuar sus estudios superiores en Exactas
A81: 45006.474 | B81: profe.basoalto.math2021@gmail.com | C81: 1ESCUELA DE EDUCACIÓN SECUNDARIA TÉCNICA Nº1 DR. DALMACIO VELEZ SARSFIELD | D81: 061115600 | E81: 2. Técnicas en computación, electrónica, informática | F81: Electrónica | G81: Estatal | H81: Ana Basoalto | I81: Fernanda Quiroga | K81: profe.basoalto.math2021@gmail.com | L81: ÁREA METROPOLITANA DE BUENOS AIRES | M81: Morón | N81: 35 | O81: 6º Secundaria (Prov.) / 5º Media (CABA) | P81: 5 | Q81: 4 | R81: 80 | S81: Esperamos la asignación de la inscripción dado que son muchos los estudiantes que desean continuar sus estudios en Exactas | T81: Si | U81: Si | V81: Jueves 27/4 | BS81: Si | BT81: No | BU81: Si | BV81: Si | BW81: No | BX81: Si | BY81: No | BZ81: Si | CA81: No | CC81: Si | CE81: Si | CI81: Si | CK81: Si | CL81: Si | CO81: Si
A82: 45002.352 | B82: ciademaria_nivelmedio@yahoo.com.ar | C82: Instituto Compañía de María | D82: 020099900 | E82: 3. Técnicas en administración de empresas, administración de las organizaciones, servicios turísticos, multimedios | F82: Bachiller en Economía y Administración | G82: Privada | H82: Mara Barbagallo | I82: Claudia Vezzaro | J82: Guadalupe Carrillo | K82: ciademaria_nivelmedio@yahoo.com.ar | L82: CABA | M82: Colegiales | N82: 26 | O82: 6º Secundaria (Prov.) / 5º Media (CABA) | P82: 4 | Q82: 5 | R82: 1 | T82: Si | U82: No | V82: Martes 25/4 | W82: Si | X82: No | Y82: No | Z82: No | AA82: Si | AB82: No | AC82: No | AD82: No | AE82: No | AF82: No | AG82: No | AH82: Si | AI82: No | AJ82: No | AK82: No | AL82: No | AM82: Si | AN82: No | AO82: No
A83: 45001.497 | B83: biblioteca@casasantacatalina.com.ar | C83: Instituto Privado Santa Catalina | D83: 020076800 | E83: 3. Técnicas en administración de empresas, administración de las organizaciones, servicios turísticos, multimedios | F83: Administracion | G83: Privada | H83: Paz Rozen | I83: Alicia Mendella | K83: biblioteca@casasantacatalina.com.ar | L83: CABA | M83: Constitucion | N83: 35 | O83: 6º Secundaria (Prov.) / 5º Media (CABA) | P83: 3 | Q83: 2 | R83: 20 | T83: Si | U83: No | V83: Martes 25/4 | W83: Si | X83: Si | Y83: No | Z83: Si | AA83: Si | AB83: Si | AC83: No | AD83: No | AE83: No | AF83: Si | AG83: Si | AH83: Si | AI83: No | AJ83: No | AK83: Si | AL83: Si | AM83: Si | AN83: No | AO83: No | AP83: Si | AQ83: Si | AR83: No | AS83: No
A84: 45005.666 | B84: pamelamartinezz111@gmail.com | C84: Instituto El Castillo | D84: 060863900 | E84: 3. Técnicas en administración de empresas, administración de las organizaciones, servicios turísticos, multimedios | F84: Economia | G84: Privada | H84: Martinez Pamela | I84: Almaraz Griselda | K84: pamelamartinezz111@gmail.com | L84: ÁREA METROPOLITANA DE BUENOS AIRES | M84: Lanus | N84: 35 | O84: 6º Secundaria (Prov.) / 5º Media (CABA) | P84: 3 | Q84: 2 | R84: 25 | T84: Si | U84: No | V84: Jueves 27/4 | BS84: Si | BT84: Si | BU84: No | BV84: Si | BW84: Si | BX84: Si | BY84: No | BZ84: No | CA84: No | CB84: Si | CC84: Si | CD84: Si | CE84: No | CF84: No | CG84: Si | CH84: Si | CI84: Si | CJ84: No | CK84: No | CL84: Si | CM84: Si | CN84: No | CO84: No
A85: 45005.709 | B85: sarmarc2012@gmail.com | C85: Escuela de educación secundaria n° 1 Boulogne Sur mer | D85: 062026100 | E85: 3. Técnicas en administración de empresas, administración de las organizaciones, servicios turísticos, multimedios | F85: Gestión de empresas y ciencias sociales | G85: Estatal | H85: Marcelo sarti | I85: José Sosa Iacona | J85: Gustavo Martino | K85: sarmarc2012@gmail.com | L85: ÁREA METROPOLITANA DE BUENOS AIRES | M85: Boulogne Sur mer | N85: 35 | O85: 6º Secundaria (Prov.) / 5º Media (CABA) | P85: 3 | Q85: 1 | R85: 90 | T85: Si | U85: Si | V85: Miércoles 26/4 | AU85: Si | AV85: Si | AW85: No | AX85: No | AY85: Si | AZ85: No | BA85: No | BB85: No | BC85: No | BD85: No | BE85: No | BF85: No | BG85: Si | BH85: No | BI85: No | BJ85: No | BK85: No | BL85: No | BM85: Si | BN85: No | BO85: No | BP85: No | BQ85: No
A86: 45001.57 | B86: gladis_espinoza@hotmail.com | C86: Escuela de Educación Secundaria N° 34 | D86: 061829300 | E86: 4. Artísticas de todas las orientaciones | F86: Artes Visuales | G86: Estatal | H86: Gladis Espinoza | I86: Andrea Gonzalez | J86: Miryam Calderón | K86: gladis_espinoza@hotmail.com | L86: ÁREA METROPOLITANA DE BUENOS AIRES | M86: Ricardo Rojas. Tigre | N86: 35 | O86: 6º Secundaria (Prov.) / 5º Media (CABA) | P86: 2 | Q86: 1 | R86: 90 | S86: Es muy importante para nuestros alumnos poder conocer otros ámbitos educativos, ampliando su visión mas alla de su entorno, viendo posibilidades y distintas realidades. Participar junto a otros jóvenes estudiantes les permitirá sentirse parte y ver que otro futuro es posible. | T86: Si | U86: Si | V86: Miércoles 26/4 | AU86: Si | AV86: Si | AW86: Si | AX86: Si | AY86: Si | AZ86: No | BA86: Si | BB86: No | BC86: Si | BD86: No | BE86: Si | BF86: Si | BG86: Si | BH86: Si | BI86: Si | BJ86: Si | BK86: Si | BL86: Si | BM86: Si | BN86: Si | BO86: No | BP86: No | BQ86: Si | BR86: Nos gustaría poder participar en al menos una charla, el Taller y Arte matemático. Asegurar esa participación y en el tiempo restante recorrer las Estaciones Interactivas y la facultad. Gracias!
A87: 45002.784 | B87: malarcon1012@gmail.com | C87: Esc. de Educacion secundaria Santo Domingo Savio | D87: 061307100 | E87: 4. Artísticas de todas las orientaciones | F87: Arte | G87: Privada | H87: Mirna Alarcon | I87: Gastón Errecart | J87: Isabel Oruè Barceló | K87: malarcon10122@gmail.com | L87: INTERIOR DE LA PROVINCIA DE BUENOS AIRES | M87: La Cava San Isidro | N87: 37 | O87: 6º Secundaria (Prov.) / 5º Media (CABA) | P87: 3 | Q87: 2 | R87: 95 | S87: El colegio Sto Dgo Savio es un colegio parroquial y los alumnos son de bajos recursos | T87: No | U87: Si | V87: Jueves 27/4 | BS87: No | BT87: Si | BU87: Si | BV87: No | BW87: No | BX87: No | BY87: Si | BZ87: Si | CA87: Si | CE87: Si | CF87: Si | CJ87: Si | CK87: Si | CN87: Si | CO87: Si | CP87: nos adaptamos a lo que uds dispongan, para nosotros todo es novedad y aprendizaje
A88: 45005.547 | B88: roberto.holub@philips.edu.ar | C88: ESCUELA TECNICA PHILIPS ARGENTINA | D88: 020012900 | E88: 5. Técnicas área producción (electromecánica, mecánica, metalurgia, electricidad, automotores, refrigeración, construcciones, maestro mayor de obras, aeronáutica, naval, aviónico, óptico, en geografía matemática) | F88: ELECTROMECANICA | G88: Privada | H88: ROBERTO HOLUB | I88: NATALIA GRIMALDI | J88: FACUNDO ALBERINO | K88: roberto.holub@philips.edu.ar | L88: CABA | M88: COLEGIALES | N88: 31 | O88: 6º Secundaria (Prov.) / 5º Media (CABA) | P88: 5 | Q88: 4 | R88: 0 | T88: Si | U88: No | V88: Miércoles 26/4 | AU88: No | AV88: Si | AW88: No | AX88: No | AY88: Si | AZ88: No | BA88: No | BB88: No | BC88: No | BD88: Si | BE88: No | BF88: No | BG88: No | BH88: No | BI88: No | BJ88: No | BK88: No | BL88: No | BM88: No | BN88: No | BO88: No | BP88: No | BQ88: No
A89: 45001.941 | B89: gonzalez.mercedes.sanjo@gmail.com | C89: Instituto San José | D89: 020169900 | E89: 9. Liceos / Normales / Colegios / Institutos orientados en ciencias sociales y/o humanidades | F89: Comunicación | G89: Privada | H89: Mercedes Gonzalez | I89: Carolina Malter | J89: Diego Pozzi | K89: gonzalez.mercedes.sanjo@gmail.com | L89: CABA | M89: Balvanera | N89: 30 | O89: 6º Secundaria (Prov.) / 5º Media (CABA) | P89: 5 | Q89: 5 | R89: 10 | T89: Si | U89: Si | V89: Jueves 27/4 | BS89: No | BT89: No | BU89: No | BV89: No | BW89: No | BX89: Si | BY89: Si | BZ89: Si | CA89: Si | CB89: No | CC89: No | CD89: No | CE89: No | CF89: No | CG89: Si | CH89: Si | CI89: Si | CJ89: Si | CK89: Si | CL89: Si | CM89: Si | CN89: Si | CO89: Si | CP89: Según los horarios que ustedes dispongan deseamos participar de VISITA GUIADA, ESTACIONES INTERACTIVAS y ARTE MATEMÁTICO.
A90: 45005.507 | B90: jp.alvarez29@gmail.com | C90: Instituto Almirante Guillermo Brown | D90: 060627100 | E90: 9. Liceos / Normales / Colegios / Institutos orientados en ciencias sociales y/o humanidades | F90: Sociales | G90: Privada | H90: Juan Pablo Alvarez | I90: Micaela Borda | J90: Nahuel Furchi | K90: jp.alvarez29@gmail.com | L90: ÁREA METROPOLITANA DE BUENOS AIRES | M90: Haedo, Morón | N90: 40 | O90: 6º Secundaria (Prov.) / 5º Media (CABA) | P90: 5 | Q90: 4 | R90: 10 | S90: Son tres divisiones de 6to. No realizo la inscripción de manera separada, ya que el colegio solicita que se vayan con los tres cursos el mismo día. | T90: Si | U90: Si | V90: Martes 25/4 | W90: Si | X90: No | Y90: Si | Z90: No | AA90: Si | AB90: No | AC90: No | AD90: No | AE90: No | AJ90: Si | AK90: No | AL90: No | AM90: No | AN90: No | AO90: No
A91: 45002.995 | B91: ceciliadiaz@docentes.sanmaron.edu.ar | C91: INSTITUTO SAN MARON | D91: 020056200 | E91: 9. Liceos / Normales / Colegios / Institutos orientados en ciencias sociales y/o humanidades | F91: Sociales y Humanidades | G91: Privada | H91: Cecilia Díaz | I91: Marcela Urbano | K91: ceciliadiaz@docentes.sanmaron.edu.ar | L91: CABA | M91: Retiro | N91: 25 | O91: 6º Secundaria (Prov.) / 5º Media (CABA) | P91: 4 | Q91: 3 | R91: 8 | T91: Si | U91: No | V91: Martes 25/4 | W91: Si | X91: No | Y91: No | Z91: No | AA91: No | AB91: No | AC91: Si | AD91: No | AE91: No | AF91: No | AG91: Si | AH91: No | AI91: No | AJ91: No | AK91: No | AL91: No | AM91: Si | AN91: No | AO91: No | AP91: No | AQ91: No | AR91: No | AS91: No
A92: 45001.665 | B92: vanina.acuna89@gmail.com | C92: Instituto Palomar de Caseros | D92: 060522400 | E92: 10. Liceos / Normales / Colegios / Institutos de otras orientaciones | F92: COMUNICACIONES Y CIENCIAS SOCIALES | G92: Privada | H92: Vanina Acuña | I92: Roxana politino | K92: vanina.acuna89@gmail.com | L92: ÁREA METROPOLITANA DE BUENOS AIRES | M92: Ciudad Jardin | N92: 35 | O92: 6º Secundaria (Prov.) / 5º Media (CABA) | P92: 3 | Q92: 3 | R92: 5 | T92: No | U92: Si | V92: Martes 25/4 | W92: No | X92: No | Y92: Si | Z92: No | AA92: No | AB92: No | AC92: Si | AD92: Si | AE92: Si | AF92: No | AG92: No | AI92: Si | AJ92: Si | AK92: No | AL92: No | AM92: No | AN92: Si | AO92: Si | AP92: No | AQ92: No | AR92: Si | AS92: Si
A93: 45001.757 | B93: carla.spazzali@gmail.com | C93: Instituto Santa María de Nazareth | D93: 020082200 | E93: 10. Liceos / Normales / Colegios / Institutos de otras orientaciones | F93: economía y comunicación | G93: Privada | H93: Carla | I93: Spazzali | J93: Belen Gonzalez | K93: carla.spazzali@gmail.com | L93: CABA | M93: saavedra | N93: 40 | O93: 6º Secundaria (Prov.) / 5º Media (CABA) | P93: 3 | Q93: 3 | R93: 5 | T93: Si | U93: No | V93: Martes 25/4 | W93: Si | X93: Si | Y93: No | Z93: Si | AA93: Si | AB93: Si | AC93: No | AD93: No | AE93: No | AF93: Si | AG93: Si | AH93: Si | AI93: No | AJ93: No | AK93: Si | AL93: Si | AM93: Si | AN93: No | AO93: No | AP93: Si | AQ93: Si | AR93: No | AS93: No
A94: 45005.635 | B94: secundaria@santiagoapostol.edu.ar | C94: Instituto Argentino Gallego Santiago Apóstol | D94: 020212700 | E94: 9. Liceos / Normales / Colegios / Institutos orientados en ciencias sociales y/o humanidades | F94: Bachiller en Ciencias Sociales y Humanidades | G94: Privada | H94: Ángeles Sananez | I94: Bibiana Rodríguez | J94: Rocío Da Silva | K94: secundaria@santiagoapostol.edu.ar | L94: CABA | M94: Balvanera - Ciudad Autónoma de Buenos Aires | N94: 20 | O94: 6º Secundaria (Prov.) / 5º Media (CABA) | P94: 5 | Q94: 3 | R94: 5 | T94: Si | U94: Si | V94: Miércoles 26/4 | AU94: Si | AV94: Si | AW94: Si | AX94: Si | AY94: Si | AZ94: Si | BA94: Si | BB94: Si | BC94: Si | BD94: Si | BE94: Si | BF94: Si | BG94: Si | BH94: Si | BI94: Si | BJ94: Si | BK94: Si | BL94: Si | BM94: Si | BN94: Si | BO94: Si | BP94: Si | BQ94: Si | BR94: Tildé muchas opciones de turnos para que nos asignen las que ustedes consideren.
A95: 45005.923 | B95: vicedireccionsagradocorazon@gmail.com | C95: Colegio Sagrado Corazon de Jesus | D95: 061607500 | E95: 9. Liceos / Normales / Colegios / Institutos orientados en ciencias sociales y/o humanidades | F95: Ciencias Sociales | G95: Privada | H95: Gabriela Lujan | I95: Claudio Bedoya | J95: Ileana Benedetti | K95: vicedireccionsagradocorazon@gmail.com | L95: CABA | M95: Quilmes | N95: 30 | O95: 6º Secundaria (Prov.) / 5º Media (CABA) | P95: 4 | Q95: 4 | R95: 5 | T95: Si | U95: No | V95: Miércoles 26/4 | AU95: No | AV95: Si | AW95: No | AX95: No | AY95: No | AZ95: Si | BA95: No | BB95: No | BC95: No | BD95: No | BE95: No | BF95: No | BG95: Si | BH95: No | BI95: Si | BJ95: No | BK95: No | BL95: No | BM95: No | BN95: Si | BR95: De ser necesario, para participar de todas las actividades, nos podemos quedar en el turno tarde.
A96: 45003.55 | B96: nariv@misericordiadevoto.edu.ar | C96: Colegio Nuestra Señora de la Misericordia de devoto A-110 | D96: 020086000 | E96: 9. Liceos / Normales / Colegios / Institutos orientados en ciencias sociales y/o humanidades | F96: Humanidades y Cs. Sociales | G96: Privada | H96: Victoria Anahí Nari | I96: Maria Adriana Lopez | J96: Ignacio Gonzalez | K96: nariv@misericordiadevoto.edu.ar | L96: CABA | M96: Devoto | N96: 30 | O96: 6º Secundaria (Prov.) / 5º Media (CABA) | P96: 3 | Q96: 2 | R96: 5 | T96: No | U96: Si | V96: Miércoles 26/4 | AU96: No | AV96: No | AW96: Si | AX96: No | AY96: No | AZ96: No | BA96: Si | BB96: No | BC96: Si | BD96: No | BE96: No | BF96: No | BG96: No | BH96: Si | BI96: No | BJ96: No | BK96: No | BL96: No | BM96: No | BN96: No | BO96: No | BQ96: No
A97: 45003.553 | B97: nariv@misericordiadevoto.edu.ar | C97: Colegio Nuestra Señora de la Misericordia de devoto A-110 | D97: 020086000 | E97: 9. Liceos / Normales / Colegios / Institutos orientados en ciencias sociales y/o humanidades | F97: Humanidades y Cs. Sociales | G97: Privada | H97: Maria Adriana Lopez | I97: Victoria Anahí Nari | J97: Ignacio Gonzalez | K97: nariv@misericordiadevoto.edu.ar | L97: CABA | M97: Devoto | N97: 28 | O97: 6º Secundaria (Prov.) / 5º Media (CABA) | P97: 3 | Q97: 2 | R97: 5 | T97: No | U97: Si | V97: Miércoles 26/4 | AU97: No | AV97: No | AW97: Si | AX97: No | AY97: No | AZ97: No | BA97: Si | BB97: No | BC97: Si | BD97: No | BE97: No | BF97: No | BG97: No | BH97: Si | BI97: No | BJ97: No | BK97: No | BL97: No | BM97: No | BN97: No | BO97: No | BP97: No | BQ97: No
A98: 45002.494 | B98: ciademaria_nivelmedio@yahoo.com.ar | C98: Instituto Compañía de María | D98: 020099900 | E98: 9. Liceos / Normales / Colegios / Institutos orientados en ciencias sociales y/o humanidades | F98: Bachiller en Humanidades y Ciencias Sociales | G98: Privada | H98: Mara Barbagallo | I98: Caludia Vezzaro | J98: Guadalupe Carillo | K98: ciademaria_nivelmedio@yahoo.com.ar | L98: CABA | M98: Colegiales | N98: 18 | O98: 6º Secundaria (Prov.) / 5º Media (CABA) | P98: 4 | Q98: 5 | R98: 1 | T98: Si | U98: No | V98: Miércoles 26/4 | AU98: No | AV98: Si | AW98: No | AX98: No | AY98: Si | AZ98: No | BA98: No | BB98: No | BC98: No | BD98: Si | BE98: No | BF98: No | BG98: No | BH98: No
A99: 45001.588 | B99: mmcannilla@gmail.com | C99: COLEGIO LINCOLN | D99: 020097800 | E99: 10. Liceos / Normales / Colegios / Institutos de otras orientaciones | F99: Bachiller Bilingue con Orientación en letras y ciencias sociales | G99: Privada | H99: María Marta Cannilla | I99: Guadalupe Rosso | J99: Mercedes Álvarez | K99: mmcannilla@gmail.com | L99: CABA | M99: Belgrano | N99: 33 | O99: 6º Secundaria (Prov.) / 5º Media (CABA) | P99: 5 | Q99: 5 | R99: 0 | T99: Si | U99: No | V99: Martes 25/4 | W99: Si | X99: No | Y99: No | Z99: No | AA99: Si | AB99: Si | AC99: No | AD99: No | AE99: No | AF99: No | AG99: No | AH99: No | AI99: No | AJ99: No | AK99: No | AL99: Si | AM99: Si | AN99: No | AO99: No | AP99: No | AQ99: No | AR99: No | AS99: No
A100: 45002.606 | B100: imc.secundaria@hotmail.com.ar | C100: Instituto Miguel Cané | D100: 061237500 | E100: 10. Liceos / Normales / Colegios / Institutos de otras orientaciones | F100: Bachiller en Arte - Artes Visuales | G100: Privada | H100: Facundo Peredo | I100: Victoria Porgi | J100: Christian Martínez Leguizamón | K100: imc.secundaria@hotmail.com.ar | L100: ÁREA METROPOLITANA DE BUENOS AIRES | M100: San Justo, La Matanza | N100: 32 | O100: 6º Secundaria (Prov.) / 5º Media (CABA) | P100: 5 | Q100: 4 | R100: 0 | T100: Si | U100: No | V100: Miércoles 26/4 | AU100: Si | AV100: No | AW100: No | AX100: No | AY100: Si | AZ100: Si | BA100: No | BB100: No | BC100: No | BD100: No | BE100: Si | BF100: Si | BG100: No | BH100: No | BI100: No | BJ100: Si | BK100: Si | BL100: No | BM100: No | BN100: No | BO100: No | BP100: No | BQ100: No
...

Sheet CRUDO MARTES
A1: Marca temporal | B1: Dirección de correo electrónico | C1: Nombre OFICIAL y COMPLETO de la institución educativa | D1: Código Único de Escuela (CUE) | E1: Tipo de escuela y orientación | F1: Especifique su orientación | G1: Gestión | H1: Nombre y apellido del/la docente responsable de la visita | I1: Nombre y apellido del/la docente acompañante 1 | J1: Nombre y apellido del/la docente acompañante 2 | K1: Dirección de correo electrónico para recibir resultado de la asignación | L1: Ubicación general de la escuela | M1: Barrio/Localidad de la escuela | N1: Cantidad de alumnos que asistirán | O1: Curso que asistirá | P1: Conectividad en la institución | Q1: Acceso a las ciencias exactas y naturales | R1: Porcentaje aproximado de estudiantes de familias de bajos recursos | S1: Exprese observaciones o comentarios que considere pertinentes | T1: Turno/s solicitado/s [Turno mañana (9:00 a 12.30 hs.)] | U1: Turno/s solicitado/s [Turno tarde (12.30 a 16:00 hs.)] | V1: Fecha solicitada | W1: CHARLAS [9:30 Redes sociales: la matemática detrás de los "influencers". Rocío Balderrama] | X1: CHARLAS [11:30 La Biblio junto a... la calculadora. Historias que no hacen historia. Juan Carlos Pedraza] | Y1: CHARLAS [14:00 ¿Cómo hacer ciencia con Twitter? Sofía del Pozo] | Z1: ESTACIONES INTERACTIVAS [9:30] | AA1: ESTACIONES INTERACTIVAS [10:30] | AB1: ESTACIONES INTERACTIVAS [11:30] | AC1: ESTACIONES INTERACTIVAS [13:00] | AD1: ESTACIONES INTERACTIVAS [14:00] | AE1: ESTACIONES INTERACTIVAS [15:00] | AF1: TALLERES [9:30] | AG1: TALLERES [10:30] | AH1: TALLERES [11:30] | AI1: TALLERES [14:00] | AJ1: TALLERES [15:00] | AK1: ARTE MATEMÁTICO [9:30] | AL1: ARTE MATEMÁTICO [10:30] | AM1: ARTE MATEMÁTICO [11:30] | AN1: ARTE MATEMÁTICO [14:00] | AO1: ARTE MATEMÁTICO [15:00] | AP1: VISITAS GUIADAS TEMÁTICAS [10:30] | AQ1: VISITAS GUIADAS TEMÁTICAS [11:30] | AR1: VISITAS GUIADAS TEMÁTICAS [14:00] | AS1: VISITAS GUIADAS TEMÁTICAS [15:00] | AT1: Exprese cualquier aclaración sobre la solicitud de inscripción que facilite la administración de vacantes. | AU1: CHARLAS [9:30 Desorden ordenado, ¡qué caos es esto! Paula Kuna] | AV1: CHARLAS [11:30 ¿Tenés una idea para cambiar el mundo? Primero simulalo. Rodrigo Castro] | AW1: CHARLAS [14:00 Embaldosados Fractales. Ursula Molter] | AX1: ESTACIONES INTERACTIVAS [9:30] | AY1: ESTACIONES INTERACTIVAS [10:30] | AZ1: ESTACIONES INTERACTIVAS [11:30] | BA1: ESTACIONES INTERACTIVAS [13:00] | BB1: ESTACIONES INTERACTIVAS [14:00] | BC1: ESTACIONES INTERACTIVAS [15:00] | BD1: TALLERES [9.30] | BE1: TALLERES [10:30] | BF1: TALLERES [11:30] | BG1: TALLERES [14:00] | BH1: TALLERES [15:00] | BI1: ARTE MATEMÁTICO [9:30] | BJ1: ARTE MATEMÁTICO [10:30] | BK1: ARTE MATEMÁTICO [11:30] | BL1: ARTE MATEMÁTICO [14:00] | BM1: ARTE MATEMÁTICO [15:00] | BN1: VISITA GUIADA [10:30] | BO1: VISITA GUIADA [11:30] | BP1: VISITA GUIADA [14:00] | BQ1: VISITA GUIADA [15:00] | BR1: Exprese cualquier aclaración sobre la solicitud de inscripción que facilite la administración de vacantes. | BS1: CHARLAS [9:30 Geometría proyectiva, fotografía y la final del mundo. Charly Di Fiore] | BT1: CHARLAS [11:30 Detective de datos. Guillermo Solovey] | BU1: CHARLAS [14:00 Datos y deportes. Iván Monardo] | BV1: ESTACIONES INTERACTIVAS [9:30] | BW1: ESTACIONES INTERACTIVAS [10:30] | BX1: ESTACIONES INTERACTIVAS [11:30] | BY1: ESTACIONES INTERACTIVAS [13:00] | BZ1: ESTACIONES INTERACTIVAS [14:00] | CA1: ESTACIONES INTERACTIVAS [15:00] | CB1: TALLERES [9:30] | CC1: TALLERES [10:30 ] | CD1: TALLERES [11:30] | CE1: TALLERES [14:00] | CF1: TALLERES [15:00] | CG1: ARTE MATEMÁTICO [9:30] | CH1: ARTE MATEMÁTICO [10:30] | CI1: ARTE MATEMÁTICO [11:30] | CJ1: ARTE MATEMÁTICO [14:00] | CK1: ARTE MATEMÁTICO [15:00] | CL1: VISITA GUIADA [10:30] | CM1: VISITA GUIADA [11:30] | CN1: VISITA GUIADA [14:00] | CO1: VISITA GUIADA [15:00] | CP1: Exprese cualquier aclaración sobre la solicitud de inscripción que facilite la administración de vacantes.
A2: 45003.486 | B2: romina.angulo@bue.edu.ar | C2: ESCUELA TECNICA Nº12 "LIBERTADOR GRAL. SAN MARTIN" | D2: 020050900 | E2: 2. Técnicas en computación, electrónica, informática | F2: ELECTRONICA | G2: Estatal | H2: ROMINA ANGULO | I2: MICAELA RODRIGUEZ | K2: romina.angulo@bue.edu.ar | L2: CABA | M2: RETIRO | N2: 17 | O2: 5º Secundaria (Prov.) / 4º Media (CABA) | P2: 3 | Q2: 3 | R2: 90 | T2: No | U2: Si | V2: Martes 25/4 | W2: No | X2: No | Y2: Si | Z2: No | AA2: No | AB2: No | AC2: Si | AD2: No | AE2: No | AF2: No | AG2: No | AH2: No | AI2: No | AJ2: Si | AK2: No | AL2: No | AM2: No | AN2: Si | AO2: No | AP2: No | AQ2: No | AR2: No | AS2: No
A3: 45002.995 | B3: ceciliadiaz@docentes.sanmaron.edu.ar | C3: INSTITUTO SAN MARON | D3: 020056200 | E3: 9. Liceos / Normales / Colegios / Institutos orientados en ciencias sociales y/o humanidades | F3: Sociales y Humanidades | G3: Privada | H3: Cecilia Díaz | I3: Marcela Urbano | K3: ceciliadiaz@docentes.sanmaron.edu.ar | L3: CABA | M3: Retiro | N3: 25 | O3: 6º Secundaria (Prov.) / 5º Media (CABA) | P3: 4 | Q3: 3 | R3: 8 | T3: Si | U3: No | V3: Martes 25/4 | W3: Si | X3: No | Y3: No | Z3: No | AA3: No | AB3: No | AC3: Si | AD3: No | AE3: No | AF3: No | AG3: Si | AH3: No | AI3: No | AJ3: No | AK3: No | AL3: No | AM3: Si | AN3: No | AO3: No | AP3: No | AQ3: No | AR3: No | AS3: No
A4: 45004.571 | B4: fbeitia@hotmail.com | C4: INST.EDUC.ARG.NTRA.SRA.DE LUJAN | D4: 020059400 | E4: 10. Liceos / Normales / Colegios / Institutos de otras orientaciones | F4: Bachillerato con orientación en Comunicación Social | G4: Privada | H4: Fernando Beitia | I4: Fernanda Goldaracena | J4: Jéssica Maidana | K4: fbeitia@hotmail.com | L4: CABA | M4: Villa Pueyrredón | N4: 34 | O4: 6º Secundaria (Prov.) / 5º Media (CABA) | P4: 4 | Q4: 4 | R4: 15 | T4: Si | U4: No | V4: Martes 25/4 | W4: Si | X4: Si | Y4: No | Z4: No | AA4: Si | AB4: No | AC4: No | AD4: No | AE4: No | AF4: No | AG4: No | AH4: No | AI4: No | AJ4: No | AK4: No | AL4: No | AM4: No | AN4: No | AO4: No | AP4: No | AQ4: No | AR4: No | AS4: No
A5: 45004.573 | B5: fbeitia@hotmail.com | C5: INST.EDUC.ARG.NTRA.SRA.DE LUJAN | D5: 020059400 | E5: 10. Liceos / Normales / Colegios / Institutos de otras orientaciones | F5: Bachillerato con orientación en Economía y Administración | G5: Privada | H5: Jéssica Maidana | I5: Fernanda Goldaracena | J5: Fernando Beitia | K5: fbeitia@hotmail.com | L5: CABA | M5: Villa Pueyrredón | N5: 35 | O5: 6º Secundaria (Prov.) / 5º Media (CABA) | P5: 4 | Q5: 4 | R5: 15 | T5: Si | U5: No | V5: Martes 25/4 | W5: Si | X5: Si | Y5: No | Z5: No | AA5: Si | AB5: No | AC5: No | AD5: No | AE5: No | AF5: No | AG5: Si | AH5: No | AI5: No | AJ5: No | AK5: No | AL5: No | AM5: No | AN5: No | AO5: No | AP5: No | AQ5: No | AR5: No | AS5: No
A6: 45004.575 | B6: fbeitia@hotmail.com | C6: INST.EDUC.ARG.NTRA.SRA.DE LUJAN | D6: 020059400 | E6: 10. Liceos / Normales / Colegios / Institutos de otras orientaciones | F6: Bachillerato con orientación en Informática | G6: Privada | H6: Jéssica Maidana | I6: Fernanda Goldaracena | J6: Fernando Beitia | K6: fbeitia@hotmail.com | L6: CABA | M6: Villa Pueyrredón | N6: 33 | O6: 6º Secundaria (Prov.) / 5º Media (CABA) | P6: 4 | Q6: 4 | R6: 15 | T6: Si | U6: No | V6: Martes 25/4 | W6: Si | X6: Si | Y6: No | Z6: No | AA6: Si | AB6: No | AC6: No | AD6: No | AE6: No | AF6: No | AG6: Si | AH6: No | AI6: No | AJ6: No | AK6: No | AL6: Si | AM6: No | AN6: No | AO6: No | AP6: No | AQ6: Si | AR6: No | AS6: No
A7: 45002.545 | B7: secretaria.secundaria@sangregorio.edu.ar | C7: Instituto educativo san gregorio el iluminador | D7: 020074000 | E7: 10. Liceos / Normales / Colegios / Institutos de otras orientaciones | F7: Economía y administración | G7: Privada | H7: Adriana Margossian | I7: Adriana Maegossian | J7: Mariana Crespo | K7: secretaria.secundaria@sangregorio.edu.ar | L7: CABA | M7: Palermo | N7: 24 | O7: 6º Secundaria (Prov.) / 5º Media (CABA) | P7: 4 | Q7: 4 | R7: 30 | S7: A pesar de tener la orientación de economía y administración, tenes alumnos interesados en carreras de ciencias exactas y naturales, y desde las materias matematica y química y física fomentamos estas ciencias | T7: Si | U7: No | V7: Martes 25/4 | W7: Si | X7: No | Y7: Si | Z7: No | AA7: Si | AB7: Si | AC7: No | AD7: No | AE7: No | AF7: No | AG7: Si | AH7: Si | AI7: No | AJ7: No | AK7: No | AL7: Si | AM7: Si | AN7: No | AO7: No | AP7: Si | AQ7: Si | AR7: No | AS7: No
A8: 45003.74 | B8: secretaria.secundaria@sangregorio.edu.ar | C8: instituto educativo san gregorio el iluminador | D8: 020074000 | E8: 10. Liceos / Normales / Colegios / Institutos de otras orientaciones | F8: Economía y administración | G8: Privada | H8: Adriana Margossian | I8: Adriana Margossian | J8: Mariana crespo | K8: secretaria.secundaria@sangregorio.edu.ar | L8: CABA | M8: Palermo | N8: 25 | O8: 6º Secundaria (Prov.) / 5º Media (CABA) | P8: 4 | Q8: 4 | R8: 30 | S8: A pesar de tener la orientación de economía y administración, tenes alumnos interesados en carreras de ciencias exactas y naturales, y desde las materias matematica y química y física fomentamos estas ciencias | T8: Si | U8: No | V8: Martes 25/4 | W8: Si | X8: No | Y8: No | Z8: No | AA8: Si | AB8: Si | AC8: No | AD8: No | AE8: No | AF8: No | AG8: Si | AH8: Si | AI8: No | AJ8: No | AK8: No | AL8: Si | AM8: Si | AN8: No | AO8: No | AP8: Si | AQ8: Si | AR8: No | AS8: No
A9: 45002.34 | B9: biblioteca@casasantacatalina.com.ar | C9: Instituto privado santa catalina | D9: 020076800 | E9: 10. Liceos / Normales / Colegios / Institutos de otras orientaciones | F9: Economía y Administración | G9: Privada | H9: Paz Rozen | I9: Alicia Mendella | K9: biblioteca@casasantacatalina.com.ar | L9: CABA | M9: Constitucion | N9: 35 | O9: 6º Secundaria (Prov.) / 5º Media (CABA) | P9: 3 | Q9: 2 | R9: 20 | S9: Este formulario lo complete ayer pero confundi la orientacion del curso. Puse Técnicas en administración de empresas, administración de las organizaciones, servicios turísticos, multimedios en lugar de 10. Liceos / Normales / Colegios / Institutos de otras orientaciones, mil disculpas. | T9: Si | U9: No | V9: Martes 25/4 | W9: Si | X9: Si | Y9: No | Z9: Si | AA9: Si | AB9: Si | AC9: No | AD9: No | AE9: No | AF9: Si | AG9: Si | AH9: Si | AI9: No | AJ9: No | AK9: Si | AL9: Si | AM9: Si | AN9: No | AO9: No | AP9: Si | AQ9: Si | AR9: No | AS9: No
A10: 45001.497 | B10: biblioteca@casasantacatalina.com.ar | C10: Instituto Privado Santa Catalina | D10: 020076800 | E10: 3. Técnicas en administración de empresas, administración de las organizaciones, servicios turísticos, multimedios | F10: Administracion | G10: Privada | H10: Paz Rozen | I10: Alicia Mendella | K10: biblioteca@casasantacatalina.com.ar | L10: CABA | M10: Constitucion | N10: 35 | O10: 6º Secundaria (Prov.) / 5º Media (CABA) | P10: 3 | Q10: 2 | R10: 20 | T10: Si | U10: No | V10: Martes 25/4 | W10: Si | X10: Si | Y10: No | Z10: Si | AA10: Si | AB10: Si | AC10: No | AD10: No | AE10: No | AF10: Si | AG10: Si | AH10: Si | AI10: No | AJ10: No | AK10: Si | AL10: Si | AM10: Si | AN10: No | AO10: No | AP10: Si | AQ10: Si | AR10: No | AS10: No
A11: 45002.736 | B11: lulizobra@gmail.com | C11: Colegio San Francisco Coll | D11: 020078500 | E11: 10. Liceos / Normales / Colegios / Institutos de otras orientaciones | F11: Economía y Administración | G11: Privada | H11: Lucila Zobra | I11: Silvina Salvia | J11: Macarena Sanguiao | K11: lulizobra@gmail.com | L11: CABA | M11: Villa Urquiza | N11: 31 | O11: 6º Secundaria (Prov.) / 5º Media (CABA) | P11: 4 | Q11: 4 | R11: 25 | T11: Si | U11: No | V11: Martes 25/4 | W11: Si | X11: No | Y11: No | Z11: No | AA11: Si | AB11: Si | AC11: No | AD11: No | AE11: No | AF11: No | AG11: Si | AH11: Si | AI11: No | AJ11: No | AK11: No | AL11: Si | AM11: Si | AN11: No | AO11: No | AP11: No | AQ11: No | AR11: No | AS11: No
A12: 45002.738 | B12: sfc.lucilazobra@gmail.com | C12: Colegio San Francisco Coll | D12: 020078500 | E12: 10. Liceos / Normales / Colegios / Institutos de otras orientaciones | F12: Economía y Administración | G12: Privada | H12: Lucila Zobra | I12: Silvina Salvia | J12: Macarena Sanguiao | K12: sfc.lucilazobra@gmail.com | L12: CABA | M12: Villa Urquiza | N12: 34 | O12: 6º Secundaria (Prov.) / 5º Media (CABA) | P12: 4 | Q12: 4 | R12: 25 | T12: Si | U12: No | V12: Martes 25/4 | W12: Si | X12: No | Y12: No | Z12: No | AA12: Si | AB12: Si | AC12: No | AD12: No | AE12: No | AF12: No | AG12: Si | AH12: Si | AI12: No | AJ12: No | AK12: No | AL12: Si | AM12: Si | AN12: No | AO12: No | AP12: No | AQ12: No | AR12: No | AS12: No
A13: 45001.757 | B13: carla.spazzali@gmail.com | C13: Instituto Santa María de Nazareth | D13: 020082200 | E13: 10. Liceos / Normales / Colegios / Institutos de otras orientaciones | F13: economía y comunicación | G13: Privada | H13: Carla | I13: Spazzali | J13: Belen Gonzalez | K13: carla.spazzali@gmail.com | L13: CABA | M13: saavedra | N13: 40 | O13: 6º Secundaria (Prov.) / 5º Media (CABA) | P13: 3 | Q13: 3 | R13: 5 | T13: Si | U13: No | V13: Martes 25/4 | W13: Si | X13: Si | Y13: No | Z13: Si | AA13: Si | AB13: Si | AC13: No | AD13: No | AE13: No | AF13: Si | AG13: Si | AH13: Si | AI13: No | AJ13: No | AK13: Si | AL13: Si | AM13: Si | AN13: No | AO13: No | AP13: Si | AQ13: Si | AR13: No | AS13: No
A14: 45000.67 | B14: morelli.nicolas.a@gmail.com | C14: Colegio Norbridge | D14: 020082300 | E14: 10. Liceos / Normales / Colegios / Institutos de otras orientaciones | F14: Economía y Administración | G14: Privada | H14: Nicolás Morelli | I14: Liliana Villena | J14: Alejandra Sánchez | K14: morelli.nicolas.a@gmail.com | L14: CABA | M14: Saavedra | N14: 36 | O14: 6º Secundaria (Prov.) / 5º Media (CABA) | P14: 4 | Q14: 4 | R14: 0 | S14: Llevamos todos los años a nuestro 5to año a la Semana De la Matemática y los estudiantes la disfrutan mucho! | T14: Si | U14: No | V14: Martes 25/4 | W14: Si | X14: No | Y14: No | Z14: No | AA14: No | AB14: Si | AC14: No | AD14: No | AE14: No | AF14: No | AG14: No | AH14: No | AI14: No | AJ14: No | AK14: No | AL14: No | AM14: Si | AN14: No | AO14: No | AP14: Si | AQ14: No | AR14: No | AS14: No | AT14: Nos gustaría poder hacer la visita guiada ya que el año pasado no pudimos.
A15: 45002.413 | B15: yaninasdiaz86@gmail.com | C15: ENS N°2 "Mariano Acosta" | D15: 020086600 | E15: 1. Liceos / Normales / Colegios / Institutos orientados en ciencias naturales y/o exactas | F15: Normal | G15: Estatal | H15: Diaz Yanina | I15: Redin Clarisa | J15: Grandal Natalia | K15: yaninas.diaz@bue.edu.ar | L15: CABA | M15: Balvanera | N15: 35 | O15: 6º Secundaria (Prov.) / 5º Media (CABA) | P15: 4 | Q15: 4 | R15: 10 | T15: Si | U15: Si | V15: Martes 25/4 | W15: Si | X15: No | Y15: No | Z15: No | AA15: No | AB15: Si | AC15: Si | AD15: No | AE15: No | AF15: No | AG15: Si | AH15: Si | AI15: No | AJ15: No | AK15: No | AL15: Si | AM15: Si | AN15: No | AO15: No | AP15: Si | AQ15: Si | AR15: No | AS15: No
A16: 45001.588 | B16: mmcannilla@gmail.com | C16: COLEGIO LINCOLN | D16: 020097800 | E16: 10. Liceos / Normales / Colegios / Institutos de otras orientaciones | F16: Bachiller Bilingue con Orientación en letras y ciencias sociales | G16: Privada | H16: María Marta Cannilla | I16: Guadalupe Rosso | J16: Mercedes Álvarez | K16: mmcannilla@gmail.com | L16: CABA | M16: Belgrano | N16: 33 | O16: 6º Secundaria (Prov.) / 5º Media (CABA) | P16: 5 | Q16: 5 | R16: 0 | T16: Si | U16: No | V16: Martes 25/4 | W16: Si | X16: No | Y16: No | Z16: No | AA16: Si | AB16: Si | AC16: No | AD16: No | AE16: No | AF16: No | AG16: No | AH16: No | AI16: No | AJ16: No | AK16: No | AL16: Si | AM16: Si | AN16: No | AO16: No | AP16: No | AQ16: No | AR16: No | AS16: No
A17: 45002.352 | B17: ciademaria_nivelmedio@yahoo.com.ar | C17: Instituto Compañía de María | D17: 020099900 | E17: 3. Técnicas en administración de empresas, administración de las organizaciones, servicios turísticos, multimedios | F17: Bachiller en Economía y Administración | G17: Privada | H17: Mara Barbagallo | I17: Claudia Vezzaro | J17: Guadalupe Carrillo | K17: ciademaria_nivelmedio@yahoo.com.ar | L17: CABA | M17: Colegiales | N17: 26 | O17: 6º Secundaria (Prov.) / 5º Media (CABA) | P17: 4 | Q17: 5 | R17: 1 | T17: Si | U17: No | V17: Martes 25/4 | W17: Si | X17: No | Y17: No | Z17: No | AA17: Si | AB17: No | AC17: No | AD17: No | AE17: No | AF17: No | AG17: No | AH17: Si | AI17: No | AJ17: No | AK17: No | AL17: No | AM17: Si | AN17: No | AO17: No
A18: 45002.002 | B18: liliana.molina@bue.edu.ar | C18: E.E.M.N°1 DE 20 Biblioteca del Congreso de la Nación | D18: 020106200 | E18: 4. Artísticas de todas las orientaciones | F18: Artes Visuales | G18: Estatal | H18: Liliana Ines Molina | I18: Carolina Rivarola | J18: Candela García | K18: liliana.molina@bue.edu.ar | L18: CABA | M18: Villa Lugano | N18: 35 | O18: 3º Secundaria (Prov.) / 2º Media (CABA) | P18: 4 | Q18: 2 | R18: 95 | T18: Si | U18: No | V18: Martes 25/4 | W18: Si | X18: No | Y18: No | Z18: No | AA18: Si | AB18: No | AC18: No | AD18: No | AE18: No | AF18: No | AG18: No | AH18: No | AI18: No | AJ18: No | AK18: No | AL18: No | AM18: Si | AN18: No | AO18: No | AP18: No | AQ18: No | AR18: No | AS18: No
A19: 45000.716 | B19: laurabusso@bue.edu.ar | C19: Escuela Normal N°9 Domingo F Sarmiento | D19: 020113300 | E19: 1. Liceos / Normales / Colegios / Institutos orientados en ciencias naturales y/o exactas | F19: Educación | G19: Estatal | H19: María Laura Busso | I19: María Fernanda Faggionatto | J19: Gonzalo Godoy | K19: laurabusso@bue.edu.ar | L19: CABA | M19: Balvanera | N19: 28 | O19: 5º Secundaria (Prov.) / 4º Media (CABA) | P19: 3 | Q19: 2 | R19: 30 | S19: Nos resulta una propuesta complementaria para un proyecto que estamos armando con los estudiantes. | T19: Si | U19: No | V19: Martes 25/4 | W19: Si | X19: No | Y19: No | Z19: No | AA19: No | AB19: Si | AC19: No | AD19: No | AE19: No | AF19: No | AG19: Si | AH19: No | AI19: No | AJ19: No | AK19: No | AL19: No | AM19: Si | AN19: No | AO19: No | AP19: No | AQ19: No | AR19: No | AS19: No | AT19: Nuestra salida esta autorizada hasta las 12.15hs
A20: 45005.613 | B20: gabriela.lucca@bue.edu.ar | C20: ENS Nº 10 JUAN BAUTISTA ALBERDI DE 10 | D20: 020121400 | E20: 1. Liceos / Normales / Colegios / Institutos orientados en ciencias naturales y/o exactas | F20: Naturales | G20: Estatal | H20: Gabriela Lucca | I20: Cecilia Accorinti | J20: Alejandra Falconi | K20: gabriela.lucca@bue.edu.ar | L20: CABA | M20: Belgrano | N20: 40 | O20: 5º Secundaria (Prov.) / 4º Media (CABA) | P20: 4 | Q20: 4 | R20: 20 | S20: son 41 alumnos en total, si van todos. | T20: Si | U20: No | V20: Martes 25/4 | W20: Si | X20: Si | Y20: No | Z20: No | AA20: Si | AB20: Si | AC20: No | AD20: No | AE20: No | AF20: No | AG20: Si | AH20: Si | AI20: No | AJ20: No | AK20: No | AL20: Si | AM20: Si | AN20: No | AO20: No | AP20: Si | AQ20: Si | AR20: No | AS20: No | AT20: Priorizamos primero la charla de 9.30; y la de 11.30 en este último caso de no ser posible, nos anotamos en arte matemático, taller o visita guiada. Podemos quedarnos hasta las 12.45 aprox.
A21: 45003.656 | B21: rodrigog.diaz@bue.edu.ar | C21: INSTITUTO INMACULADA CONCEPCIÓN A-86 | D21: 020122500 | E21: 1. Liceos / Normales / Colegios / Institutos orientados en ciencias naturales y/o exactas | F21: Informática | G21: Privada | H21: RODRIGO DIAZ | I21: NAZARENO AGUIRRE | J21: MARIANA CHIESA | K21: rodrigog.diaz@bue.edu.ar | L21: CABA | M21: Almagro | N21: 35 | O21: 5º Secundaria (Prov.) / 4º Media (CABA) | P21: 3 | Q21: 3 | R21: 30 | S21: Corresponde a otra división de la orientación | T21: Si | U21: Si | V21: Martes 25/4 | W21: Si | X21: Si | Y21: Si | Z21: Si | AA21: Si | AB21: Si | AC21: Si | AD21: Si | AE21: Si | AF21: Si | AG21: Si | AH21: Si | AI21: Si | AJ21: Si | AK21: Si | AL21: Si | AM21: Si | AN21: Si | AO21: Si | AP21: Si | AQ21: Si | AR21: Si | AS21: Si | AT21: Importante porcentaje de alumnos cursando UBA XXI en carreras afines.
A22: 45003.653 | B22: rodrigog.diaz@bue.edu.ar | C22: INSTITUTO INMACULADA CONCEPCIÓN A-86 | D22: 020122500 | E22: 2. Técnicas en computación, electrónica, informática | F22: Informática | G22: Privada | H22: RODRIGO GASTÓN DÍAZ | I22: MARIANA CHIESA | J22: NAZARENO AGUIRRE | K22: rodrigog.diaz@bue.edu.ar | L22: CABA | M22: Almagro | N22: 35 | O22: 5º Secundaria (Prov.) / 4º Media (CABA) | P22: 3 | Q22: 3 | R22: 30 | T22: Si | U22: Si | V22: Martes 25/4 | W22: Si | X22: Si | Y22: Si | Z22: Si | AA22: Si | AB22: Si | AC22: Si | AD22: Si | AE22: Si | AF22: Si | AG22: Si | AH22: Si | AI22: Si | AJ22: Si | AK22: Si | AL22: Si | AM22: Si | AN22: Si | AO22: Si | AP22: Si | AQ22: Si | AR22: Si | AS22: Si | AT22: Importante porcentaje de alumnos cursando UBA XXI en carreras afines a la temática.
A23: 45000.738 | B23: silveiga@yahoo.com.ar | C23: ENS Nº 4 ESTANISLAO ZEBALLOS | D23: 020129700 | E23: 1. Liceos / Normales / Colegios / Institutos orientados en ciencias naturales y/o exactas | F23: Matemática y física | G23: Estatal | H23: Silvia Ana Veiga | I23: Gisela Serrano | J23: Mónica Sivila | K23: silveiga@yahoo.com.ar | L23: CABA | M23: Caballito | N23: 23 | O23: 6º Secundaria (Prov.) / 5º Media (CABA) | P23: 4 | Q23: 4 | R23: 50 | S23: Vamos a la semana de la Matemática todos los años con nuestros 5º bach matemática y Física | T23: Si | U23: No | V23: Martes 25/4 | W23: Si | X23: No | Y23: No | Z23: No | AA23: Si | AB23: No | AC23: No | AD23: No | AE23: No | AF23: No | AG23: No | AH23: Si | AI23: No | AJ23: No | AK23: No | AL23: No | AM23: No | AN23: No | AO23: No | AP23: No | AQ23: No | AR23: No | AS23: No | AT23: Vamos con los chicos de 5º orientación Matemática y Física todos los años desde que comenzó la semana de la Matemática.
A24: 45000.835 | B24: Anabella.caceres@bue.edu.ar | C24: Escuela Normal Superior n5 "Martin Miguel de Güemes" | D24: 020132800 | E24: 1. Liceos / Normales / Colegios / Institutos orientados en ciencias naturales y/o exactas | F24: Matematica y Fisica | G24: Estatal | H24: A. Carolina Cáceres | I24: Lorena Paniagua | J24: Gustavo Catuara | K24: Anabella.caceres@bue.edu.ar | L24: CABA | M24: Barracas | N24: 15 | O24: 6º Secundaria (Prov.) / 5º Media (CABA) | P24: 3 | Q24: 3 | R24: 30 | T24: Si | U24: No | V24: Martes 25/4 | W24: Si | X24: No | Y24: No | Z24: No | AA24: No | AB24: Si | AC24: Si | AD24: No | AE24: No | AH24: Si | AL24: Si | AR24: Si
A25: 45000.84 | B25: Anabella.caceres@bue.edu.ar | C25: Escuela Normal Superior n5 " Martin Miguel de Güemes" | D25: 020132800 | E25: 1. Liceos / Normales / Colegios / Institutos orientados en ciencias naturales y/o exactas | F25: Matematica y Fisica | G25: Estatal | H25: A. Carolina Cáceres | I25: Lorena Paniagua | J25: Gustavo Catuara | K25: Anabella.caceres@bue.edu.ar | L25: CABA | M25: Barracas | N25: 16 | O25: 5º Secundaria (Prov.) / 4º Media (CABA) | P25: 3 | Q25: 3 | R25: 30 | T25: Si | U25: No | V25: Martes 25/4 | W25: Si | X25: No | Y25: No | Z25: No | AA25: Si | AB25: No | AC25: No | AD25: No | AE25: No | AF25: No | AG25: No | AH25: Si | AI25: No | AJ25: No | AK25: No | AL25: No | AM25: No | AN25: Si | AO25: No | AP25: No | AQ25: No | AR25: Si | AS25: No
A26: 45000.824 | B26: d.ana.gomez@sanrafael.esc.edu.ar | C26: Instituto San Rafael (A-120) | D26: 020133700 | E26: 1. Liceos / Normales / Colegios / Institutos orientados en ciencias naturales y/o exactas | F26: Administración de empresas | G26: Privada | H26: Ana Paula Gómez Tascón | I26: Franco Luciano Mazzoli | K26: d.ana.gomez@sanrafael.esc.edu.ar | L26: CABA | M26: Villa Devoto | N26: 34 | O26: 4º Secundaria (Prov:) / 3º Media (CABA) | P26: 3 | Q26: 1 | R26: 15 | T26: Si | U26: No | V26: Martes 25/4 | W26: Si | X26: Si | Y26: No | Z26: No | AA26: No | AB26: No | AC26: No | AD26: No | AE26: No | AF26: No | AG26: Si | AH26: No | AI26: No | AJ26: No | AK26: No | AL26: No | AM26: No | AN26: No | AO26: No | AP26: No | AQ26: No | AR26: No | AS26: No | AT26: Consideré q cada actividad dura una hora. Por ello, me anoté con este fixture: 9:30 charla de redes/ 10:30 taller del hacer matemático / 11:30 charla de calculadora
A27: 45000.831 | B27: d.ana.gomez@sanrafael.esc.edu.ar | C27: Instituto San Rafael (A-120) | D27: 020133700 | E27: 1. Liceos / Normales / Colegios / Institutos orientados en ciencias naturales y/o exactas | F27: Ciencias Naturales | G27: Privada | H27: Ana Paula Gómez Tascón | I27: Franco Luciano Mazzoli | K27: d.ana.gomez@sanrafael.esc.edu.ar | L27: CABA | M27: Villa Devoto | N27: 34 | O27: 4º Secundaria (Prov:) / 3º Media (CABA) | P27: 3 | Q27: 1 | R27: 15 | T27: Si | U27: No | V27: Martes 25/4 | W27: Si | X27: Si | Y27: No | Z27: No | AA27: No | AB27: No | AC27: No | AD27: No | AE27: No | AF27: No | AG27: Si | AH27: No | AI27: No | AJ27: No | AK27: No | AL27: No | AM27: No | AN27: No | AO27: No | AP27: No | AQ27: No | AR27: No | AS27: No
A28: 45001.784 | B28: andreoniraquel@institutourquiza.edu.ar | C28: Instituto General Justo José de Urquiza A 40 | D28: 020134800 | E28: 3. Técnicas en administración de empresas, administración de las organizaciones, servicios turísticos, multimedios | F28: Economía y administración / Comunicación | G28: Privada | H28: Raquel Andreoni | I28: Micaela Barbalace | J28: Mercedes González | K28: andreoniraquel@institutourquiza.edu.ar | L28: CABA | M28: Caballito | N28: 40 | O28: 5º Secundaria (Prov.) / 4º Media (CABA) | P28: 5 | Q28: 4 | R28: 5 | T28: Si | U28: No | V28: Martes 25/4 | W28: No | X28: No | Y28: No | Z28: Si | AA28: No | AB28: No | AC28: No | AD28: No | AE28: No | AF28: No | AG28: No | AH28: No | AI28: No | AJ28: No | AK28: No | AL28: Si | AM28: No | AN28: No | AO28: No | AP28: No | AQ28: No | AR28: No | AS28: No
